Workbook

Sheet LEEME
A1: Plantilla base · Dinámica RI, equivalencias y salones
A2: Llena las hojas en este archivo y después se integran al simulador HTML. Los nombres de hojas y columnas deben conservarse.
A4: Hoja | B4: Para qué sirve | C4: Obligatoria
A5: base_ni_ri_2030_2040 | B5: Trayectoria base editable de NI, RI y MT por año, periodo, campus, nivel y modalidad. | C5: Sí
A6: equivalencias_promedio | B6: Promedio histórico de alumnos que cuentan como NI, pero entran académicamente a S2, S3, S4, etc. | C6: Sí
A7: tasas_avance | B7: Tasas por campus y nivel para mover alumnos entre semestres: S1→S2, S8→Egreso, S8→Rezago, etc. | C7: Sí
A8: presencialidad_semestre | B8: % de presencialidad o uso de salones por semestre académico. | C8: Sí
A9: distribucion_ri_semestre | B9: Distribución opcional de RI total entre semestres. Si no existe, se puede estimar con las tasas. | C9: Opcional
A10: catalogos | B10: Listas auxiliares para validación: periodos, niveles, modalidades y estados. | C10: No editar si no es necesario
A13: Concepto | B13: Definición
A14: NI total | B14: Alumno que cuenta como nuevo ingreso para captación. Puede entrar a S1 o por equivalencia a un semestre posterior.
A15: RI total | B15: Alumno de reingreso reportado en la base. En el cálculo interno se distribuye por semestre.
A16: Equivalencias | B16: No se suman adicional a la MT. Solo reubican parte de los NI al semestre académico correcto.
A17: Rezago | B17: Alumno que llegó al último semestre, pero no egresó en el corte y se mantiene activo por materias/trámites pendientes.
A18: MT | B18: Matrícula total = NI total + RI total.
A19: DEFAULT | B19: Si una tasa o configuración aplica para todos los campus, puedes usar campus = DEFAULT. Una fila específica por campus debe tener prioridad en el simulador.

Sheet catalogos
A1: Catálogos para validación
A2: Puedes agregar campus o modalidades si lo necesitas. No cambies los nombres principales de nivel/periodo/estado.
A4: campus | C4: nivel | E4: modalidad | G4: periodo | I4: semestres_prepa | K4: semestres_profesional | M4: estados_destino | O4: metodo_equivalencia | Q4: usa_salon
A5: DEFAULT | C5: Preparatoria | E5: Presencial | G5: AD | I5: S1 | K5: S1 | M5: S1 | O5: fijo | Q5: 1
A6: Institucional | C6: Profesional | E6: Híbrido | G6: EM | I6: S2 | K6: S2 | M6: S2 | O6: pct_sobre_ni | Q6: 0
A7: Aguascalientes | I7: S3 | K7: S3 | M7: S3
A8: Cancún | I8: S4 | K8: S4 | M8: S4
A9: Chihuahua | I9: S5 | K9: S5 | M9: S5
A10: Ciudad Juárez | I10: S6 | K10: S6 | M10: S6
A11: Cuautitlán Izcalli | I11: Rezago | K11: S7 | M11: S7
A12: Cuernavaca | K12: S8 | M12: S8
A13: Culiacán | K13: Rezago | M13: Rezago
A14: Cumbres | M14: Egreso
A15: Durango | M15: Baja
A16: Ferrería
A17: Guadalajara
A18: Guadalupe
A19: Hermosillo
A20: Laguna
A21: Las Torres
A22: Los Mochis
A23: Mazatlán
A24: Mérida
A25: Nuevo Laredo
A26: Obregón
A27: Puebla
... A38: Morelia

Sheet base_ni_ri_2030_2040
A1: Base NI / RI / MT 2030–2040
A2: Carga aquí la trayectoria base anual o por periodo. Esta base no es meta: es el punto de partida editable del simulador.
A4: anio | B4: periodo | C4: campus | D4: nivel | E4: modalidad | F4: ni_total | G4: ri_total | H4: mt_total | I4: validacion_mt | J4: comentario
A5: 2030 | B5: AD | C5: Aguascalientes | D5: Preparatoria | E5: Presencial | F5: 244.65 | G5: 426 | H5: =tbl_base_ni_ri[[#This Row],[ni_total]]+tbl_base_ni_ri[[#This Row],[ri_total]] -> 670.65 | I5: =IF(OR(F5="",G5="",H5=""),"",IF(ABS(H5-F5-G5)<0.01,"OK","Revisar MT")) -> OK | J5: Ejemplo: sustituir con dato base
A6: 2031 | B6: AD | C6: Aguascalientes | D6: Preparatoria | E6: Presencial | F6: 256.8825 | G6: 441 | H6: =tbl_base_ni_ri[[#This Row],[ni_total]]+tbl_base_ni_ri[[#This Row],[ri_total]] -> 697.8825 | I6: =IF(OR(F6="",G6="",H6=""),"",IF(ABS(H6-F6-G6)<0.01,"OK","Revisar MT")) -> OK | J6: Ejemplo: sustituir con dato base
A7: 2032 | B7: AD | C7: Aguascalientes | D7: Preparatoria | E7: Presencial | F7: 269.72663 | G7: 456 | H7: =tbl_base_ni_ri[[#This Row],[ni_total]]+tbl_base_ni_ri[[#This Row],[ri_total]] -> 725.72663 | I7: =IF(OR(F7="",G7="",H7=""),"",IF(ABS(H7-F7-G7)<0.01,"OK","Revisar MT")) -> OK | J7: Ejemplo: sustituir con dato base
A8: 2033 | B8: AD | C8: Aguascalientes | D8: Preparatoria | E8: Presencial | F8: 283.21296 | G8: 479 | H8: =tbl_base_ni_ri[[#This Row],[ni_total]]+tbl_base_ni_ri[[#This Row],[ri_total]] -> 762.21296 | I8: =IF(OR(F8="",G8="",H8=""),"",IF(ABS(H8-F8-G8)<0.01,"OK","Revisar MT")) -> OK | J8: Ejemplo: sustituir con dato base
A9: 2034 | B9: AD | C9: Aguascalientes | D9: Preparatoria | E9: Presencial | F9: 291.70934 | G9: 506 | H9: =tbl_base_ni_ri[[#This Row],[ni_total]]+tbl_base_ni_ri[[#This Row],[ri_total]] -> 797.70934 | I9: =IF(OR(F9="",G9="",H9=""),"",IF(ABS(H9-F9-G9)<0.01,"OK","Revisar MT")) -> OK | J9: Ejemplo: sustituir con dato base
A10: 2035 | B10: AD | C10: Aguascalientes | D10: Preparatoria | E10: Presencial | F10: 300.46063 | G10: 536 | H10: =tbl_base_ni_ri[[#This Row],[ni_total]]+tbl_base_ni_ri[[#This Row],[ri_total]] -> 836.46063 | I10: =IF(OR(F10="",G10="",H10=""),"",IF(ABS(H10-F10-G10)<0.01,"OK","Revisar MT")) -> OK | J10: Ejemplo: sustituir con dato base
A11: 2036 | B11: AD | C11: Aguascalientes | D11: Preparatoria | E11: Presencial | F11: 309.47444 | G11: 572 | H11: =tbl_base_ni_ri[[#This Row],[ni_total]]+tbl_base_ni_ri[[#This Row],[ri_total]] -> 881.47444 | I11: =IF(OR(F11="",G11="",H11=""),"",IF(ABS(H11-F11-G11)<0.01,"OK","Revisar MT")) -> OK | J11: Ejemplo: sustituir con dato base
A12: 2037 | B12: AD | C12: Aguascalientes | D12: Preparatoria | E12: Presencial | F12: 319.06815 | G12: 594 | H12: =tbl_base_ni_ri[[#This Row],[ni_total]]+tbl_base_ni_ri[[#This Row],[ri_total]] -> 913.06815 | I12: =IF(OR(F12="",G12="",H12=""),"",IF(ABS(H12-F12-G12)<0.01,"OK","Revisar MT")) -> OK | J12: Ejemplo: sustituir con dato base
A13: 2038 | B13: AD | C13: Aguascalientes | D13: Preparatoria | E13: Presencial | F13: 328.95926 | G13: 618 | H13: =tbl_base_ni_ri[[#This Row],[ni_total]]+tbl_base_ni_ri[[#This Row],[ri_total]] -> 946.95926 | I13: =IF(OR(F13="",G13="",H13=""),"",IF(ABS(H13-F13-G13)<0.01,"OK","Revisar MT")) -> OK | J13: Ejemplo: sustituir con dato base
A14: 2039 | B14: AD | C14: Aguascalientes | D14: Preparatoria | E14: Presencial | F14: 339.157 | G14: 642 | H14: =tbl_base_ni_ri[[#This Row],[ni_total]]+tbl_base_ni_ri[[#This Row],[ri_total]] -> 981.157 | I14: =IF(OR(F14="",G14="",H14=""),"",IF(ABS(H14-F14-G14)<0.01,"OK","Revisar MT")) -> OK | J14: Ejemplo: sustituir con dato base
A15: 2040 | B15: AD | C15: Aguascalientes | D15: Preparatoria | E15: Presencial | F15: 349.67087 | G15: 667 | H15: =tbl_base_ni_ri[[#This Row],[ni_total]]+tbl_base_ni_ri[[#This Row],[ri_total]] -> 1016.6709 | I15: =IF(OR(F15="",G15="",H15=""),"",IF(ABS(H15-F15-G15)<0.01,"OK","Revisar MT")) -> OK | J15: Ejemplo: sustituir con dato base
A16: 2030 | B16: AD | C16: Cancún | D16: Preparatoria | E16: Presencial | F16: 344.41 | G16: 531 | H16: =tbl_base_ni_ri[[#This Row],[ni_total]]+tbl_base_ni_ri[[#This Row],[ri_total]] -> 875.41 | I16: =IF(OR(F16="",G16="",H16=""),"",IF(ABS(H16-F16-G16)<0.01,"OK","Revisar MT")) -> OK | J16: Ejemplo: sustituir con dato base
... A26: 2040 | B26: AD | C26: Cancún | D26: Preparatoria | E26: Presencial | F26: 380.44291 | G26: 612 | H26: =tbl_base_ni_ri[[#This Row],[ni_total]]+tbl_base_ni_ri[[#This Row],[ri_total]] -> 992.44291 | I26: =IF(OR(F26="",G26="",H26=""),"",IF(ABS(H26-F26-G26)<0.01,"OK","Revisar MT")) -> OK | J26: Ejemplo: sustituir con dato base
A27: 2030 | B27: AD | C27: Chihuahua | D27: Preparatoria | E27: Presencial | F27: 249.26 | G27: 300 | H27: =tbl_base_ni_ri[[#This Row],[ni_total]]+tbl_base_ni_ri[[#This Row],[ri_total]] -> 549.26 | I27: =IF(OR(F27="",G27="",H27=""),"",IF(ABS(H27-F27-G27)<0.01,"OK","Revisar MT")) -> OK
A28: 2031 | B28: AD | C28: Chihuahua | D28: Preparatoria | E28: Presencial | F28: 256.7378 | G28: 307 | H28: =tbl_base_ni_ri[[#This Row],[ni_total]]+tbl_base_ni_ri[[#This Row],[ri_total]] -> 563.7378 | I28: =IF(OR(F28="",G28="",H28=""),"",IF(ABS(H28-F28-G28)<0.01,"OK","Revisar MT")) -> OK
A29: 2032 | B29: AD | C29: Chihuahua | D29: Preparatoria | E29: Presencial | F29: 264.43993 | G29: 312 | H29: =tbl_base_ni_ri[[#This Row],[ni_total]]+tbl_base_ni_ri[[#This Row],[ri_total]] -> 576.43993 | I29: =IF(OR(F29="",G29="",H29=""),"",IF(ABS(H29-F29-G29)<0.01,"OK","Revisar MT")) -> OK
A30: 2033 | B30: AD | C30: Chihuahua | D30: Preparatoria | E30: Presencial | F30: 272.37313 | G30: 323 | H30: =tbl_base_ni_ri[[#This Row],[ni_total]]+tbl_base_ni_ri[[#This Row],[ri_total]] -> 595.37313 | I30: =IF(OR(F30="",G30="",H30=""),"",IF(ABS(H30-F30-G30)<0.01,"OK","Revisar MT")) -> OK
A31: 2034 | B31: AD | C31: Chihuahua | D31: Preparatoria | E31: Presencial | F31: 277.82059 | G31: 345 | H31: =tbl_base_ni_ri[[#This Row],[ni_total]]+tbl_base_ni_ri[[#This Row],[ri_total]] -> 622.82059 | I31: =IF(OR(F31="",G31="",H31=""),"",IF(ABS(H31-F31-G31)<0.01,"OK","Revisar MT")) -> OK
A32: 2035 | B32: AD | C32: Chihuahua | D32: Preparatoria | E32: Presencial | F32: 283.37701 | G32: 376 | H32: =tbl_base_ni_ri[[#This Row],[ni_total]]+tbl_base_ni_ri[[#This Row],[ri_total]] -> 659.37701 | I32: =IF(OR(F32="",G32="",H32=""),"",IF(ABS(H32-F32-G32)<0.01,"OK","Revisar MT")) -> OK
A33: 2036 | B33: AD | C33: Chihuahua | D33: Preparatoria | E33: Presencial | F33: 289.04455 | G33: 396 | H33: =tbl_base_ni_ri[[#This Row],[ni_total]]+tbl_base_ni_ri[[#This Row],[ri_total]] -> 685.04455 | I33: =IF(OR(F33="",G33="",H33=""),"",IF(ABS(H33-F33-G33)<0.01,"OK","Revisar MT")) -> OK
A34: 2037 | B34: AD | C34: Chihuahua | D34: Preparatoria | E34: Presencial | F34: 291.64595 | G34: 412 | H34: =tbl_base_ni_ri[[#This Row],[ni_total]]+tbl_base_ni_ri[[#This Row],[ri_total]] -> 703.64595 | I34: =IF(OR(F34="",G34="",H34=""),"",IF(ABS(H34-F34-G34)<0.01,"OK","Revisar MT")) -> OK
A35: 2038 | B35: AD | C35: Chihuahua | D35: Preparatoria | E35: Presencial | F35: 294.27076 | G35: 443 | H35: =tbl_base_ni_ri[[#This Row],[ni_total]]+tbl_base_ni_ri[[#This Row],[ri_total]] -> 737.27076 | I35: =IF(OR(F35="",G35="",H35=""),"",IF(ABS(H35-F35-G35)<0.01,"OK","Revisar MT")) -> OK
A36: 2039 | B36: AD | C36: Chihuahua | D36: Preparatoria | E36: Presencial | F36: 296.9192 | G36: 476 | H36: =tbl_base_ni_ri[[#This Row],[ni_total]]+tbl_base_ni_ri[[#This Row],[ri_total]] -> 772.9192 | I36: =IF(OR(F36="",G36="",H36=""),"",IF(ABS(H36-F36-G36)<0.01,"OK","Revisar MT")) -> OK
A37: 2040 | B37: AD | C37: Chihuahua | D37: Preparatoria | E37: Presencial | F37: 299.59147 | G37: 500 | H37: =tbl_base_ni_ri[[#This Row],[ni_total]]+tbl_base_ni_ri[[#This Row],[ri_total]] -> 799.59147 | I37: =IF(OR(F37="",G37="",H37=""),"",IF(ABS(H37-F37-G37)<0.01,"OK","Revisar MT")) -> OK
A38: 2030 | B38: AD | C38: Ciudad Juárez | D38: Preparatoria | E38: Presencial | F38: 342.023 | G38: 605 | H38: =tbl_base_ni_ri[[#This Row],[ni_total]]+tbl_base_ni_ri[[#This Row],[ri_total]] -> 947.023 | I38: =IF(OR(F38="",G38="",H38=""),"",IF(ABS(H38-F38-G38)<0.01,"OK","Revisar MT")) -> OK
... A697: 2040 | B697: AD | C697: Morelia | D697: Profesional | E697: Presencial | F697: 300 | G697: 553 | H697: =tbl_base_ni_ri[[#This Row],[ni_total]]+tbl_base_ni_ri[[#This Row],[ri_total]] -> 853 | I697: =IF(OR(F697="",G697="",H697=""),"",IF(ABS(H697-F697-G697)<0.01,"OK","Revisar MT")) -> OK
A698: 2030 | C698: Institucional | D698: Posgrado | F698: 4876 | G698: 12494 | H698: =tbl_base_ni_ri[[#This Row],[ni_total]]+tbl_base_ni_ri[[#This Row],[ri_total]] -> 17370 | I698: =IF(OR(F698="",G698="",H698=""),"",IF(ABS(H698-F698-G698)<0.01,"OK","Revisar MT")) -> OK
A699: 2031 | C699: Institucional | D699: Posgrado | F699: 4892 | G699: 12535 | H699: =tbl_base_ni_ri[[#This Row],[ni_total]]+tbl_base_ni_ri[[#This Row],[ri_total]] -> 17427 | I699: =IF(OR(F699="",G699="",H699=""),"",IF(ABS(H699-F699-G699)<0.01,"OK","Revisar MT")) -> OK
A700: 2032 | C700: Institucional | D700: Posgrado | F700: 5013 | G700: 12300 | H700: =tbl_base_ni_ri[[#This Row],[ni_total]]+tbl_base_ni_ri[[#This Row],[ri_total]] -> 17313 | I700: =IF(OR(F700="",G700="",H700=""),"",IF(ABS(H700-F700-G700)<0.01,"OK","Revisar MT")) -> OK
A701: 2033 | C701: Institucional | D701: Posgrado | F701: 5196 | G701: 12200 | H701: =tbl_base_ni_ri[[#This Row],[ni_total]]+tbl_base_ni_ri[[#This Row],[ri_total]] -> 17396 | I701: =IF(OR(F701="",G701="",H701=""),"",IF(ABS(H701-F701-G701)<0.01,"OK","Revisar MT")) -> OK
A702: 2034 | C702: Institucional | D702: Posgrado | F702: 5482 | G702: 12150 | H702: =tbl_base_ni_ri[[#This Row],[ni_total]]+tbl_base_ni_ri[[#This Row],[ri_total]] -> 17632 | I702: =IF(OR(F702="",G702="",H702=""),"",IF(ABS(H702-F702-G702)<0.01,"OK","Revisar MT")) -> OK
A703: 2035 | C703: Institucional | D703: Posgrado | F703: 5885 | G703: 12100 | H703: =tbl_base_ni_ri[[#This Row],[ni_total]]+tbl_base_ni_ri[[#This Row],[ri_total]] -> 17985 | I703: =IF(OR(F703="",G703="",H703=""),"",IF(ABS(H703-F703-G703)<0.01,"OK","Revisar MT")) -> OK
A704: 2036 | C704: Institucional | D704: Posgrado | F704: 6465 | G704: 12100 | H704: =tbl_base_ni_ri[[#This Row],[ni_total]]+tbl_base_ni_ri[[#This Row],[ri_total]] -> 18565 | I704: =IF(OR(F704="",G704="",H704=""),"",IF(ABS(H704-F704-G704)<0.01,"OK","Revisar MT")) -> OK
A705: 2037 | C705: Institucional | D705: Posgrado | F705: 7215 | G705: 12100 | H705: =tbl_base_ni_ri[[#This Row],[ni_total]]+tbl_base_ni_ri[[#This Row],[ri_total]] -> 19315 | I705: =IF(OR(F705="",G705="",H705=""),"",IF(ABS(H705-F705-G705)<0.01,"OK","Revisar MT")) -> OK
A706: 2038 | C706: Institucional | D706: Posgrado | F706: 8105 | G706: 12350 | H706: =tbl_base_ni_ri[[#This Row],[ni_total]]+tbl_base_ni_ri[[#This Row],[ri_total]] -> 20455 | I706: =IF(OR(F706="",G706="",H706=""),"",IF(ABS(H706-F706-G706)<0.01,"OK","Revisar MT")) -> OK
A707: 2039 | C707: Institucional | D707: Posgrado | F707: 9165 | G707: 12800 | H707: =tbl_base_ni_ri[[#This Row],[ni_total]]+tbl_base_ni_ri[[#This Row],[ri_total]] -> 21965 | I707: =IF(OR(F707="",G707="",H707=""),"",IF(ABS(H707-F707-G707)<0.01,"OK","Revisar MT")) -> OK
A708: 2040 | C708: Institucional | D708: Posgrado | F708: 10273 | G708: 13400 | H708: =tbl_base_ni_ri[[#This Row],[ni_total]]+tbl_base_ni_ri[[#This Row],[ri_total]] -> 23673 | I708: =IF(OR(F708="",G708="",H708=""),"",IF(ABS(H708-F708-G708)<0.01,"OK","Revisar MT")) -> OK
A709: 2030 | C709: Institucional | D709: Ejecutivo | F709: 2794 | G709: 11342 | H709: =tbl_base_ni_ri[[#This Row],[ni_total]]+tbl_base_ni_ri[[#This Row],[ri_total]] -> 14136 | I709: =IF(OR(F709="",G709="",H709=""),"",IF(ABS(H709-F709-G709)<0.01,"OK","Revisar MT")) -> OK
... A979: 2029 | C979: Institucional | D979: Ejecutivo | F979: 2602 | G979: 11098 | H979: =tbl_base_ni_ri[[#This Row],[ni_total]]+tbl_base_ni_ri[[#This Row],[ri_total]] -> 13700 | I979: =IF(OR(F979="",G979="",H979=""),"",IF(ABS(H979-F979-G979)<0.01,"OK","Revisar MT")) -> OK
A980: 2020 | C980: Aguascalientes | D980: Profesional | F980: 0 | G980: 0 | H980: 0 | I980: =IF(OR(F980="",G980="",H980=""),"",IF(ABS(H980-F980-G980)<0.01,"OK","Revisar MT")) -> OK
A981: 2021 | C981: Aguascalientes | D981: Profesional | F981: 0 | G981: 0 | H981: 0 | I981: =IF(OR(F981="",G981="",H981=""),"",IF(ABS(H981-F981-G981)<0.01,"OK","Revisar MT")) -> OK
A982: 2022 | C982: Aguascalientes | D982: Profesional | F982: 0 | G982: 0 | H982: 0 | I982: =IF(OR(F982="",G982="",H982=""),"",IF(ABS(H982-F982-G982)<0.01,"OK","Revisar MT")) -> OK
A983: 2023 | C983: Aguascalientes | D983: Profesional | F983: 0 | G983: 0 | H983: 0 | I983: =IF(OR(F983="",G983="",H983=""),"",IF(ABS(H983-F983-G983)<0.01,"OK","Revisar MT")) -> OK
A984: 2024 | C984: Aguascalientes | D984: Profesional | F984: 0 | G984: 0 | H984: 0 | I984: =IF(OR(F984="",G984="",H984=""),"",IF(ABS(H984-F984-G984)<0.01,"OK","Revisar MT")) -> OK
A985: 2025 | C985: Aguascalientes | D985: Profesional | F985: 0 | G985: 0 | H985: 0 | I985: =IF(OR(F985="",G985="",H985=""),"",IF(ABS(H985-F985-G985)<0.01,"OK","Revisar MT")) -> OK
A986: 2020 | C986: Cancún | D986: Profesional | F986: 123 | G986: 414 | H986: 537 | I986: =IF(OR(F986="",G986="",H986=""),"",IF(ABS(H986-F986-G986)<0.01,"OK","Revisar MT")) -> OK
A987: 2021 | C987: Cancún | D987: Profesional | F987: 103 | G987: 414 | H987: 517 | I987: =IF(OR(F987="",G987="",H987=""),"",IF(ABS(H987-F987-G987)<0.01,"OK","Revisar MT")) -> OK
A988: 2022 | C988: Cancún | D988: Profesional | F988: 157 | G988: 370 | H988: 527 | I988: =IF(OR(F988="",G988="",H988=""),"",IF(ABS(H988-F988-G988)<0.01,"OK","Revisar MT")) -> OK
A989: 2023 | C989: Cancún | D989: Profesional | F989: 134 | G989: 404 | H989: 538 | I989: =IF(OR(F989="",G989="",H989=""),"",IF(ABS(H989-F989-G989)<0.01,"OK","Revisar MT")) -> OK
A990: 2024 | C990: Cancún | D990: Profesional | F990: 113 | G990: 418 | H990: 531 | I990: =IF(OR(F990="",G990="",H990=""),"",IF(ABS(H990-F990-G990)<0.01,"OK","Revisar MT")) -> OK
A991: 2025 | C991: Cancún | D991: Profesional | F991: 115 | G991: 401 | H991: 516 | I991: =IF(OR(F991="",G991="",H991=""),"",IF(ABS(H991-F991-G991)<0.01,"OK","Revisar MT")) -> OK
... A1000: 2022 | C1000: Ciudad Juárez | D1000: Profesional | F1000: 124 | G1000: 383 | H1000: 507 | I1000: =IF(OR(F1000="",G1000="",H1000=""),"",IF(ABS(H1000-F1000-G1000)<0.01,"OK","Revisar MT")) -> OK
A1001: 2023 | C1001: Ciudad Juárez | D1001: Profesional | F1001: 105 | G1001: 389 | H1001: 494
A1002: 2024 | C1002: Ciudad Juárez | D1002: Profesional | F1002: 114 | G1002: 397 | H1002: 511
A1003: 2025 | C1003: Ciudad Juárez | D1003: Profesional | F1003: 98 | G1003: 397 | H1003: 495
A1004: 2020 | C1004: Cuautitlán Izcalli | D1004: Profesional | F1004: 158 | G1004: 522 | H1004: 680
A1005: 2021 | C1005: Cuautitlán Izcalli | D1005: Profesional | F1005: 175 | G1005: 530 | H1005: 705
A1006: 2022 | C1006: Cuautitlán Izcalli | D1006: Profesional | F1006: 234 | G1006: 573 | H1006: 807
A1007: 2023 | C1007: Cuautitlán Izcalli | D1007: Profesional | F1007: 235 | G1007: 620 | H1007: 855
A1008: 2024 | C1008: Cuautitlán Izcalli | D1008: Profesional | F1008: 247 | G1008: 667 | H1008: 914
A1009: 2025 | C1009: Cuautitlán Izcalli | D1009: Profesional | F1009: 256 | G1009: 724 | H1009: 980
A1010: 2020 | C1010: Cuernavaca | D1010: Profesional | F1010: 70 | G1010: 303 | H1010: 373
A1011: 2021 | C1011: Cuernavaca | D1011: Profesional | F1011: 62 | G1011: 281 | H1011: 343
A1012: 2022 | C1012: Cuernavaca | D1012: Profesional | F1012: 86 | G1012: 238 | H1012: 324
... A1357: 2025 | C1357: Morelia | D1357: Preparatoria | F1357: 229 | G1357: 147 | H1357: 376

Sheet equivalencias_promedio
A1: Equivalencias promedio histórico
A2: Alumnos que cuentan como NI, pero académicamente ingresan a un semestre distinto a S1. No se suman adicional a MT; solo reubican NI.
A4: campus | B4: nivel | C4: modalidad | D4: periodo | E4: semestre_ingreso | F4: equivalencias_promedio | G4: pct_sobre_ni | H4: metodo | I4: comentario
A5: DEFAULT | B5: Preparatoria | C5: Presencial | D5: AD | E5: S2 | F5: 0 | H5: fijo | I5: Ejemplo, cambia a promedio histórico
A6: DEFAULT | B6: Preparatoria | C6: Presencial | D6: AD | E6: S3 | F6: 0 | H6: fijo | I6: Ejemplo, cambia a promedio histórico
A7: DEFAULT | B7: Profesional | C7: Presencial | D7: AD | E7: S3 | F7: 0 | H7: fijo | I7: Ejemplo, cambia a promedio histórico
A8: DEFAULT | B8: Profesional | C8: Presencial | D8: AD | E8: S5 | F8: 0 | H8: fijo | I8: Ejemplo, cambia a promedio histórico
A9: Cancún | B9: Profesional | C9: Presencial | D9: AD | E9: S3 | G9: 0.05 | H9: pct_sobre_ni | I9: Ejemplo con porcentaje sobre NI

Sheet tasas_avance
A1: Tasas de avance / permanencia por campus
A2: Usa campus DEFAULT para tasa general. Si un campus tiene una tasa distinta, agrega una fila específica del campus.
A4: campus | B4: nivel | C4: modalidad | D4: periodo_origen | E4: estado_origen | F4: estado_destino | G4: tasa | H4: comentario
A5: DEFAULT | B5: Preparatoria | C5: Presencial | D5: AD | E5: S1 | F5: S2 | G5: 0.925
A6: DEFAULT | B6: Preparatoria | C6: Presencial | D6: AD | E6: S2 | F6: S3 | G6: 0.903
A7: DEFAULT | B7: Preparatoria | C7: Presencial | D7: AD | E7: S3 | F7: S4 | G7: 0.963
A8: DEFAULT | B8: Preparatoria | C8: Presencial | D8: AD | E8: S4 | F8: S5 | G8: 0.911
A9: DEFAULT | B9: Preparatoria | C9: Presencial | D9: AD | E9: S5 | F9: S6 | G9: 0.976
A10: DEFAULT | B10: Preparatoria | C10: Presencial | D10: AD | E10: S6 | F10: Egreso | G10: 0.981
A11: DEFAULT | B11: Preparatoria | C11: Presencial | D11: AD | E11: S6 | F11: Rezago | G11: 0.019
A12: DEFAULT | B12: Preparatoria | C12: Presencial | D12: AD | E12: Rezago | F12: Egreso | G12: 0.8 | H12: Ajustar con histórico
A13: DEFAULT | B13: Preparatoria | C13: Presencial | D13: AD | E13: Rezago | F13: Rezago | G13: 0.2 | H13: Ajustar con histórico
A14: DEFAULT | B14: Profesional | C14: Presencial | D14: AD | E14: S1 | F14: S2 | G14: 0.895
A15: DEFAULT | B15: Profesional | C15: Presencial | D15: AD | E15: S2 | F15: S3 | G15: 0.928
A16: DEFAULT | B16: Profesional | C16: Presencial | D16: AD | E16: S3 | F16: S4 | G16: 0.958
A17: DEFAULT | B17: Profesional | C17: Presencial | D17: AD | E17: S4 | F17: S5 | G17: 0.968
A18: DEFAULT | B18: Profesional | C18: Presencial | D18: AD | E18: S5 | F18: S6 | G18: 0.975
A19: DEFAULT | B19: Profesional | C19: Presencial | D19: AD | E19: S6 | F19: S7 | G19: 0.977
A20: DEFAULT | B20: Profesional | C20: Presencial | D20: AD | E20: S7 | F20: S8 | G20: 0.979
A21: DEFAULT | B21: Profesional | C21: Presencial | D21: AD | E21: S8 | F21: Egreso | G21: 0.71
A22: DEFAULT | B22: Profesional | C22: Presencial | D22: AD | E22: S8 | F22: Rezago | G22: 0.29
A23: DEFAULT | B23: Profesional | C23: Presencial | D23: AD | E23: Rezago | F23: Egreso | G23: 0.4 | H23: Ajustar con histórico
A24: DEFAULT | B24: Profesional | C24: Presencial | D24: AD | E24: Rezago | F24: Rezago | G24: 0.6 | H24: Ajustar con histórico

Sheet presencialidad_semestre
A1: % presencialidad por semestre
A2: Esta sería la parte editable del simulador para decidir qué semestres usan salones y con qué intensidad.
A4: campus | B4: nivel | C4: modalidad | D4: semestre | E4: pct_presencialidad | F4: usa_salon | G4: comentario
A5: DEFAULT | B5: Preparatoria | C5: Presencial | D5: S1 | E5: 1 | F5: 1
A6: DEFAULT | B6: Preparatoria | C6: Presencial | D6: S2 | E6: 1 | F6: 1
A7: DEFAULT | B7: Preparatoria | C7: Presencial | D7: S3 | E7: 1 | F7: 1
A8: DEFAULT | B8: Preparatoria | C8: Presencial | D8: S4 | E8: 1 | F8: 1
A9: DEFAULT | B9: Preparatoria | C9: Presencial | D9: S5 | E9: 1 | F9: 1
A10: DEFAULT | B10: Preparatoria | C10: Presencial | D10: S6 | E10: 1 | F10: 1
A11: DEFAULT | B11: Preparatoria | C11: Presencial | D11: Rezago | E11: 0.2 | F11: 1
A12: DEFAULT | B12: Profesional | C12: Presencial | D12: S1 | E12: 1 | F12: 1
A13: DEFAULT | B13: Profesional | C13: Presencial | D13: S2 | E13: 1 | F13: 1
A14: DEFAULT | B14: Profesional | C14: Presencial | D14: S3 | E14: 1 | F14: 1
A15: DEFAULT | B15: Profesional | C15: Presencial | D15: S4 | E15: 1 | F15: 1
A16: DEFAULT | B16: Profesional | C16: Presencial | D16: S5 | E16: 0.7 | F16: 1
... A20: DEFAULT | B20: Profesional | C20: Presencial | D20: Rezago | E20: 0.2 | F20: 1

Sheet distribucion_ri_semestre
A1: Distribución de RI por semestre
A2: Hoja opcional. Sirve para repartir el RI total base entre semestres antes de calcular salones. Los porcentajes por campus/nivel/periodo deben sumar 100%.
A4: campus | B4: nivel | C4: modalidad | D4: periodo | E4: semestre | F4: pct_ri | G4: comentario
A5: Cancún | B5: Profesional | C5: Presencial | D5: AD | E5: S1 | F5: 0.24224806 | G5: Ejemplo, ajustar con histórico
A6: Cancún | B6: Profesional | C6: Presencial | D6: AD | E6: S2 | F6: 0 | G6: Ejemplo, ajustar con histórico
A7: Cancún | B7: Profesional | C7: Presencial | D7: AD | E7: S3 | F7: 0.22093023 | G7: Ejemplo, ajustar con histórico
A8: Cancún | B8: Profesional | C8: Presencial | D8: AD | E8: S4 | F8: 0.011627907 | G8: Ejemplo, ajustar con histórico
A9: Cancún | B9: Profesional | C9: Presencial | D9: AD | E9: S5 | F9: 0.25193798 | G9: Ejemplo, ajustar con histórico
A10: Cancún | B10: Profesional | C10: Presencial | D10: AD | E10: S6 | F10: 0.01744186 | G10: Ejemplo, ajustar con histórico
A11: Cancún | B11: Profesional | C11: Presencial | D11: AD | E11: S7 | F11: 0.16666667 | G11: Ejemplo, ajustar con histórico
A12: Cancún | B12: Profesional | C12: Presencial | D12: AD | E12: S8 | F12: 0.089147287 | G12: Ejemplo, ajustar con histórico
A13: Chihuahua | B13: Profesional | C13: Presencial | D13: AD | E13: S1 | F13: 0.27131783 | G13: Ejemplo, ajustar con histórico
A14: Chihuahua | B14: Profesional | C14: Presencial | D14: AD | E14: S2 | F14: 0 | G14: Ejemplo, ajustar con histórico
A15: Chihuahua | B15: Profesional | C15: Presencial | D15: AD | E15: S3 | F15: 0.23643411 | G15: Ejemplo, ajustar con histórico
A16: Chihuahua | B16: Profesional | C16: Presencial | D16: AD | E16: S4 | F16: 0.01744186 | G16: Ejemplo, ajustar con histórico
... A18: Chihuahua | B18: Profesional | C18: Presencial | D18: AD | E18: S6 | F18: 0.01744186 | G18: Ejemplo, ajustar con histórico
A19: Chihuahua | B19: Profesional | C19: Presencial | D19: AD | E19: S7 | F19: 0.26356589
A20: Chihuahua | B20: Profesional | C20: Presencial | D20: AD | E20: S8 | F20: 0.075581395
A21: Ciudad Juárez | B21: Profesional | C21: Presencial | D21: AD | E21: S1 | F21: 0.23643411
A22: Ciudad Juárez | B22: Profesional | C22: Presencial | D22: AD | E22: S2 | F22: 0.0019379845
A23: Ciudad Juárez | B23: Profesional | C23: Presencial | D23: AD | E23: S3 | F23: 0.22674419
A24: Ciudad Juárez | B24: Profesional | C24: Presencial | D24: AD | E24: S4 | F24: 0.031007752
A25: Ciudad Juárez | B25: Profesional | C25: Presencial | D25: AD | E25: S5 | F25: 0.19573643
A26: Ciudad Juárez | B26: Profesional | C26: Presencial | D26: AD | E26: S6 | F26: 0.040697674
A27: Ciudad Juárez | B27: Profesional | C27: Presencial | D27: AD | E27: S7 | F27: 0.15310078
A28: Ciudad Juárez | B28: Profesional | C28: Presencial | D28: AD | E28: S8 | F28: 0.073643411
A29: Cuautitlán Izcalli | B29: Profesional | C29: Presencial | D29: AD | E29: S1 | F29: 0.55813953
A30: Cuautitlán Izcalli | B30: Profesional | C30: Presencial | D30: AD | E30: S2 | F30: 0.0019379845
... A244: Zapopan | B244: Profesional | C244: Presencial | D244: AD | E244: S8 | F244: 0.046511628

Sheet validaciones
A1: Validaciones rápidas
A2: Estas fórmulas ayudan a revisar si algunas hojas tienen inconsistencias básicas.
A4: Validación | B4: Resultado esperado | C4: Qué revisar
A5: MT = NI + RI en base_ni_ri_2030_2040 | B5: validacion_mt debe decir OK | C5: Si aparece Revisar MT, corrige mt_total o deja que sea NI + RI.
A6: Distribución RI por semestre | B6: pct_ri debe sumar 100% por campus/nivel/periodo | C6: Revisar manualmente o con tabla dinámica si cargas muchos campus.
A7: Tasas desde un mismo estado | B7: Suma de destinos por origen debería ser <= 100% | C7: Ejemplo: S8→Egreso + S8→Rezago.
A8: Equivalencias promedio | B8: No deben ser mayores al NI total del periodo | C8: Si usas fijo y el NI proyectado baja, revisar el promedio.

Sheet parametros_multicampus
A1: Módulo multicampus / flex / presencial | E1: Nota v43
A2: La clasificación se hace por grupo académico estimado. En S6-S7 primero divide por la cantidad de rutas de enfoque de la hoja rutas_por_programa. | E2: Ruta redondeada | F2: Ejemplo: 21 alumnos / 6 rutas = 4 por ruta.
A3: parametro | B3: valor | C3: descripcion | E3: Clasificación | F3: Con 4 alumnos cae como Multicampus, no Mixto.
A4: min_multicampus | B4: 4 | C4: Menor a este valor se clasifica como Flex. | E4: Presenciales | F4: Se reportan total, mañana y tarde según configuración de Salones.
A5: max_multicampus | B5: 11 | C5: De min_multicampus a este valor se clasifica como Multicampus. | E5: Parámetros sugeridos | F5: ruta_semestre_min=6, ruta_semestre_max=7
A6: capacidad_salon_flex | B6: 4 | C6: Capacidad en alumnos del espacio/salón flex.
A7: capacidad_salon_multicampus | B7: 12 | C7: Capacidad en alumnos del espacio/salón multicampus. | E7: Nota v44
A8: capacidad_salon_normal | B8: 25 | C8: Capacidad en alumnos del salón presencial normal. | E8: Salones presenciales | F8: Se calculan agregando alumnos y dividiendo entre 25.
A9: semestre_min | B9: 1 | C9: Primer semestre a revisar. | E9: Antes | F9: Se sumaban salones por grupo y eso podía inflar mañana/tarde.
A10: semestre_max | B10: 8 | C10: Último semestre a revisar. | E10: Comparación | F10: Pres. mañana debe ser comparable con la lógica de Salones.
A11: ruta_semestre_min | B11: 6 | C11: Desde este semestre se divide entre rutas de enfoque.
A12: ruta_semestre_max | B12: 7 | C12: Hasta este semestre se divide entre rutas de enfoque. | E12: Nota v45
A13: umbral_salones_normales | B13: 10 | C13: Salones presenciales mínimos para sugerir bloque/edificio. | E13: S1 | F13: Se reparte desde NI Profesional del año.
E14: S2-S8 | F14: Se reparten desde RI Profesional usando la distribución de semestre normalizada.
E15: Validación | F15: La pestaña Multicampus muestra NI S1 y RI S2-S8 para verificar cuadratura.
E16: Ejemplo | F16: Si Campus dice NI Prof 2030 = 191, S1 debe sumar aprox. 191.
E18: Nota v46
E19: Base 2030-2040 | F19: El HTML respeta exactamente NI, RI y MT de la hoja base.
E20: S1 | F20: Se reparte con NI Profesional.
E21: S2-S8 | F21: Se reparte con RI Profesional y debe cuadrar al total RI.
E22: S8 | F22: Cuenta como RI en validación, pero NO genera Flex/Multicampus/Presencial.
E23: Evaluación de espacios | F23: Solo S1-S7.
E24: % programa | F24: Se normaliza a 100% para repartir todos los NI/RI entre los programas cargados.
E26: Nota v47
E27: S8 | F27: Ya no aparece en el desglose por programa ni genera espacios.
E28: Tabla de programas | F28: Ya no muestra etiquetas NI/RI dentro de las celdas.
E29: Cuadre Salones | F29: Pres. mañana en Multicampus usa el mismo cálculo de la pestaña Salones.
E30: Carrera nueva | F30: Se puede simular desde el HTML. Se suma a NI, RI y MT de Profesional.
E31: RI carrera nueva | F31: Se estima con el RI/NI del campus en cada año.
E32: Rutas carrera nueva | F32: Se capturan en el simulador para S6 y S7.
E33: Prioridad | F33: Los espacios multicampus/flex son complemento; salones presenciales mañana cuadra con Salones.
E35: Nota v48
E36: Tasas 2030-2040 | F36: Vuelven a mostrarse. Si no se editan, se respeta la base del Excel.
E37: Si se editan | F37: Recalcula desde el año previo usando la tasa capturada.
E38: Validación removida | F38: Se quitó la tabla de validación de Multicampus.
E39: RI S2-S8 | F39: El reparto base se fuerza a cuadrar con RI Profesional.
E40: S8 | F40: No aparece en desglose de programas ni genera espacios.
E41: Salones | F41: Profesional en Salones y Multicampus excluye S8 y usa el mismo total.
E42: Por semestre | F42: Los salones mañana/tarde se asignan por peso para que sumen exactamente el total anual.
E44: Nota v49
E45: Fix Multicampus | F45: Se reconstruyó la lógica final sin recursión; vuelve a cargar años y tablas.
E46: Tasas 2030-2040 | F46: Se muestran. Si no se tocan, respeta la base del Excel.
E47: Si se editan | F47: Recalcula desde el año previo con la tasa capturada.
E48: RI S2-S8 | F48: Se fuerza a cuadrar con RI Profesional del Campus.
E49: S8 | F49: No aparece en desglose ni genera espacios.
E50: Salones | F50: Pres. mañana en Multicampus usa el mismo total de la pestaña Salones.
E51: Validación | F51: Se eliminó la tabla de validación para evitar confusión por redondeos.

Sheet Maps bimestral
A1: Base de troncalidad por programa y certificado
A3: Programa | B3: Certificado | C3: Tipo de certificado | D3: Secuencia | E3: Numero de Semestre | F3: Observaciones
A4: Licenciatura en Administración de Empresas | B4: Transformación digital | C4: Troncal | D4: 1 | E4: 1 | F4: Reemplazar ejemplos por datos reales. La llave principal será Programa + Certificado + Numero de Semestre.
A5: Licenciatura en Administración de Empresas | B5: Fundamentos de programación | D5: 3 | E5: 1
A6: Licenciatura en Administración de Empresas | B6: Estrategia y ventaja competitiva | D6: 2 | E6: 1
A7: Licenciatura en Administración de Empresas | B7: Certificado de Lengua Extranjera 1 | D7: 4 | E7: 1
A8: Licenciatura en Administración de Empresas | B8: Emprendimiento | D8: 6 | E8: 2
A9: Licenciatura en Administración de Empresas | B9: Big Data Analytics | D9: 7 | E9: 2
A10: Licenciatura en Administración de Empresas | B10: Administración de operaciones | D10: 5 | E10: 2
A11: Licenciatura en Administración de Empresas | B11: Certificado de Lengua Extranjera 2 | D11: 8 | E11: 2
A12: Licenciatura en Administración de Empresas | B12: Mercadotecnia estratégica | D12: 9 | E12: 3
A13: Licenciatura en Administración de Empresas | B13: Derecho corporativo | D13: 11 | E13: 3
A14: Licenciatura en Administración de Empresas | B14: Administración del talento humano | D14: 10 | E14: 3
A15: Licenciatura en Administración de Empresas | B15: Certificado de Lengua Extranjera 3 | D15: 12 | E15: 3
A16: Licenciatura en Administración de Empresas | B16: Mercadotecnia digital | D16: 15 | E16: 4
... A339: Licenciatura en Mercadotecnia | B339: Certificado de Lengua Extranjera 7 | D339: 28 | E339: 7

Sheet Portafolio Actual
A1: Portafolio actual de programas por campus
A3: Campus | B3: Nivel | C3: Programa | D3: Modalidad | E3: Activo | F3: Observaciones
A4: Cancún | B4: Profesional | C4: Licenciatura en Diseño Gráfico y Animación | D4: Presencial | E4: SI | F4: Capturar un renglón por campus-programa activo.
A5: Cancún | B5: Profesional | C5: Licenciatura en Derecho | D5: Presencial | E5: SI
A6: Cancún | B6: Profesional | C6: Licenciatura en Ingeniería en Desarrollo de Software | D6: Presencial | E6: SI
A7: Cancún | B7: Profesional | C7: Licenciatura en Mercadotecnia | D7: Presencial | E7: SI
A8: Cancún | B8: Profesional | C8: Licenciatura en Administración de Empresas | D8: Presencial | E8: SI
A9: Cancún | B9: Profesional | C9: Licenciatura en Comercio y Negocios Internacionales | D9: Presencial | E9: SI
A10: Cancún | B10: Profesional | C10: Licenciatura en Nutrición | D10: Presencial | E10: SI
A11: Chihuahua | B11: Profesional | C11: Licenciatura en Diseño Gráfico y Animación | D11: Presencial | E11: SI
A12: Chihuahua | B12: Profesional | C12: Licenciatura en Derecho | D12: Presencial | E12: SI
A13: Chihuahua | B13: Profesional | C13: Licenciatura en Ingeniería en Desarrollo de Software | D13: Presencial | E13: SI
A14: Chihuahua | B14: Profesional | C14: Licenciatura en Mercadotecnia | D14: Presencial | E14: SI
A15: Chihuahua | B15: Profesional | C15: Licenciatura en Creación y Desarrollo de Empresas | D15: Presencial | E15: SI
A16: Chihuahua | B16: Profesional | C16: Licenciatura en Comercio y Negocios Internacionales | D16: Presencial | E16: SI
... A232: Zacatecas | B232: Profesional | C232: Licenciatura en Ingeniería Industrial | D232: Presencial | E232: SI

Sheet Rutas enfoque
A1: Rutas enfoque y reutilización de certificados | H1: Nota v42
H2: La división S6-S7 usa primero rutas_por_programa. | I2: Esta hoja queda como respaldo/detalle de certificados.
A3: Programa | B3: Ruta | C3: Certificado | D3: Numero de certificado | E3: Reutilizacion de certificados | F3: Observaciones | H3: Si rutas_por_programa dice 4 rutas: | I3: se divide entre 4 aunque aquí no estén todas las rutas detalladas.
A4: Licenciatura en Mercadotecnia | B4: Estrategia Publicitaria | C4: Diseño de productos | D4: Optativa 1 | E4: 1 | F4: Reutilización = número de rutas/programas donde se repite el certificado. | H4: Troncalidad: | I4: Maps bimestral sigue ayudando a agrupar certificados compartidos.
A5: Licenciatura en Mercadotecnia | B5: Estrategia Publicitaria | C5: UX/UI | D5: Optativa 5 | E5: 1
A6: Licenciatura en Mercadotecnia | B6: Estrategia Publicitaria | C6: Sociología del consumo | D6: Optativa 3 | E6: 1
A7: Licenciatura en Mercadotecnia | B7: Estrategia Publicitaria | C7: Publicidad | D7: Optativa 2 | E7: 1
A8: Licenciatura en Mercadotecnia | B8: Estrategia Publicitaria | C8: Diseño para medios digitales | D8: Optativa 6 | E8: 1
A9: Licenciatura en Mercadotecnia | B9: Estrategia Publicitaria | C9: Comercio detallista | D9: Optativa 4 | E9: 1
A10: Licenciatura en Mercadotecnia | B10: Estrategías de Mercadotecnia en Buscadores y Comercio Electrónico | C10: Analítica digital | D10: Optativa 6 | E10: 2
A11: Licenciatura en Mercadotecnia | B11: Estrategías de Mercadotecnia en Buscadores y Comercio Electrónico | C11: Serch engine optimization (SEO) | D11: Optativa 1 | E11: 1
A12: Licenciatura en Mercadotecnia | B12: Estrategías de Mercadotecnia en Buscadores y Comercio Electrónico | C12: Serch engine marketin (SEM) | D12: Optativa 2 | E12: 1
A13: Licenciatura en Mercadotecnia | B13: Estrategías de Mercadotecnia en Buscadores y Comercio Electrónico | C13: Marketing automation | D13: Optativa 3 | E13: 1
A14: Licenciatura en Mercadotecnia | B14: Estrategías de Mercadotecnia en Buscadores y Comercio Electrónico | C14: Growth hacking | D14: Optativa 4 | E14: 1
A15: Licenciatura en Mercadotecnia | B15: Estrategías de Mercadotecnia en Buscadores y Comercio Electrónico | C15: Comercio electrónico | D15: Optativa 5 | E15: 1
A16: Licenciatura en Mercadotecnia | B16: Gestión de ventas estratégicas | C16: Servicios y experiencia al cliente | D16: Optativa 5 | E16: 3
... A272: Licenciatura en Administración de Empresas | B272: Turismo | C272: Gestión de alimentos y Bebidas | D272: Optativa 3 | E272: 1

Sheet aportacion_ni_programa
A1: Aportación de NI por programa para repartir MT Profesional | J1: Nota v40
J2: Con solo 2026 basta. | K2: El simulador usa NI_programa / NI_total_campus por programa.
A3: Campus | B3: Periodo | C3: Nivel | D3: Programa | E3: Anio | F3: NI_programa | G3: NI_total_campus | H3: pct_aportacion | I3: Observaciones | J3: Si llenas pct_aportacion, se usa directo. | K3: Si no, divide NI_programa entre NI_total_campus.
A4: Cancún | B4: AD | C4: Profesional | D4: Licenciatura en Administración de Empresas | E4: 2026 | F4: 13 | G4: 105 | I4: Puedes llenar NI_programa y NI_total_campus o directamente pct_aportacion. | J4: Evita duplicar programa-campus-año. | K4: Si se duplica, puede inflar la mezcla porcentual.
A5: Cancún | B5: AD | C5: Profesional | D5: Licenciatura en Comercio y Negocios Internacionales | E5: 2026 | F5: 21 | G5: 105
A6: Cancún | B6: AD | C6: Profesional | D6: Licenciatura en Derecho | E6: 2026 | F6: 7 | G6: 105
A7: Cancún | B7: AD | C7: Profesional | D7: Licenciatura en Diseño Gráfico y Animación | E7: 2026 | F7: 10 | G7: 105
A8: Cancún | B8: AD | C8: Profesional | D8: Licenciatura en Ingeniería en Desarrollo de Software | E8: 2026 | F8: 26 | G8: 105
A9: Cancún | B9: AD | C9: Profesional | D9: Licenciatura en Mercadotecnia | E9: 2026 | F9: 13 | G9: 105
A10: Cancún | B10: AD | C10: Profesional | D10: Licenciatura en Nutrición | E10: 2026 | F10: 15 | G10: 105
A11: Chihuahua | B11: AD | C11: Profesional | D11: Licenciatura en Comercio y Negocios Internacionales | E11: 2026 | F11: 23 | G11: 107
A12: Chihuahua | B12: AD | C12: Profesional | D12: Licenciatura en Creación y Desarrollo de Empresas | E12: 2026 | F12: 12 | G12: 107
A13: Chihuahua | B13: AD | C13: Profesional | D13: Licenciatura en Derecho | E13: 2026 | F13: 14 | G13: 107
A14: Chihuahua | B14: AD | C14: Profesional | D14: Licenciatura en Diseño Gráfico y Animación | E14: 2026 | F14: 17 | G14: 107
A15: Chihuahua | B15: AD | C15: Profesional | D15: Licenciatura en Ingeniería Industrial | E15: 2026 | F15: 11 | G15: 107
A16: Chihuahua | B16: AD | C16: Profesional | D16: Licenciatura en Ingeniería Mecatrónica | E16: 2026 | F16: 11 | G16: 107
A17: Chihuahua | B17: AD | C17: Profesional | D17: Licenciatura en Ingeniería en Desarrollo de Software | E17: 2026 | F17: 19 | G17: 107
A18: Chihuahua | B18: AD | C18: Profesional | D18: Licenciatura en Mercadotecnia | E18: 2026 | F18: 0 | G18: 107 | H18: 0.001
A19: Ciudad Juárez | B19: AD | C19: Profesional | D19: Licenciatura en Comercio y Negocios Internacionales | E19: 2026 | F19: 33 | G19: 84
A20: Ciudad Juárez | B20: AD | C20: Profesional | D20: Licenciatura en Diseño Gráfico y Animación | E20: 2026 | F20: 4 | G20: 84
A21: Ciudad Juárez | B21: AD | C21: Profesional | D21: Licenciatura en Administración de Empresas | E21: 2026 | F21: 9 | G21: 84
A22: Ciudad Juárez | B22: AD | C22: Profesional | D22: Licenciatura en Ingeniería Industrial | E22: 2026 | F22: 9 | G22: 84
A23: Ciudad Juárez | B23: AD | C23: Profesional | D23: Licenciatura en Ingeniería Mecatrónica | E23: 2026 | F23: 13 | G23: 84
A24: Ciudad Juárez | B24: AD | C24: Profesional | D24: Licenciatura en Ingeniería en Desarrollo de Software | E24: 2026 | F24: 10 | G24: 84
A25: Ciudad Juárez | B25: AD | C25: Profesional | D25: Licenciatura en Mercadotecnia | E25: 2026 | F25: 6 | G25: 84
A26: Cuautitlán Izcalli | B26: AD | C26: Profesional | D26: Licenciatura en Administración de Empresas | E26: 2026 | F26: 21 | G26: 269
A27: Cuautitlán Izcalli | B27: AD | C27: Profesional | D27: Licenciatura en Comercio y Negocios Internacionales | E27: 2026 | F27: 42 | G27: 269
A28: Cuautitlán Izcalli | B28: AD | C28: Profesional | D28: Licenciatura en Contabilidad y Estrategia Financiera | E28: 2026 | F28: 20 | G28: 269
A29: Cuautitlán Izcalli | B29: AD | C29: Profesional | D29: Licenciatura en Derecho | E29: 2026 | F29: 20 | G29: 269
A30: Cuautitlán Izcalli | B30: AD | C30: Profesional | D30: Licenciatura en Diseño Gráfico y Animación | E30: 2026 | F30: 31 | G30: 269
... A37: Cuernavaca | B37: AD | C37: Profesional | D37: Licenciatura en Diseño Gráfico y Animación | E37: 2026 | F37: 10 | G37: 95
A38: Cuernavaca | B38: AD | C38: Profesional | D38: Licenciatura en Ingeniería Industrial | E38: 2026 | F38: 0 | G38: 95 | H38: 0.001
A39: Cuernavaca | B39: AD | C39: Profesional | D39: Licenciatura en Ingeniería Mecatrónica | E39: 2026 | F39: 19 | G39: 95
A40: Cuernavaca | B40: AD | C40: Profesional | D40: Licenciatura en Ingeniería en Desarrollo de Software | E40: 2026 | F40: 22 | G40: 95
A41: Cuernavaca | B41: AD | C41: Profesional | D41: Licenciatura en Mercadotecnia | E41: 2026 | F41: 14 | G41: 95
A42: Culiacán | B42: AD | C42: Profesional | D42: Licenciatura en Administración de Empresas | E42: 2026 | F42: 30 | G42: 250
A43: Culiacán | B43: AD | C43: Profesional | D43: Licenciatura en Comercio y Negocios Internacionales | E43: 2026 | F43: 62 | G43: 250
A44: Culiacán | B44: AD | C44: Profesional | D44: Licenciatura en Contabilidad y Estrategia Financiera | E44: 2026 | F44: 38 | G44: 250
A45: Culiacán | B45: AD | C45: Profesional | D45: Licenciatura en Diseño Gráfico y Animación | E45: 2026 | F45: 10 | G45: 250
A46: Culiacán | B46: AD | C46: Profesional | D46: Licenciatura en Ingeniería Industrial | E46: 2026 | F46: 39 | G46: 250
A47: Culiacán | B47: AD | C47: Profesional | D47: Licenciatura en Ingeniería en Desarrollo de Software | E47: 2026 | F47: 42 | G47: 250
A48: Culiacán | B48: AD | C48: Profesional | D48: Licenciatura en Mercadotecnia | E48: 2026 | F48: 29 | G48: 250
A49: Cumbres | B49: AD | C49: Profesional | D49: Licenciatura en Administración de Empresas | E49: 2026 | F49: 22 | G49: 195
A50: Cumbres | B50: AD | C50: Profesional | D50: Licenciatura en Comercio y Negocios Internacionales | E50: 2026 | F50: 43 | G50: 195
... A59: Durango | B59: AD | C59: Profesional | D59: Licenciatura en Ingeniería en Desarrollo de Software | E59: 2026 | F59: 10 | G59: 46
A60: Durango | B60: AD | C60: Profesional | D60: Licenciatura en Mercadotecnia | E60: 2026 | F60: 0 | G60: 46 | H60: 0.0005
A61: Ferrería | B61: AD | C61: Profesional | D61: Licenciatura en Administración de Empresas | E61: 2026 | F61: 13 | G61: 242
A62: Ferrería | B62: AD | C62: Profesional | D62: Licenciatura en Comercio y Negocios Internacionales | E62: 2026 | F62: 43 | G62: 242
A63: Ferrería | B63: AD | C63: Profesional | D63: Licenciatura en Contabilidad y Estrategia Financiera | E63: 2026 | F63: 17 | G63: 242
A64: Ferrería | B64: AD | C64: Profesional | D64: Licenciatura en Derecho | E64: 2026 | F64: 16 | G64: 242
A65: Ferrería | B65: AD | C65: Profesional | D65: Licenciatura en Diseño Gráfico y Animación | E65: 2026 | F65: 25 | G65: 242
A66: Ferrería | B66: AD | C66: Profesional | D66: Licenciatura en Ingeniería Industrial | E66: 2026 | F66: 9 | G66: 242
A67: Ferrería | B67: AD | C67: Profesional | D67: Licenciatura en Ingeniería Mecatrónica | E67: 2026 | F67: 23 | G67: 242
A68: Ferrería | B68: AD | C68: Profesional | D68: Licenciatura en Ingeniería en Desarrollo de Software | E68: 2026 | F68: 28 | G68: 242
A69: Ferrería | B69: AD | C69: Profesional | D69: Licenciatura en Mercadotecnia | E69: 2026 | F69: 29 | G69: 242
A70: Ferrería | B70: AD | C70: Profesional | D70: Licenciatura en Nutrición | E70: 2026 | F70: 15 | G70: 242
A71: Ferrería | B71: AD | C71: Profesional | D71: Licenciatura en Psicología | E71: 2026 | F71: 24 | G71: 242
A72: Guadalajara | B72: AD | C72: Profesional | D72: Licenciatura en Administración de Empresas | E72: 2026 | F72: 8 | G72: 98
... A77: Guadalajara | B77: AD | C77: Profesional | D77: Licenciatura en Ingeniería en Desarrollo de Software | E77: 2026 | F77: 20 | G77: 98
A78: Guadalajara | B78: AD | C78: Profesional | D78: Licenciatura en Ingeniería en Logística y Cadena de Suministro | E78: 2026 | F78: 0 | G78: 98 | H78: 0.001
A79: Guadalajara | B79: AD | C79: Profesional | D79: Licenciatura en Mercadotecnia | E79: 2026 | F79: 10 | G79: 98
A80: Guadalupe | B80: AD | C80: Profesional | D80: Licenciatura en Administración de Empresas | E80: 2026 | F80: 29 | G80: 169
A81: Guadalupe | B81: AD | C81: Profesional | D81: Licenciatura en Comercio y Negocios Internacionales | E81: 2026 | F81: 48 | G81: 169
A82: Guadalupe | B82: AD | C82: Profesional | D82: Licenciatura en Ingeniería Industrial | E82: 2026 | F82: 31 | G82: 169
A83: Guadalupe | B83: AD | C83: Profesional | D83: Licenciatura en Ingeniería Mecatrónica | E83: 2026 | F83: 16 | G83: 169
A84: Guadalupe | B84: AD | C84: Profesional | D84: Licenciatura en Ingeniería en Desarrollo de Software | E84: 2026 | F84: 23 | G84: 169
A85: Guadalupe | B85: AD | C85: Profesional | D85: Licenciatura en Mercadotecnia | E85: 2026 | F85: 22 | G85: 169
A86: Hermosillo | B86: AD | C86: Profesional | D86: Licenciatura en Administración de Empresas | E86: 2026 | F86: 6 | G86: 42
A87: Hermosillo | B87: AD | C87: Profesional | D87: Licenciatura en Comercio y Negocios Internacionales | E87: 2026 | F87: 4 | G87: 42
A88: Hermosillo | B88: AD | C88: Profesional | D88: Licenciatura en Diseño Gráfico y Animación | E88: 2026 | F88: 8 | G88: 42
A89: Hermosillo | B89: AD | C89: Profesional | D89: Licenciatura en Ingeniería Industrial | E89: 2026 | F89: 7 | G89: 42
A90: Hermosillo | B90: AD | C90: Profesional | D90: Licenciatura en Ingeniería en Desarrollo de Software | E90: 2026 | F90: 7 | G90: 42
... A141: Nuevo Laredo | B141: AD | C141: Profesional | D141: Licenciatura en Diseño Gráfico y Animación | E141: 2026 | F141: 18 | G141: 60
A142: Nuevo Laredo | B142: AD | C142: Profesional | D142: Licenciatura en Ingeniería Industrial | E142: 2026 | F142: 0 | G142: 60 | H142: 0.0008
A143: Nuevo Laredo | B143: AD | C143: Profesional | D143: Licenciatura en Mercadotecnia | E143: 2026 | F143: 13 | G143: 60
A144: Puebla | B144: AD | C144: Profesional | D144: Licenciatura en Administración de Empresas | E144: 2026 | F144: 8 | G144: 114
A145: Puebla | B145: AD | C145: Profesional | D145: Licenciatura en Comercio y Negocios Internacionales | E145: 2026 | F145: 17 | G145: 114
A146: Puebla | B146: AD | C146: Profesional | D146: Licenciatura en Derecho | E146: 2026 | F146: 18 | G146: 114
A147: Puebla | B147: AD | C147: Profesional | D147: Licenciatura en Diseño Gráfico y Animación | E147: 2026 | F147: 6 | G147: 114
A148: Puebla | B148: AD | C148: Profesional | D148: Licenciatura en Ingeniería en Desarrollo de Software | E148: 2026 | F148: 22 | G148: 114
A149: Puebla | B149: AD | C149: Profesional | D149: Licenciatura en Ingeniería en Mecatrónica | E149: 2026 | F149: 23 | G149: 114
A150: Puebla | B150: AD | C150: Profesional | D150: Licenciatura en Ingeniería Industrial | E150: 2026 | F150: 10 | G150: 114
A151: Puebla | B151: AD | C151: Profesional | D151: Licenciatura en Mercadotecnia | E151: 2026 | F151: 10 | G151: 114
A152: Querétaro | B152: AD | C152: Profesional | D152: Licenciatura en Administración de Empresas | E152: 2026 | F152: 6 | G152: 71
A153: Querétaro | B153: AD | C153: Profesional | D153: Licenciatura en Comercio y Negocios Internacionales | E153: 2026 | F153: 18 | G153: 71
A154: Querétaro | B154: AD | C154: Profesional | D154: Licenciatura en Diseño Gráfico y Animación | E154: 2026 | F154: 8 | G154: 71
... A232: Aguascalientes | B232: AD | C232: Profesional | D232: Licenciatura en Contabilidad y Estrategia Financiera | E232: 2026 | F232: 7 | G232: 83
A233: Aguascalientes | B233: AD | C233: Profesional | D233: Licenciatura en Ingeniería en Logística y Cadena de Suministro | E233: 2026 | G233: 83
A234: Aguascalientes | B234: AD | C234: Profesional | D234: Licenciatura en Ingeniería Mecatrónica | E234: 2026 | F234: 9 | G234: 83
A235: Aguascalientes | B235: AD | C235: Profesional | D235: Licenciatura en Ingeniería Industrial | E235: 2026 | F235: 12 | G235: 83

Sheet rutas_por_programa
A1: Cantidad de rutas de enfoque por programa | H1: Nota v43
A2: Llena esta hoja. Se usa para dividir los alumnos de S6 y S7 entre rutas de enfoque. | H2: S6-S7 se divide entre esta cantidad de rutas. | I2: Se usa redondeo hacia arriba: 21/6 = 4.
A3: Programa | B3: Cantidad de rutas de enfoque | C3: Notas | H3: Clasificación: | I3: <4 Flex | 4 a 11 Multicampus | 12+ Presencial
A4: Licenciatura en Ingeniería Mecatrónica | B4: 8 | C4: Borra o reemplaza este ejemplo | H4: Presenciales: | I4: Se desglosan en mañana/tarde con la configuración de Salones.
A5: Licenciatura en Ingeniería en Logística y Cadena de Suministro | B5: 3 | C5: Borra o reemplaza este ejemplo
A6: Licenciatura en Ingeniería en Desarrollo de Software | B6: 6
A7: Licenciatura en Ingeniería Industrial | B7: 4
A8: Licenciatura en Administración de Empresas | B8: 4
A9: Licenciatura en Comercio y Negocios Internacionales | B9: 2
A10: Licenciatura en Contabilidad y Estrategia Financiera | B10: 2
A11: Licenciatura en Creación y Desarrollo de Empresas | B11: 2
A12: Licenciatura en Derecho | B12: 4
A13: Licenciatura en Diseño Gráfico y Animación | B13: 3
A14: Licenciatura en Gastronomía Internacional | B14: 3
A15: Licenciatura en Mercadotecnia | B15: 4
A16: Ingeniero en Tecnología y trasnformación Digital | B16: 5
A17: Licenciatura en Administración y Desarrollo de talento | B17: 2
A18: Licenciatura en Educación | B18: 3

Sheet carreras_nuevas_2027
A1: Carreras nuevas 2027 por campus
A2: Llena una fila por campus-carrera nueva. Estas carreras empiezan en 2027: no aparecen en 2026. El NI propuesto se captura en la columna NI 2027; el simulador lo usa para repartir el NI total del campus en Multicampus, no para sumarlo doble a la pestaña Campus.
A3: Campus | B3: Periodo | C3: Nivel | D3: Programa | E3: Modalidad | F3: Activo | G3: Año inicio | H3: NI 2027 | I3: Cantidad de rutas de enfoque | J3: Observaciones
A4: Cd. Juarez | B4: AD | C4: Profesional | D4: Licenciatura en Contabilidad y Estrategia Financiera | E4: Presencial | F4: SI | G4: 2027 | H4: 25 | I4: 4 | J4: Borra esta fila y captura las carreras reales.
A5: Cumbres | B5: AD | C5: Profesional | D5: Licenciatura en Derecho | E5: Presencial | F5: SI | G5: 2027 | H5: 25 | I5: 3 | J5: La columna NI 2027 es la aportación esperada del programa.
A6: Tampico | B6: AD | C6: Profesional | D6: Licenciatura en Ingeniería en Desarrollo de Software | E6: Presencial | F6: SI | G6: 2027 | H6: 18
A7: Durango | B7: AD | C7: Profesional | D7: Licenciatura en Contabilidad y Estrategia Financiera | E7: Presencial | F7: SI | G7: 2027 | H7: 12
A8: Guadalupe | B8: AD | C8: Profesional | D8: Licenciatura en Contabilidad y Estrategia Financiera | E8: Presencial | F8: SI | G8: 2027 | H8: 12
A9: Hermosillo | B9: AD | C9: Profesional | D9: Licenciatura en Contabilidad y Estrategia Financiera | E9: Presencial | F9: SI | G9: 2027 | H9: 12
A10: Laguna | B10: AD | C10: Profesional | D10: Licenciatura en Contabilidad y Estrategia Financiera | E10: Presencial | F10: SI | G10: 2027 | H10: 18
A11: Nuevo Laredo | B11: AD | C11: Profesional | D11: Licenciatura en Ingeniería en Logística y Cadena de Suministro | E11: Presencial | F11: SI | G11: 2027 | H11: 18
A12: San Nicolás | B12: AD | C12: Profesional | D12: Licenciatura en Contabilidad y Estrategia Financiera | E12: Presencial | F12: SI | G12: 2027 | H12: 12
A13: Guadalajara | B13: AD | C13: Profesional | D13: Licenciatura en Creación y Desarrollo de Empresas | E13: Presencial | F13: SI | G13: 2027 | H13: 12
A14: Los Mochis | B14: AD | C14: Profesional | D14: Licenciatura en Ingeniería en Logística y Cadena de Suministro | E14: Presencial | F14: SI | G14: 2027 | H14: 18
A15: Querétaro | B15: AD | C15: Profesional | D15: Licenciatura en Contabilidad y Estrategia Financiera | E15: Presencial | F15: SI | G15: 2027 | H15: 12
A16: SLP | B16: AD | C16: Profesional | D16: Licenciatura en Ingeniería en Logística y Cadena de Suministro | E16: Presencial | F16: SI | G16: 2027 | H16: 18
A17: Zapopan | B17: AD | C17: Profesional | D17: Licenciatura en Contabilidad y Estrategia Financiera | E17: Presencial | F17: SI | G17: 2027 | H17: 12
... A60: Chihuahua | B60: AD | C60: Profesional | D60: Ing. en IA | E60: Presencial | F60: SI | G60: 2027 | H60: 18

Sheet cierres_reales
A1: Año | B1: Periodo | C1: Campus | D1: Nivel | E1: NI Real | F1: RI Real | G1: MT Real
A2: 2026 | B2: AD | C2: Aguascalientes | D2: Profesional | E2: 82 | F2: 0 | G2: 82
A3: 2026 | B3: AD | C3: Cancún | D3: Profesional | E3: 104 | F3: 370 | G3: 474
A4: 2026 | B4: AD | C4: Chihuahua | D4: Profesional | E4: 108 | F4: 374 | G4: 482
A5: 2026 | B5: AD | C5: Ciudad Juárez | D5: Profesional | E5: 81 | F5: 383 | G5: 464
A6: 2026 | B6: AD | C6: Cuautitlán Izcalli | D6: Profesional | E6: 269 | F6: 744 | G6: 1013
A7: 2026 | B7: AD | C7: Cuernavaca | D7: Profesional | E7: 95 | F7: 253 | G7: 348
A8: 2026 | B8: AD | C8: Culiacán | D8: Profesional | E8: 251 | F8: 775 | G8: 1026
A9: 2026 | B9: AD | C9: Cumbres | D9: Profesional | E9: 196 | F9: 679 | G9: 875
A10: 2026 | B10: AD | C10: Durango | D10: Profesional | E10: 47 | F10: 125 | G10: 172
A11: 2026 | B11: AD | C11: Ferrería | D11: Profesional | E11: 243 | F11: 885 | G11: 1128
A12: 2026 | B12: AD | C12: Guadalajara | D12: Profesional | E12: 99 | F12: 348 | G12: 447
A13: 2026 | B13: AD | C13: Guadalupe | D13: Profesional | E13: 171 | F13: 684 | G13: 855
... A64: 2026 | B64: AD | C64: Zapopan | D64: Preparatoria | E64: 390 | F64: 683 | G64: 1073

Sheet parametros_pos_ejec
A1: parametro | B1: valor | C1: opciones_validas | D1: como_lo_usara_el_simulador | E1: notas
A2: meta_mt_total_2036 | B2: 43000 | C2: Número | D2: Meta total de MT Posgrado + Ejecutivo en agosto 2036. | E2: Ejemplo: 43000.
A3: anio_meta | B3: 2036 | C3: 2036 | D3: Año de referencia para resolver la meta. | E3: Mantener 2036.
A4: anio_final_simulacion | B4: 2045 | C4: 2045 | D4: La simulación continúa hasta este año. | E4: Aunque la meta principal sea 2036.
A5: anio_base_ni_anual | B5: 2029 | C5: 2029 | D5: Año académico base para tomar el NI anual y crecer hacia adelante. | E5: Debe coincidir con el último año base confiable.
A6: anio_inicio_asincrono | B6: 2028 | C6: 2026-2045 | D6: Antes de este año, NI Asíncrono = 0. | E6: Si empieza en 2028, captura 2028.
A7: anio_deja_captar_sincrono | B7: 2029 | C7: Nunca, 2030-2045 | D7: Desde ese año, NI Síncrono = 0; el RI Síncrono sigue avanzando por matriz. | E7: Default v104: 2029. Puedes cambiarlo en el simulador a Nunca si Síncrono seguirá captando.
A8: reparto_meta_2036_interno | B8: 58% Posgrado / 42% Ejecutivo | C8: Informativo | D8: La v104 lo usa internamente; ya no se captura como control. | E8: Se elimina del UI para evitar confusión.
A9: modo_asincrono_interno | B9: Resolver meta | C9: Informativo | D9: La v104 siempre resuelve cuánto debe aportar Asíncrono para llegar a la meta 2036. | E9: Se elimina del UI.
A10: crecimiento_anual_ni_sincrono_posgrado | B10: 0 | C10: Porcentaje | D10: Crecimiento anual del NI Síncrono de Posgrado si sigue captando. | E10: Si deja de captar, prevalece anio_deja_captar_sincrono.
A11: crecimiento_anual_ni_sincrono_ejecutivo | B11: 0 | C11: Porcentaje | D11: Crecimiento anual del NI Síncrono de Ejecutivo si sigue captando. | E11: Si deja de captar, prevalece anio_deja_captar_sincrono.
A12: crecimiento_anual_ni_asincrono_posgrado_manual | C12: Porcentaje | D12: Solo se usa si modo_asincrono_2036 = Crecimiento manual. | E12: Si modo es Resolver meta, puedes dejarlo vacío.
A13: crecimiento_anual_ni_asincrono_ejecutivo_manual | C13: Porcentaje | D13: Solo se usa si modo_asincrono_2036 = Crecimiento manual. | E13: Si modo es Resolver meta, puedes dejarlo vacío.
A14: usar_stock_ri_agosto_2029 | B14: Sí | C14: Sí, No | D14: Sí: usa stock_ri_agosto_2029 para arrancar la matriz. No: usa MT/RI agregado y estima distribución. | E14: Ideal: Sí si tienes stock por bimestre académico.
A35: parametro | B35: valor | C35: tipo | D35: descripcion | E35: notas
A36: anio_inicio_reparto_ni_sinc_asinc | B36: 2029 | C36: Control | D36: Año académico desde el que el NI total se reparte entre Síncrono y Asíncrono. | E36: Default 2029.
A37: pct_ni_sincrono_posgrado | B37: 0% | C37: Control | D37: Porcentaje del NI anual total de Posgrado que seguirá entrando como Síncrono. | E37: 0% = deja de captar Síncrono; Asíncrono recibe 100%.
A38: pct_ni_sincrono_ejecutivo | B38: 0% | C38: Control | D38: Porcentaje del NI anual total de Ejecutivo que seguirá entrando como Síncrono. | E38: 0% = deja de captar Síncrono; Asíncrono recibe 100%.
A39: crecimiento_anual_ni_total_posgrado | B39: 3% | C39: Control | D39: Crecimiento anual del NI total de Posgrado antes de repartir entre modalidades. | E39: Default v114: 3% anual desde la base de cada periodo 2029.
A40: crecimiento_anual_ni_total_ejecutivo | B40: 3% | C40: Control | D40: Crecimiento anual del NI total de Ejecutivo antes de repartir entre modalidades. | E40: Default v114: 3% anual desde la base de cada periodo 2029.
A41: ri_tetra_inicial_posgrado | B41: 9800 | C41: Control | D41: RI histórico de programas tetra Posgrado que todavía cuenta como Síncrono. | E41: Se agota con egresos_anuales_tetra_posgrado.
A42: egreso_anual_tetra_posgrado | B42: 5000 | C42: Control | D42: Salida anual del RI tetra histórico de Posgrado. | E42: Default 5,000.
A43: ri_tetra_inicial_ejecutivo | B43: 6100 | C43: Control | D43: RI histórico de programas tetra Ejecutivo que todavía cuenta como Síncrono. | E43: Se agota con egresos_anuales_tetra_ejecutivo.
A44: egreso_anual_tetra_ejecutivo | B44: 1200 | C44: Control | D44: Salida anual del RI tetra histórico de Ejecutivo. | E44: Default 1,200.
A47: parametro | B47: valor | C47: tipo | D47: descripcion | E47: notas
A48: anio_meta_pos_ejec | B48: 2036 | C48: Control | D48: Año en que se quiere llegar a la meta MT. | E48: Editable en el simulador.
A49: meta_mt_total | B49: 43000 | C49: Control | D49: Meta MT total Posgrado + Ejecutivo. | E49: Default 43,000.
A50: modo_crecimiento_pos_ejec | B50: Manual por bloques | C50: Resolver meta, Manual por bloques | D50: Define si el simulador calcula el crecimiento requerido o usa bloques manuales por nivel. | E50: Default v125: Resolver meta.
A51: anio_pasar_mt_sincrono_a_asincrono | B51: Nunca | C51: Nunca, 2027-2045 | D51: Año en que se reclasifica la MT Síncrona viva como Asíncrona. | E51: No cambia la MT total; cambia la modalidad.
A60: pmp_mt_pos_ejec | B60: Hoja editable | C60: Insumo | D60: Captura MT PMP oficial hasta 2029. | E60: El simulador usa esa MT hasta 2029; desde Enero 2030 proyecta con crecimientos.
A61: inicio_crecimiento_proyectado | B61: Enero 2030 | C61: Regla | D61: Inicio de crecimiento manual o resuelto. | E61: Las capturas PMP cubren hasta 2029.

Sheet ni_bimestral_pos_ejec
A1: anio_academico | B1: periodo | C1: anio_calendario | D1: nivel | E1: modalidad | F1: NI
A2: 2026 | B2: Agosto | C2: 2026 | D2: Posgrado | E2: Síncrono | F2: 1866
A3: 2026 | B3: Octubre | C3: 2026 | D3: Posgrado | E3: Síncrono | F3: 1660
A4: 2026 | B4: Enero | C4: 2027 | D4: Posgrado | E4: Síncrono | F4: 2062
A5: 2026 | B5: Marzo | C5: 2027 | D5: Posgrado | E5: Síncrono | F5: 1513
A6: 2026 | B6: Junio | C6: 2027 | D6: Posgrado | E6: Síncrono | F6: 2245
A7: 2026 | B7: Agosto | C7: 2026 | D7: Posgrado | E7: Asíncrono | F7: 0
A8: 2026 | B8: Octubre | C8: 2026 | D8: Posgrado | E8: Asíncrono | F8: 0
A9: 2026 | B9: Enero | C9: 2027 | D9: Posgrado | E9: Asíncrono | F9: 0
A10: 2026 | B10: Marzo | C10: 2027 | D10: Posgrado | E10: Asíncrono | F10: 0
A11: 2026 | B11: Junio | C11: 2027 | D11: Posgrado | E11: Asíncrono | F11: 0
A12: 2026 | B12: Agosto | C12: 2026 | D12: Ejecutivo | E12: Síncrono | F12: 952
A13: 2026 | B13: Octubre | C13: 2026 | D13: Ejecutivo | E13: Síncrono | F13: 867
... A86: 2025 | B86: Junio | C86: 2026 | D86: Ejecutivo | E86: Síncrono | F86: 785

Sheet crecimiento_anual_pos_ejec
A1: anio_academico | B1: nivel | C1: modalidad | D1: crecimiento_ni_anual | E1: captacion_activa | F1: modo_uso | G1: notas
A2: 2030 | B2: Posgrado | C2: Síncrono | D2: 0.03 | E2: Sí | F2: Síncrono | G2: Se usa si Síncrono sigue captando. Si anio_deja_captar_sincrono aplica, NI Síncrono será 0 desde ese año.
A3: 2030 | B3: Posgrado | C3: Asíncrono | E3: Sí | F3: Asíncrono manual | G3: Solo se usa si modo_asincrono_2036 = Crecimiento manual. Si es Resolver meta, puede quedar vacío.
A4: 2030 | B4: Ejecutivo | C4: Síncrono | D4: 0.03 | E4: Sí | F4: Síncrono | G4: Se usa si Síncrono sigue captando. Si anio_deja_captar_sincrono aplica, NI Síncrono será 0 desde ese año.
A5: 2030 | B5: Ejecutivo | C5: Asíncrono | E5: Sí | F5: Asíncrono manual | G5: Solo se usa si modo_asincrono_2036 = Crecimiento manual. Si es Resolver meta, puede quedar vacío.
A6: 2031 | B6: Posgrado | C6: Síncrono | D6: 0.03 | E6: Sí | F6: Síncrono | G6: Se usa si Síncrono sigue captando. Si anio_deja_captar_sincrono aplica, NI Síncrono será 0 desde ese año.
A7: 2031 | B7: Posgrado | C7: Asíncrono | E7: Sí | F7: Asíncrono manual | G7: Solo se usa si modo_asincrono_2036 = Crecimiento manual. Si es Resolver meta, puede quedar vacío.
A8: 2031 | B8: Ejecutivo | C8: Síncrono | D8: 0.03 | E8: Sí | F8: Síncrono | G8: Se usa si Síncrono sigue captando. Si anio_deja_captar_sincrono aplica, NI Síncrono será 0 desde ese año.
A9: 2031 | B9: Ejecutivo | C9: Asíncrono | E9: Sí | F9: Asíncrono manual | G9: Solo se usa si modo_asincrono_2036 = Crecimiento manual. Si es Resolver meta, puede quedar vacío.
A10: 2032 | B10: Posgrado | C10: Síncrono | D10: 0.03 | E10: Sí | F10: Síncrono | G10: Se usa si Síncrono sigue captando. Si anio_deja_captar_sincrono aplica, NI Síncrono será 0 desde ese año.
A11: 2032 | B11: Posgrado | C11: Asíncrono | E11: Sí | F11: Asíncrono manual | G11: Solo se usa si modo_asincrono_2036 = Crecimiento manual. Si es Resolver meta, puede quedar vacío.
A12: 2032 | B12: Ejecutivo | C12: Síncrono | D12: 0.03 | E12: Sí | F12: Síncrono | G12: Se usa si Síncrono sigue captando. Si anio_deja_captar_sincrono aplica, NI Síncrono será 0 desde ese año.
A13: 2032 | B13: Ejecutivo | C13: Asíncrono | E13: Sí | F13: Asíncrono manual | G13: Solo se usa si modo_asincrono_2036 = Crecimiento manual. Si es Resolver meta, puede quedar vacío.
A14: 2033 | B14: Posgrado | C14: Síncrono | D14: 0.03 | E14: Sí | F14: Síncrono | G14: Se usa si Síncrono sigue captando. Si anio_deja_captar_sincrono aplica, NI Síncrono será 0 desde ese año.
A15: 2033 | B15: Posgrado | C15: Asíncrono | E15: Sí | F15: Asíncrono manual | G15: Solo se usa si modo_asincrono_2036 = Crecimiento manual. Si es Resolver meta, puede quedar vacío.
A16: 2033 | B16: Ejecutivo | C16: Síncrono | D16: 0.03 | E16: Sí | F16: Síncrono | G16: Se usa si Síncrono sigue captando. Si anio_deja_captar_sincrono aplica, NI Síncrono será 0 desde ese año.
A17: 2033 | B17: Ejecutivo | C17: Asíncrono | E17: Sí | F17: Asíncrono manual | G17: Solo se usa si modo_asincrono_2036 = Crecimiento manual. Si es Resolver meta, puede quedar vacío.
A18: 2034 | B18: Posgrado | C18: Síncrono | D18: 0.03 | E18: Sí | F18: Síncrono | G18: Se usa si Síncrono sigue captando. Si anio_deja_captar_sincrono aplica, NI Síncrono será 0 desde ese año.
A19: 2034 | B19: Posgrado | C19: Asíncrono | E19: Sí | F19: Asíncrono manual | G19: Solo se usa si modo_asincrono_2036 = Crecimiento manual. Si es Resolver meta, puede quedar vacío.
A20: 2034 | B20: Ejecutivo | C20: Síncrono | D20: 0.03 | E20: Sí | F20: Síncrono | G20: Se usa si Síncrono sigue captando. Si anio_deja_captar_sincrono aplica, NI Síncrono será 0 desde ese año.
A21: 2034 | B21: Ejecutivo | C21: Asíncrono | E21: Sí | F21: Asíncrono manual | G21: Solo se usa si modo_asincrono_2036 = Crecimiento manual. Si es Resolver meta, puede quedar vacío.
A22: 2035 | B22: Posgrado | C22: Síncrono | D22: 0.03 | E22: Sí | F22: Síncrono | G22: Se usa si Síncrono sigue captando. Si anio_deja_captar_sincrono aplica, NI Síncrono será 0 desde ese año.
A23: 2035 | B23: Posgrado | C23: Asíncrono | E23: Sí | F23: Asíncrono manual | G23: Solo se usa si modo_asincrono_2036 = Crecimiento manual. Si es Resolver meta, puede quedar vacío.
A24: 2035 | B24: Ejecutivo | C24: Síncrono | D24: 0.03 | E24: Sí | F24: Síncrono | G24: Se usa si Síncrono sigue captando. Si anio_deja_captar_sincrono aplica, NI Síncrono será 0 desde ese año.
A25: 2035 | B25: Ejecutivo | C25: Asíncrono | E25: Sí | F25: Asíncrono manual | G25: Solo se usa si modo_asincrono_2036 = Crecimiento manual. Si es Resolver meta, puede quedar vacío.
A26: 2036 | B26: Posgrado | C26: Síncrono | D26: 0.03 | E26: Sí | F26: Síncrono | G26: Se usa si Síncrono sigue captando. Si anio_deja_captar_sincrono aplica, NI Síncrono será 0 desde ese año.
A27: 2036 | B27: Posgrado | C27: Asíncrono | E27: Sí | F27: Asíncrono manual | G27: Solo se usa si modo_asincrono_2036 = Crecimiento manual. Si es Resolver meta, puede quedar vacío.
A28: 2036 | B28: Ejecutivo | C28: Síncrono | D28: 0.03 | E28: Sí | F28: Síncrono | G28: Se usa si Síncrono sigue captando. Si anio_deja_captar_sincrono aplica, NI Síncrono será 0 desde ese año.
A29: 2036 | B29: Ejecutivo | C29: Asíncrono | E29: Sí | F29: Asíncrono manual | G29: Solo se usa si modo_asincrono_2036 = Crecimiento manual. Si es Resolver meta, puede quedar vacío.
A30: 2037 | B30: Posgrado | C30: Síncrono | D30: 0.03 | E30: Sí | F30: Síncrono | G30: Se usa si Síncrono sigue captando. Si anio_deja_captar_sincrono aplica, NI Síncrono será 0 desde ese año.
A31: 2037 | B31: Posgrado | C31: Asíncrono | E31: Sí | F31: Asíncrono manual | G31: Solo se usa si modo_asincrono_2036 = Crecimiento manual. Si es Resolver meta, puede quedar vacío.
A32: 2037 | B32: Ejecutivo | C32: Síncrono | D32: 0.03 | E32: Sí | F32: Síncrono | G32: Se usa si Síncrono sigue captando. Si anio_deja_captar_sincrono aplica, NI Síncrono será 0 desde ese año.
A33: 2037 | B33: Ejecutivo | C33: Asíncrono | E33: Sí | F33: Asíncrono manual | G33: Solo se usa si modo_asincrono_2036 = Crecimiento manual. Si es Resolver meta, puede quedar vacío.
A34: 2038 | B34: Posgrado | C34: Síncrono | D34: 0.03 | E34: Sí | F34: Síncrono | G34: Se usa si Síncrono sigue captando. Si anio_deja_captar_sincrono aplica, NI Síncrono será 0 desde ese año.
A35: 2038 | B35: Posgrado | C35: Asíncrono | E35: Sí | F35: Asíncrono manual | G35: Solo se usa si modo_asincrono_2036 = Crecimiento manual. Si es Resolver meta, puede quedar vacío.
A36: 2038 | B36: Ejecutivo | C36: Síncrono | D36: 0.03 | E36: Sí | F36: Síncrono | G36: Se usa si Síncrono sigue captando. Si anio_deja_captar_sincrono aplica, NI Síncrono será 0 desde ese año.
A37: 2038 | B37: Ejecutivo | C37: Asíncrono | E37: Sí | F37: Asíncrono manual | G37: Solo se usa si modo_asincrono_2036 = Crecimiento manual. Si es Resolver meta, puede quedar vacío.
A38: 2039 | B38: Posgrado | C38: Síncrono | D38: 0.03 | E38: Sí | F38: Síncrono | G38: Se usa si Síncrono sigue captando. Si anio_deja_captar_sincrono aplica, NI Síncrono será 0 desde ese año.
A39: 2039 | B39: Posgrado | C39: Asíncrono | E39: Sí | F39: Asíncrono manual | G39: Solo se usa si modo_asincrono_2036 = Crecimiento manual. Si es Resolver meta, puede quedar vacío.
A40: 2039 | B40: Ejecutivo | C40: Síncrono | D40: 0.03 | E40: Sí | F40: Síncrono | G40: Se usa si Síncrono sigue captando. Si anio_deja_captar_sincrono aplica, NI Síncrono será 0 desde ese año.
A41: 2039 | B41: Ejecutivo | C41: Asíncrono | E41: Sí | F41: Asíncrono manual | G41: Solo se usa si modo_asincrono_2036 = Crecimiento manual. Si es Resolver meta, puede quedar vacío.
A42: 2040 | B42: Posgrado | C42: Síncrono | D42: 0.03 | E42: Sí | F42: Síncrono | G42: Se usa si Síncrono sigue captando. Si anio_deja_captar_sincrono aplica, NI Síncrono será 0 desde ese año.
A43: 2040 | B43: Posgrado | C43: Asíncrono | E43: Sí | F43: Asíncrono manual | G43: Solo se usa si modo_asincrono_2036 = Crecimiento manual. Si es Resolver meta, puede quedar vacío.
A44: 2040 | B44: Ejecutivo | C44: Síncrono | D44: 0.03 | E44: Sí | F44: Síncrono | G44: Se usa si Síncrono sigue captando. Si anio_deja_captar_sincrono aplica, NI Síncrono será 0 desde ese año.
A45: 2040 | B45: Ejecutivo | C45: Asíncrono | E45: Sí | F45: Asíncrono manual | G45: Solo se usa si modo_asincrono_2036 = Crecimiento manual. Si es Resolver meta, puede quedar vacío.
A46: 2041 | B46: Posgrado | C46: Síncrono | D46: 0.03 | E46: Sí | F46: Síncrono | G46: Se usa si Síncrono sigue captando. Si anio_deja_captar_sincrono aplica, NI Síncrono será 0 desde ese año.
A47: 2041 | B47: Posgrado | C47: Asíncrono | E47: Sí | F47: Asíncrono manual | G47: Solo se usa si modo_asincrono_2036 = Crecimiento manual. Si es Resolver meta, puede quedar vacío.
A48: 2041 | B48: Ejecutivo | C48: Síncrono | D48: 0.03 | E48: Sí | F48: Síncrono | G48: Se usa si Síncrono sigue captando. Si anio_deja_captar_sincrono aplica, NI Síncrono será 0 desde ese año.
A49: 2041 | B49: Ejecutivo | C49: Asíncrono | E49: Sí | F49: Asíncrono manual | G49: Solo se usa si modo_asincrono_2036 = Crecimiento manual. Si es Resolver meta, puede quedar vacío.
A50: 2042 | B50: Posgrado | C50: Síncrono | D50: 0.03 | E50: Sí | F50: Síncrono | G50: Se usa si Síncrono sigue captando. Si anio_deja_captar_sincrono aplica, NI Síncrono será 0 desde ese año.
A51: 2042 | B51: Posgrado | C51: Asíncrono | E51: Sí | F51: Asíncrono manual | G51: Solo se usa si modo_asincrono_2036 = Crecimiento manual. Si es Resolver meta, puede quedar vacío.
A52: 2042 | B52: Ejecutivo | C52: Síncrono | D52: 0.03 | E52: Sí | F52: Síncrono | G52: Se usa si Síncrono sigue captando. Si anio_deja_captar_sincrono aplica, NI Síncrono será 0 desde ese año.
A53: 2042 | B53: Ejecutivo | C53: Asíncrono | E53: Sí | F53: Asíncrono manual | G53: Solo se usa si modo_asincrono_2036 = Crecimiento manual. Si es Resolver meta, puede quedar vacío.
A54: 2043 | B54: Posgrado | C54: Síncrono | D54: 0.03 | E54: Sí | F54: Síncrono | G54: Se usa si Síncrono sigue captando. Si anio_deja_captar_sincrono aplica, NI Síncrono será 0 desde ese año.
A55: 2043 | B55: Posgrado | C55: Asíncrono | E55: Sí | F55: Asíncrono manual | G55: Solo se usa si modo_asincrono_2036 = Crecimiento manual. Si es Resolver meta, puede quedar vacío.
A56: 2043 | B56: Ejecutivo | C56: Síncrono | D56: 0.03 | E56: Sí | F56: Síncrono | G56: Se usa si Síncrono sigue captando. Si anio_deja_captar_sincrono aplica, NI Síncrono será 0 desde ese año.
A57: 2043 | B57: Ejecutivo | C57: Asíncrono | E57: Sí | F57: Asíncrono manual | G57: Solo se usa si modo_asincrono_2036 = Crecimiento manual. Si es Resolver meta, puede quedar vacío.
A58: 2044 | B58: Posgrado | C58: Síncrono | D58: 0.03 | E58: Sí | F58: Síncrono | G58: Se usa si Síncrono sigue captando. Si anio_deja_captar_sincrono aplica, NI Síncrono será 0 desde ese año.
A59: 2044 | B59: Posgrado | C59: Asíncrono | E59: Sí | F59: Asíncrono manual | G59: Solo se usa si modo_asincrono_2036 = Crecimiento manual. Si es Resolver meta, puede quedar vacío.
A60: 2044 | B60: Ejecutivo | C60: Síncrono | D60: 0.03 | E60: Sí | F60: Síncrono | G60: Se usa si Síncrono sigue captando. Si anio_deja_captar_sincrono aplica, NI Síncrono será 0 desde ese año.
A61: 2044 | B61: Ejecutivo | C61: Asíncrono | E61: Sí | F61: Asíncrono manual | G61: Solo se usa si modo_asincrono_2036 = Crecimiento manual. Si es Resolver meta, puede quedar vacío.
A62: 2045 | B62: Posgrado | C62: Síncrono | D62: 0.03 | E62: Sí | F62: Síncrono | G62: Se usa si Síncrono sigue captando. Si anio_deja_captar_sincrono aplica, NI Síncrono será 0 desde ese año.
A63: 2045 | B63: Posgrado | C63: Asíncrono | E63: Sí | F63: Asíncrono manual | G63: Solo se usa si modo_asincrono_2036 = Crecimiento manual. Si es Resolver meta, puede quedar vacío.
A64: 2045 | B64: Ejecutivo | C64: Síncrono | D64: 0.03 | E64: Sí | F64: Síncrono | G64: Se usa si Síncrono sigue captando. Si anio_deja_captar_sincrono aplica, NI Síncrono será 0 desde ese año.
A65: 2045 | B65: Ejecutivo | C65: Asíncrono | E65: Sí | F65: Asíncrono manual | G65: Solo se usa si modo_asincrono_2036 = Crecimiento manual. Si es Resolver meta, puede quedar vacío.

Sheet reparto_periodos_pos_ejec
A1: nivel | B1: modalidad | C1: periodo | D1: pct_reparto | E1: notas
A2: Posgrado | B2: Síncrono | C2: Agosto | D2: 18.5 | E2: Captura porcentaje del NI anual. La suma de los 5 periodos por Nivel + Modalidad debe ser 100%.
A3: Posgrado | B3: Síncrono | C3: Octubre | D3: 18.5 | E3: Captura porcentaje del NI anual. La suma de los 5 periodos por Nivel + Modalidad debe ser 100%.
A4: Posgrado | B4: Síncrono | C4: Enero | D4: 22 | E4: Captura porcentaje del NI anual. La suma de los 5 periodos por Nivel + Modalidad debe ser 100%.
A5: Posgrado | B5: Síncrono | C5: Marzo | D5: 16 | E5: Captura porcentaje del NI anual. La suma de los 5 periodos por Nivel + Modalidad debe ser 100%.
A6: Posgrado | B6: Síncrono | C6: Junio | D6: 25 | E6: Captura porcentaje del NI anual. La suma de los 5 periodos por Nivel + Modalidad debe ser 100%.
A7: Posgrado | B7: Asíncrono | C7: Agosto | D7: 18.5 | E7: Captura porcentaje del NI anual. La suma de los 5 periodos por Nivel + Modalidad debe ser 100%.
A8: Posgrado | B8: Asíncrono | C8: Octubre | D8: 18.5 | E8: Captura porcentaje del NI anual. La suma de los 5 periodos por Nivel + Modalidad debe ser 100%.
A9: Posgrado | B9: Asíncrono | C9: Enero | D9: 22 | E9: Captura porcentaje del NI anual. La suma de los 5 periodos por Nivel + Modalidad debe ser 100%.
A10: Posgrado | B10: Asíncrono | C10: Marzo | D10: 16 | E10: Captura porcentaje del NI anual. La suma de los 5 periodos por Nivel + Modalidad debe ser 100%.
A11: Posgrado | B11: Asíncrono | C11: Junio | D11: 25 | E11: Captura porcentaje del NI anual. La suma de los 5 periodos por Nivel + Modalidad debe ser 100%.
A12: Ejecutivo | B12: Síncrono | C12: Agosto | D12: 20.5 | E12: Captura porcentaje del NI anual. La suma de los 5 periodos por Nivel + Modalidad debe ser 100%.
A13: Ejecutivo | B13: Síncrono | C13: Octubre | D13: 19 | E13: Captura porcentaje del NI anual. La suma de los 5 periodos por Nivel + Modalidad debe ser 100%.
... A21: Ejecutivo | B21: Asíncrono | C21: Junio | D21: 21.5 | E21: Captura porcentaje del NI anual. La suma de los 5 periodos por Nivel + Modalidad debe ser 100%.

Sheet tasas_ri_bimestre_pos_ejec
A1: nivel | B1: modalidad | C1: bimestre_origen | D1: bimestre_destino | E1: tasa | F1: notas
A2: Posgrado | B2: Síncrono | C2: B1 | D2: B2 | E2: 0.9 | F2: Posgrado: duración normal aprox. 10 bimestres; se dejan 15 tasas para rezago/extensión.
A3: Posgrado | B3: Síncrono | C3: B2 | D3: B3 | E3: 0.95 | F3: Posgrado: duración normal aprox. 10 bimestres; se dejan 15 tasas para rezago/extensión.
A4: Posgrado | B4: Síncrono | C4: B3 | D4: B4 | E4: 0.95 | F4: Posgrado: duración normal aprox. 10 bimestres; se dejan 15 tasas para rezago/extensión.
A5: Posgrado | B5: Síncrono | C5: B4 | D5: B5 | E5: 0.92 | F5: Posgrado: duración normal aprox. 10 bimestres; se dejan 15 tasas para rezago/extensión.
A6: Posgrado | B6: Síncrono | C6: B5 | D6: B6 | E6: 0.95 | F6: Posgrado: duración normal aprox. 10 bimestres; se dejan 15 tasas para rezago/extensión.
A7: Posgrado | B7: Síncrono | C7: B6 | D7: B7 | E7: 0.88 | F7: Posgrado: duración normal aprox. 10 bimestres; se dejan 15 tasas para rezago/extensión.
A8: Posgrado | B8: Síncrono | C8: B7 | D8: B8 | E8: 0.88 | F8: Posgrado: duración normal aprox. 10 bimestres; se dejan 15 tasas para rezago/extensión.
A9: Posgrado | B9: Síncrono | C9: B8 | D9: B9 | E9: 0.88 | F9: Posgrado: duración normal aprox. 10 bimestres; se dejan 15 tasas para rezago/extensión.
A10: Posgrado | B10: Síncrono | C10: B9 | D10: B10 | E10: 0.88 | F10: Posgrado: duración normal aprox. 10 bimestres; se dejan 15 tasas para rezago/extensión.
A11: Posgrado | B11: Síncrono | C11: B10 | D11: B11 | E11: 0.2 | F11: Posgrado: duración normal aprox. 10 bimestres; se dejan 15 tasas para rezago/extensión.
A12: Posgrado | B12: Síncrono | C12: B11 | D12: B12 | E12: 0.1 | F12: Posgrado: duración normal aprox. 10 bimestres; se dejan 15 tasas para rezago/extensión.
A13: Posgrado | B13: Síncrono | C13: B12 | D13: B13 | E13: 0.4 | F13: Posgrado: duración normal aprox. 10 bimestres; se dejan 15 tasas para rezago/extensión.
... A67: Ejecutivo | B67: Asíncrono | C67: B19 | D67: B20 | E67: 0.1 | F67: Ejecutivo: duración normal aprox. 15 bimestres; se dejan 20 tasas para rezago/extensión.

Sheet stock_ri_agosto_2029
A1: anio_corte | B1: periodo_corte | C1: nivel | D1: modalidad | E1: bimestre_academico | F1: alumnos_RI | G1: notas
A2: 2029 | B2: Agosto | C2: Posgrado | D2: Síncrono | E2: B2 | F2: 2533 | G2: Stock RI vivo en agosto 2029 por edad académica. Si no tienes este desglose, llena mt_agosto_real_pos_ejec.
A3: 2029 | B3: Agosto | C3: Posgrado | D3: Síncrono | E3: B3 | F3: 1605 | G3: Stock RI vivo en agosto 2029 por edad académica. Si no tienes este desglose, llena mt_agosto_real_pos_ejec.
A4: 2029 | B4: Agosto | C4: Posgrado | D4: Síncrono | E4: B4 | F4: 2052 | G4: Stock RI vivo en agosto 2029 por edad académica. Si no tienes este desglose, llena mt_agosto_real_pos_ejec.
A5: 2029 | B5: Agosto | C5: Posgrado | D5: Síncrono | E5: B5 | F5: 1507 | G5: Stock RI vivo en agosto 2029 por edad académica. Si no tienes este desglose, llena mt_agosto_real_pos_ejec.
A6: 2029 | B6: Agosto | C6: Posgrado | D6: Síncrono | E6: B6 | F6: 1432 | G6: Stock RI vivo en agosto 2029 por edad académica. Si no tienes este desglose, llena mt_agosto_real_pos_ejec.
A7: 2029 | B7: Agosto | C7: Posgrado | D7: Síncrono | E7: B7 | F7: 1599 | G7: Stock RI vivo en agosto 2029 por edad académica. Si no tienes este desglose, llena mt_agosto_real_pos_ejec.
A8: 2029 | B8: Agosto | C8: Posgrado | D8: Síncrono | E8: B8 | F8: 940 | G8: Stock RI vivo en agosto 2029 por edad académica. Si no tienes este desglose, llena mt_agosto_real_pos_ejec.
A9: 2029 | B9: Agosto | C9: Posgrado | D9: Síncrono | E9: B9 | F9: 1112 | G9: Stock RI vivo en agosto 2029 por edad académica. Si no tienes este desglose, llena mt_agosto_real_pos_ejec.
A10: 2029 | B10: Agosto | C10: Posgrado | D10: Síncrono | E10: B10 | F10: 811 | G10: Stock RI vivo en agosto 2029 por edad académica. Si no tienes este desglose, llena mt_agosto_real_pos_ejec.
A11: 2029 | B11: Agosto | C11: Posgrado | D11: Síncrono | E11: B11 | F11: 714 | G11: Stock RI vivo en agosto 2029 por edad académica. Si no tienes este desglose, llena mt_agosto_real_pos_ejec.
A12: 2029 | B12: Agosto | C12: Posgrado | D12: Síncrono | E12: B12 | F12: 169 | G12: Stock RI vivo en agosto 2029 por edad académica. Si no tienes este desglose, llena mt_agosto_real_pos_ejec.
A13: 2029 | B13: Agosto | C13: Posgrado | D13: Síncrono | E13: B13 | F13: 12 | G13: Stock RI vivo en agosto 2029 por edad académica. Si no tienes este desglose, llena mt_agosto_real_pos_ejec.
... A15: 2029 | B15: Agosto | C15: Posgrado | D15: Síncrono | E15: B15 | F15: 2 | G15: Stock RI vivo en agosto 2029 por edad académica. Si no tienes este desglose, llena mt_agosto_real_pos_ejec.
A16: 2029 | B16: Agosto | C16: Posgrado | D16: Asíncrono | E16: B2 | G16: Stock RI vivo en agosto 2029 por edad académica. Si no tienes este desglose, llena mt_agosto_real_pos_ejec.
A17: 2029 | B17: Agosto | C17: Posgrado | D17: Asíncrono | E17: B3 | G17: Stock RI vivo en agosto 2029 por edad académica. Si no tienes este desglose, llena mt_agosto_real_pos_ejec.
A18: 2029 | B18: Agosto | C18: Posgrado | D18: Asíncrono | E18: B4 | G18: Stock RI vivo en agosto 2029 por edad académica. Si no tienes este desglose, llena mt_agosto_real_pos_ejec.
A19: 2029 | B19: Agosto | C19: Posgrado | D19: Asíncrono | E19: B5 | G19: Stock RI vivo en agosto 2029 por edad académica. Si no tienes este desglose, llena mt_agosto_real_pos_ejec.
A20: 2029 | B20: Agosto | C20: Posgrado | D20: Asíncrono | E20: B6 | G20: Stock RI vivo en agosto 2029 por edad académica. Si no tienes este desglose, llena mt_agosto_real_pos_ejec.
A21: 2029 | B21: Agosto | C21: Posgrado | D21: Asíncrono | E21: B7 | G21: Stock RI vivo en agosto 2029 por edad académica. Si no tienes este desglose, llena mt_agosto_real_pos_ejec.
A22: 2029 | B22: Agosto | C22: Posgrado | D22: Asíncrono | E22: B8 | G22: Stock RI vivo en agosto 2029 por edad académica. Si no tienes este desglose, llena mt_agosto_real_pos_ejec.
A23: 2029 | B23: Agosto | C23: Posgrado | D23: Asíncrono | E23: B9 | G23: Stock RI vivo en agosto 2029 por edad académica. Si no tienes este desglose, llena mt_agosto_real_pos_ejec.
A24: 2029 | B24: Agosto | C24: Posgrado | D24: Asíncrono | E24: B10 | G24: Stock RI vivo en agosto 2029 por edad académica. Si no tienes este desglose, llena mt_agosto_real_pos_ejec.
A25: 2029 | B25: Agosto | C25: Posgrado | D25: Asíncrono | E25: B11 | G25: Stock RI vivo en agosto 2029 por edad académica. Si no tienes este desglose, llena mt_agosto_real_pos_ejec.
A26: 2029 | B26: Agosto | C26: Posgrado | D26: Asíncrono | E26: B12 | G26: Stock RI vivo en agosto 2029 por edad académica. Si no tienes este desglose, llena mt_agosto_real_pos_ejec.
A27: 2029 | B27: Agosto | C27: Posgrado | D27: Asíncrono | E27: B13 | G27: Stock RI vivo en agosto 2029 por edad académica. Si no tienes este desglose, llena mt_agosto_real_pos_ejec.
... A29: 2029 | B29: Agosto | C29: Posgrado | D29: Asíncrono | E29: B15 | G29: Stock RI vivo en agosto 2029 por edad académica. Si no tienes este desglose, llena mt_agosto_real_pos_ejec.
A30: 2029 | B30: Agosto | C30: Ejecutivo | D30: Síncrono | E30: B2 | F30: 1244 | G30: Stock RI vivo en agosto 2029 por edad académica. Si no tienes este desglose, llena mt_agosto_real_pos_ejec.
A31: 2029 | B31: Agosto | C31: Ejecutivo | D31: Síncrono | E31: B3 | F31: 747 | G31: Stock RI vivo en agosto 2029 por edad académica. Si no tienes este desglose, llena mt_agosto_real_pos_ejec.
A32: 2029 | B32: Agosto | C32: Ejecutivo | D32: Síncrono | E32: B4 | F32: 840 | G32: Stock RI vivo en agosto 2029 por edad académica. Si no tienes este desglose, llena mt_agosto_real_pos_ejec.
A33: 2029 | B33: Agosto | C33: Ejecutivo | D33: Síncrono | E33: B5 | F33: 691 | G33: Stock RI vivo en agosto 2029 por edad académica. Si no tienes este desglose, llena mt_agosto_real_pos_ejec.
A34: 2029 | B34: Agosto | C34: Ejecutivo | D34: Síncrono | E34: B6 | F34: 717 | G34: Stock RI vivo en agosto 2029 por edad académica. Si no tienes este desglose, llena mt_agosto_real_pos_ejec.
A35: 2029 | B35: Agosto | C35: Ejecutivo | D35: Síncrono | E35: B7 | F35: 715 | G35: Stock RI vivo en agosto 2029 por edad académica. Si no tienes este desglose, llena mt_agosto_real_pos_ejec.
A36: 2029 | B36: Agosto | C36: Ejecutivo | D36: Síncrono | E36: B8 | F36: 430 | G36: Stock RI vivo en agosto 2029 por edad académica. Si no tienes este desglose, llena mt_agosto_real_pos_ejec.
A37: 2029 | B37: Agosto | C37: Ejecutivo | D37: Síncrono | E37: B9 | F37: 484 | G37: Stock RI vivo en agosto 2029 por edad académica. Si no tienes este desglose, llena mt_agosto_real_pos_ejec.
A38: 2029 | B38: Agosto | C38: Ejecutivo | D38: Síncrono | E38: B10 | F38: 392 | G38: Stock RI vivo en agosto 2029 por edad académica. Si no tienes este desglose, llena mt_agosto_real_pos_ejec.
A39: 2029 | B39: Agosto | C39: Ejecutivo | D39: Síncrono | E39: B11 | F39: 432 | G39: Stock RI vivo en agosto 2029 por edad académica. Si no tienes este desglose, llena mt_agosto_real_pos_ejec.
A40: 2029 | B40: Agosto | C40: Ejecutivo | D40: Síncrono | E40: B12 | F40: 318 | G40: Stock RI vivo en agosto 2029 por edad académica. Si no tienes este desglose, llena mt_agosto_real_pos_ejec.
A41: 2029 | B41: Agosto | C41: Ejecutivo | D41: Síncrono | E41: B13 | F41: 225 | G41: Stock RI vivo en agosto 2029 por edad académica. Si no tienes este desglose, llena mt_agosto_real_pos_ejec.
... A48: 2029 | B48: Agosto | C48: Ejecutivo | D48: Síncrono | E48: B20 | F48: 3 | G48: Stock RI vivo en agosto 2029 por edad académica. Si no tienes este desglose, llena mt_agosto_real_pos_ejec.
A49: 2029 | B49: Agosto | C49: Ejecutivo | D49: Asíncrono | E49: B2 | G49: Stock RI vivo en agosto 2029 por edad académica. Si no tienes este desglose, llena mt_agosto_real_pos_ejec.
A50: 2029 | B50: Agosto | C50: Ejecutivo | D50: Asíncrono | E50: B3 | G50: Stock RI vivo en agosto 2029 por edad académica. Si no tienes este desglose, llena mt_agosto_real_pos_ejec.
A51: 2029 | B51: Agosto | C51: Ejecutivo | D51: Asíncrono | E51: B4 | G51: Stock RI vivo en agosto 2029 por edad académica. Si no tienes este desglose, llena mt_agosto_real_pos_ejec.
A52: 2029 | B52: Agosto | C52: Ejecutivo | D52: Asíncrono | E52: B5 | G52: Stock RI vivo en agosto 2029 por edad académica. Si no tienes este desglose, llena mt_agosto_real_pos_ejec.
A53: 2029 | B53: Agosto | C53: Ejecutivo | D53: Asíncrono | E53: B6 | G53: Stock RI vivo en agosto 2029 por edad académica. Si no tienes este desglose, llena mt_agosto_real_pos_ejec.
A54: 2029 | B54: Agosto | C54: Ejecutivo | D54: Asíncrono | E54: B7 | G54: Stock RI vivo en agosto 2029 por edad académica. Si no tienes este desglose, llena mt_agosto_real_pos_ejec.
A55: 2029 | B55: Agosto | C55: Ejecutivo | D55: Asíncrono | E55: B8 | G55: Stock RI vivo en agosto 2029 por edad académica. Si no tienes este desglose, llena mt_agosto_real_pos_ejec.
A56: 2029 | B56: Agosto | C56: Ejecutivo | D56: Asíncrono | E56: B9 | G56: Stock RI vivo en agosto 2029 por edad académica. Si no tienes este desglose, llena mt_agosto_real_pos_ejec.
A57: 2029 | B57: Agosto | C57: Ejecutivo | D57: Asíncrono | E57: B10 | G57: Stock RI vivo en agosto 2029 por edad académica. Si no tienes este desglose, llena mt_agosto_real_pos_ejec.
A58: 2029 | B58: Agosto | C58: Ejecutivo | D58: Asíncrono | E58: B11 | G58: Stock RI vivo en agosto 2029 por edad académica. Si no tienes este desglose, llena mt_agosto_real_pos_ejec.
A59: 2029 | B59: Agosto | C59: Ejecutivo | D59: Asíncrono | E59: B12 | G59: Stock RI vivo en agosto 2029 por edad académica. Si no tienes este desglose, llena mt_agosto_real_pos_ejec.
A60: 2029 | B60: Agosto | C60: Ejecutivo | D60: Asíncrono | E60: B13 | G60: Stock RI vivo en agosto 2029 por edad académica. Si no tienes este desglose, llena mt_agosto_real_pos_ejec.
... A67: 2029 | B67: Agosto | C67: Ejecutivo | D67: Asíncrono | E67: B20 | G67: Stock RI vivo en agosto 2029 por edad académica. Si no tienes este desglose, llena mt_agosto_real_pos_ejec.

Sheet LEEME_pos_ejec
A1: Plantillas Posgrado / Ejecutivo · v2
A2: Objetivo | B2: Simular Posgrado + Ejecutivo separando Síncrono y Asíncrono, con meta total 2036 y proyección hasta 2045.
A3: Lógica corregida | B3: Primero se calcula la vida natural de Síncrono con NI, RI y egresos por matriz de cohortes. Después Asíncrono cubre la brecha necesaria para llegar a la meta total 2036.
A5: Hoja | B5: Qué llenar | C5: Obligatorio | D5: Notas
A6: parametros_pos_ejec | B6: Meta total 2036, año inicio Asíncrono, regla para dejar o no dejar de captar Síncrono, modo de Asíncrono y crecimientos principales. | C6: Sí | D6: No captures meta directa de Asíncrono; el simulador la calcula como meta total menos MT Síncrona.
A7: ni_bimestral_pos_ejec | B7: NI real/base por año académico, periodo, nivel y modalidad para 2026–2029. | C7: Sí | D7: Año académico 2026 = Ago 2026 + Oct 2026 + Ene 2027 + Mar 2027 + Jun 2027.
A8: mt_agosto_real_pos_ejec | B8: MT real de agosto por nivel/modalidad para validar o arrancar el motor. | C8: Recomendado | D8: Útil si tienes MT y RI agregados pero no todo el stock RI por bimestre académico.
A9: stock_ri_agosto_2029 | B9: Stock RI vivo en agosto 2029 por bimestre académico. | C9: Ideal | D9: Es la forma más precisa de arrancar la matriz desde 2029. Si no lo tienes, deja vacío y se usará el agregado.
A10: reparto_periodos_pos_ejec | B10: % de reparto del NI anual entre Agosto, Octubre, Enero, Marzo y Junio. | C10: Sí | D10: Debe sumar 100% por Nivel + Modalidad.
A11: tasas_ri_bimestre_pos_ejec | B11: Tasas por avance de cohorte: B1→B2, B2→B3, etc. | C11: Sí | D11: Posgrado: 15 tasas por modalidad. Ejecutivo: 20 tasas por modalidad.
A12: crecimiento_anual_pos_ejec | B12: Crecimiento anual del NI desde 2030 hasta 2045 por nivel/modalidad. | C12: Sí/según modo | D12: Para Síncrono aplica si sigue captando. Para Asíncrono aplica si modo_asincrono = Crecimiento manual; si es Resolver meta, puede quedar vacío.
A14: Regla de brecha 2036 | B14: MT Asíncrono requerida 2036 = Meta total 2036 - MT Síncrona calculada 2036.
A15: Importante | B15: Si Síncrono deja de captar, su NI se vuelve 0 desde ese año, pero su RI sigue vivo hasta que la matriz lo agote.

Sheet mt_agosto_real_pos_ejec
A1: anio_corte | B1: periodo_corte | C1: nivel | D1: modalidad | E1: NI_agosto_real | F1: RI_agosto_real | G1: MT_agosto_real | H1: notas
A2: 2026 | B2: Agosto | C2: Posgrado | D2: Síncrono | H2: Captura el dato real de agosto si lo tienes. MT = NI agosto + RI agosto.
A3: 2026 | B3: Agosto | C3: Posgrado | D3: Asíncrono | H3: Captura el dato real de agosto si lo tienes. MT = NI agosto + RI agosto.
A4: 2026 | B4: Agosto | C4: Ejecutivo | D4: Síncrono | H4: Captura el dato real de agosto si lo tienes. MT = NI agosto + RI agosto.
A5: 2026 | B5: Agosto | C5: Ejecutivo | D5: Asíncrono | H5: Captura el dato real de agosto si lo tienes. MT = NI agosto + RI agosto.
A6: 2027 | B6: Agosto | C6: Posgrado | D6: Síncrono | H6: Captura el dato real de agosto si lo tienes. MT = NI agosto + RI agosto.
A7: 2027 | B7: Agosto | C7: Posgrado | D7: Asíncrono | H7: Captura el dato real de agosto si lo tienes. MT = NI agosto + RI agosto.
A8: 2027 | B8: Agosto | C8: Ejecutivo | D8: Síncrono | H8: Captura el dato real de agosto si lo tienes. MT = NI agosto + RI agosto.
A9: 2027 | B9: Agosto | C9: Ejecutivo | D9: Asíncrono | H9: Captura el dato real de agosto si lo tienes. MT = NI agosto + RI agosto.
A10: 2028 | B10: Agosto | C10: Posgrado | D10: Síncrono | H10: Captura el dato real de agosto si lo tienes. MT = NI agosto + RI agosto.
A11: 2028 | B11: Agosto | C11: Posgrado | D11: Asíncrono | E11: 80 | F11: 0 | H11: Captura el dato real de agosto si lo tienes. MT = NI agosto + RI agosto.
A12: 2028 | B12: Agosto | C12: Ejecutivo | D12: Síncrono | H12: Captura el dato real de agosto si lo tienes. MT = NI agosto + RI agosto.
A13: 2028 | B13: Agosto | C13: Ejecutivo | D13: Asíncrono | E13: 36 | F13: 0 | H13: Captura el dato real de agosto si lo tienes. MT = NI agosto + RI agosto.
A14: 2029 | B14: Agosto | C14: Posgrado | D14: Síncrono | H14: Captura el dato real de agosto si lo tienes. MT = NI agosto + RI agosto.
A15: 2029 | B15: Agosto | C15: Posgrado | D15: Asíncrono | E15: 226 | F15: 301 | H15: Captura el dato real de agosto si lo tienes. MT = NI agosto + RI agosto.
A16: 2029 | B16: Agosto | C16: Ejecutivo | D16: Síncrono | H16: Captura el dato real de agosto si lo tienes. MT = NI agosto + RI agosto.
A17: 2029 | B17: Agosto | C17: Ejecutivo | D17: Asíncrono | E17: 49 | F17: 134 | H17: Captura el dato real de agosto si lo tienes. MT = NI agosto + RI agosto.

Sheet stock_ri_periodo_pos_ejec
A1: anio_academico | B1: periodo | C1: anio_calendario | D1: nivel | E1: modalidad | F1: tipo_programa | G1: bimestre_academico | H1: alumnos_RI | I1: notas
A2: 2025 | B2: Octubre | C2: 2025 | D2: Ejecutivo | E2: Síncrono | F2: Bimestral | G2: B2 | H2: 708 | I2: Ejemplo: reparte aquí los ~6100 RI tetra por bimestre académico.
A3: 2025 | B3: Enero | C3: 2026 | D3: Ejecutivo | E3: Síncrono | F3: Bimestral | G3: B2 | H3: 550 | I3: Ejemplo: reparte aquí los ~2100 RI bimestrales por bimestre académico.
A4: 2025 | B4: Enero | C4: 2026 | D4: Ejecutivo | E4: Síncrono | F4: Bimestral | G4: B3 | H4: 450 | I4: Ejemplo: reparte aquí los ~5000 RI tetra de posgrado por bimestre académico.
A5: 2025 | B5: Marzo | C5: 2026 | D5: Ejecutivo | E5: Síncrono | F5: Bimestral | G5: B4 | H5: 368 | I5: Usa año académico 2028; Enero pertenece al calendario 2029.
A6: 2025 | B6: Marzo | C6: 2026 | D6: Ejecutivo | E6: Síncrono | F6: Bimestral | G6: B3 | H6: 325
A7: 2025 | B7: Marzo | C7: 2026 | D7: Ejecutivo | E7: Síncrono | F7: Bimestral | G7: B2 | H7: 793
A8: 2025 | B8: Junio | C8: 2026 | D8: Ejecutivo | E8: Síncrono | F8: Bimestral | G8: B5 | H8: 2
A9: 2025 | B9: Junio | C9: 2026 | D9: Ejecutivo | E9: Síncrono | F9: Bimestral | G9: B4 | H9: 301
A10: 2025 | B10: Junio | C10: 2026 | D10: Ejecutivo | E10: Síncrono | F10: Bimestral | G10: B3 | H10: 766
A11: 2025 | B11: Junio | C11: 2026 | D11: Ejecutivo | E11: Síncrono | F11: Bimestral | G11: B2 | H11: 420

Sheet mt_periodo_real_pos_ejec
A1: anio_academico | B1: periodo | C1: anio_calendario | D1: nivel | E1: modalidad | F1: NI_real | G1: RI_real | H1: MT_real | I1: notas
A2: 2028 | B2: Enero | C2: 2029 | D2: Posgrado | E2: Asíncrono | F2: 0 | G2: 0 | H2: 0 | I2: Aquí sí puedes poner enero, marzo y junio; no solo agosto.
A3: 2028 | B3: Marzo | C3: 2029 | D3: Posgrado | E3: Asíncrono | F3: 0 | G3: 0 | H3: 0 | I3: Año académico 2028, calendario 2029.
A4: 2028 | B4: Junio | C4: 2029 | D4: Posgrado | E4: Asíncrono | F4: 0 | G4: 0 | H4: 0 | I4: Si MT_real queda vacío, el simulador usa NI_real + RI_real.
A5: 2029 | B5: Agosto | C5: 2029 | D5: Ejecutivo | E5: Síncrono | F5: 0 | G5: 0 | H5: 0 | I5: Si deja de captar desde agosto 2029, NI_real puede quedar 0 y RI_real sigue vivo.

Sheet LEEME_v105_pos_ejec
A1: Cambio | B1: Descripción
A2: stock_ri_periodo_pos_ejec | B2: Aquí se pone el RI vivo por periodo y bimestre académico. Esto alimenta la matriz, por eso sirve para simular desde 2026 y no solo desde agosto 2029.
A3: mt_periodo_real_pos_ejec | B3: Aquí se pueden poner NI/RI/MT reales por cualquier periodo: Agosto, Octubre, Enero, Marzo o Junio.
A4: Año académico | B4: Ejemplo: año académico 2028 = Agosto 2028 + Octubre 2028 + Enero 2029 + Marzo 2029 + Junio 2029.
A5: Dejar de captar Síncrono | B5: El año seleccionado aplica desde Agosto de ese año académico. Por ejemplo, 2029 significa desde Agosto 2029, no desde Enero 2029.
A6: RI Síncrono | B6: Aunque NI Síncrono sea 0, el RI sigue avanzando con las tasas de tasas_ri_bimestre_pos_ejec hasta agotarse.

Sheet LEEME_v108_pos_ejec
A1: Tema | B1: Descripción
A2: Reparto NI Síncrono/Asíncrono | B2: Desde el año de estrategia, el simulador toma el NI anual total del nivel y lo reparte con % NI Síncrono. Asíncrono recibe el complemento.
A3: Dejar de captar Síncrono | B3: Se modela con % NI Síncrono = 0%. Así el NI nuevo pasa a Asíncrono, pero el RI Síncrono vivo sigue contando.
A4: RI tetra histórico | B4: Además de la matriz bimestral, el simulador suma un RI tetra histórico como run-off. Defaults: Posgrado 9,800 con salida 5,000/año; Ejecutivo 6,100 con salida 1,200/año.
A5: Matriz bimestral | B5: Los NI 2027/2028 y el stock RI por bimestre siguen avanzando con las tasas de tasas_ri_bimestre_pos_ejec.
A6: Meta 2036 | B6: La meta no se asigna completa a Asíncrono. Primero cuenta la MT Síncrona calculada, incluyendo RI tetra histórico y cohortes vivas.

Sheet LEEME_v114_pos_ejec
A1: Tema | B1: Descripción
A2: Corrección NI 2029+ | B2: Desde 2029, cada periodo usa el total original del periodo y lo reparte entre Síncrono/Asíncrono.
A3: Crecimiento por periodo | B3: Agosto 2030 se calcula desde Agosto 2029 × 1.03. No se recalcula con el porcentaje anual de distribución.
A4: Octubre 2029 | B4: Si Octubre quedó menor por faltante de asíncrono/base, toma al menos el total de Agosto del mismo nivel.
A5: Default crecimiento | B5: Los controles de crecimiento anual NI total Posgrado y Ejecutivo quedan en 3%.
A6: MT síncrona | B6: 0% de NI Síncrono no borra los RI vivos ni la MT tetra histórica.

Sheet LEEME_v115_pos_ejec
A1: Tema | B1: Descripción
A2: RI Síncrono no debe caer a cero | B2: 0% o 50% de NI Síncrono solo afecta los nuevos ingresos futuros; los RI vivos siguen avanzando.
A3: Por qué puede verse igual | B3: Si el reparto es 50/50 y las tasas Síncrono/Asíncrono son iguales, el RI generado desde 2029 puede ser muy parecido en ambas modalidades.
A4: Qué debe ser mayor | B4: El RI Síncrono total debería incluir además el arrastre de cohortes pre-reparto, especialmente Ejecutivo desde 2025 y Posgrado desde 2026.
A5: Nuevas columnas | B5: Las tablas separan RI arrastre pre-reparto y RI generación reparto+ para validar la dinámica.
A6: MT tetra histórica | B6: Sigue separada de RI bimestral y aporta a MT Síncrona.

Sheet LEEME_v116_pos_ejec
A1: Tema | B1: Descripción
A2: Tablas separadas | B2: Se agregan tablas separadas para Síncrono y Asíncrono periodo por periodo.
A3: Dinámica Síncrono | B3: Síncrono usa stock_ri_periodo_pos_ejec, NI históricos, NI futuro repartido y tasas propias.
A4: Dinámica Asíncrono | B4: Asíncrono usa NI asíncronos históricos, NI futuro repartido y tasas propias.
A5: Estado B1..B20 | B5: Se agrega vista por bimestre para revisar cómo avanza cada cohorte. B1 = NI del periodo; B2+ = RI.
A6: Sin arrastre visible | B6: Se eliminan columnas de arrastre de la vista principal; la diferencia se ve directamente por modalidad y bimestre.
A7: Reales | B7: mt_periodo_real_pos_ejec queda como validación; no sobrescribe la dinámica de cohortes.

Sheet LEEME_v117_pos_ejec
A1: Tema | B1: Descripción
A2: Meta 2029 | B2: Se agregó meta de MT Agosto 2029 = 30,000. Si la base queda abajo, se agrega ajuste de arranque en Asíncrono Agosto 2029.
A3: Meta 2036 | B3: El modo default resuelve el crecimiento anual requerido del NI total para llegar a MT Agosto 2036 = 43,000.
A4: Un solo crecimiento | B4: El crecimiento calculado aplica al NI total de ambos niveles y modalidades; luego se reparte según el % Síncrono/Asíncrono.
A5: 50/50 | B5: Si se captura 50% Síncrono, cada periodo proyectado se parte 50/50 entre modalidades.
A6: Síncrono | B6: Sigue teniendo NI si el porcentaje Síncrono es mayor que 0, y sus RI avanzan con sus tasas propias.
A7: Asíncrono | B7: Recibe el complemento del reparto y genera sus propios RI con sus tasas.
A8: Validación | B8: La sección Lectura 2036 muestra crecimiento requerido, ajuste 2029 y gaps.

Sheet LEEME_v118_pos_ejec
A1: Tema | B1: Descripción
A2: Corrección de pestaña | B2: La v118 se reconstruyó desde la v116 estable para evitar que Posgrado / Ejecutivo quede en blanco.
A3: Meta 2029 | B3: Mantiene meta Agosto 2029 = 30,000 y muestra ajuste en Asíncrono si la base queda debajo.
A4: Meta 2036 | B4: Puede resolver el crecimiento anual requerido para llegar a 43,000 en Agosto 2036.
A5: Tablas separadas | B5: Se conservan tablas Síncrono y Asíncrono periodo por periodo, más estado B1..B20.
A6: Seguridad de render | B6: Si hubiera un error, la pestaña mostrará el mensaje técnico en vez de quedar vacía.

Sheet LEEME_v119_pos_ejec
A1: Tema | B1: Descripción
A2: Velocidad | B2: Se quitó la tabla de agosto año a año y B1..B20 queda desactivado por default.
A3: Caché | B3: Se corrigió el caché para que los campos calculados no obliguen a recalcular todo varias veces.
A4: Solver | B4: Se redujeron iteraciones del crecimiento requerido para acelerar el render.
A5: Comparativo | B5: Se agregó una tabla con referencia: 100% Síncrono, crecimiento anual 3%, sin ajuste/meta.
A6: 50/50 | B6: Si Síncrono y Asíncrono tienen el mismo NI repartido y las mismas tasas, sus RI nuevos pueden converger.
A7: Diferencia esperada | B7: Síncrono debe diferir por el stock vivo previo y por la MT tetra histórica mientras sigan existiendo.
A8: B1..B20 | B8: Activa la vista solo cuando quieras validar el avance de cohortes por bimestre.

Sheet LEEME_v120_pos_ejec
A1: Tema | B1: Descripción
A2: Vista ligera | B2: Se quitaron las tablas inferiores de detalle anual, detalle periodo, B1..B20 y validación de insumos.
A3: Tablas conservadas | B3: Se conservan Lectura 2036, Escenario 100% Síncrono, Comparativo, Síncrono periodo por periodo, Asíncrono periodo por periodo y Tasas.
A4: Escenario sin repartir | B4: Calcula 100% Síncrono con crecimiento configurable y resta su MT 2036 contra 43,000.
A5: Aporte Asíncrono requerido | B5: Es 43,000 menos la MT 2036 del escenario 100% Síncrono.
A6: 50/50 | B6: Si Síncrono y Asíncrono reciben el mismo NI y usan las mismas tasas, pueden converger a montos parecidos.
A7: Diferencia contra 100% Síncrono | B7: El comparativo muestra 2029 y 2036 del escenario actual vs el escenario sin repartir.
A8: Parámetro nuevo | B8: crecimiento_escenario_100_sincrono, default 3%.

Sheet LEEME_v121_pos_ejec
A1: Tema | B1: Descripción
A2: Desglose 100% Síncrono | B2: Se agregó tabla Agosto año a año para el escenario sin repartir NI.
A3: Periodo por periodo 100% Síncrono | B3: Se agregó tabla completa por periodo para ver NI, RI y MT de Posgrado y Ejecutivo.
A4: Cómo llegar a 31,700 | B4: La tabla de Agosto muestra la trayectoria hasta Agosto 2036 y el total resultante.
A5: Aporte Asíncrono requerido | B5: En Agosto 2036 se muestra 43,000 menos la MT del escenario 100% Síncrono.
A6: Escenario con reparto | B6: Se conservan las tablas separadas Síncrono y Asíncrono del escenario con reparto.
A7: Exportación CSV | B7: El CSV incluye el escenario 100% Síncrono y el escenario con reparto.

Sheet reparto_ni_anual_pos_ejec
A1: anio_academico | B1: pct_ni_sincrono_posgrado | C1: pct_ni_asincrono_posgrado | D1: pct_ni_sincrono_ejecutivo | E1: pct_ni_asincrono_ejecutivo | F1: notas
A2: 2027 | B2: 100% | C2: 0% | D2: 100% | E2: 0% | F2: Base/PMP: se conserva Síncrono salvo capturas directas en NI.
A3: 2028 | B3: 100% | C3: 0% | D3: 100% | E3: 0% | F3: Base/PMP: se conserva Síncrono salvo capturas directas en NI.
A4: 2029 | B4: 100% | C4: 0% | D4: 100% | E4: 0% | F4: Base/PMP: se conserva Síncrono salvo capturas directas en NI.
A5: 2030 | B5: 0% | C5: 100% | D5: 0% | E5: 100% | F5: Default v150: nuevos NI proyectados hacia Asíncrono.
A6: 2031 | B6: 0% | C6: 100% | D6: 0% | E6: 100% | F6: Default v150: nuevos NI proyectados hacia Asíncrono.
A7: 2032 | B7: 0% | C7: 100% | D7: 0% | E7: 100% | F7: Default v150: nuevos NI proyectados hacia Asíncrono.
A8: 2033 | B8: 0% | C8: 100% | D8: 0% | E8: 100% | F8: Default v150: nuevos NI proyectados hacia Asíncrono.
A9: 2034 | B9: 0% | C9: 100% | D9: 0% | E9: 100% | F9: Default v150: nuevos NI proyectados hacia Asíncrono.
A10: 2035 | B10: 0% | C10: 100% | D10: 0% | E10: 100% | F10: Default v150: nuevos NI proyectados hacia Asíncrono.
A11: 2036 | B11: 0% | C11: 100% | D11: 0% | E11: 100% | F11: Default v150: nuevos NI proyectados hacia Asíncrono.
A12: 2037 | B12: 0% | C12: 100% | D12: 0% | E12: 100% | F12: Default v150: nuevos NI proyectados hacia Asíncrono.
A13: 2038 | B13: 0% | C13: 100% | D13: 0% | E13: 100% | F13: Default v150: nuevos NI proyectados hacia Asíncrono.
... A20: 2045 | B20: 0% | C20: 100% | D20: 0% | E20: 100% | F20: Default v150: nuevos NI proyectados hacia Asíncrono.

Sheet LEEME_v122_pos_ejec
A1: Tema | B1: Descripción
A2: Reparto anual | B2: Se agregó control año por año de % NI Síncrono para Posgrado y Ejecutivo desde 2029 hasta 2045.
A3: Complemento Asíncrono | B3: Asíncrono se calcula como 100% menos el % Síncrono de cada año.
A4: Aplicación | B4: El porcentaje de cada año académico afecta todos sus periodos desde Agosto.
A5: MT Síncrona viva | B5: Si en 2036 pones 0% Síncrono, no entran nuevos NI Síncronos, pero siguen RI vivos de cohortes anteriores y MT tetra histórica.
A6: Escenario 100% Síncrono | B6: Se mantiene el desglose de escenario sin repartir para comparar contra el escenario con reparto anual.
A7: Exportación | B7: El CSV incluye una sección reparto_anual_ni con los porcentajes usados por año.

Sheet LEEME_v123_pos_ejec
A1: Tema | B1: Descripción
A2: Sin meta 2029 | B2: Se quitó la meta 30,000 de 2029 y el ajuste automático asociado.
A3: Sin escenario 100% Síncrono | B3: Se quitó el escenario alterno 100% Síncrono y sus tablas.
A4: Distribución 2027-2035 | B4: La distribución NI por modalidad solo se captura de 2027 a 2035; default 100% Síncrono.
A5: Crecimiento por nivel | B5: Los crecimientos manuales están en bloques Posgrado y Ejecutivo.
A6: Resolver meta | B6: El modo Resolver meta calcula el crecimiento anual requerido para llegar a la meta en el año elegido.
A7: Año meta | B7: Se agregó control para elegir el año de la meta MT.
A8: Transferencia S→A | B8: Se agregó control para reclasificar MT Síncrona viva como Asíncrona desde un año; la MT total no cambia.
A9: Tablas por nivel | B9: Las tablas inferiores ahora son Posgrado y Ejecutivo, con columnas Síncrono/Asíncrono NI, RI y MT.
A10: Tasas | B10: Las tasas se muestran en dos tablas lado a lado: Posgrado y Ejecutivo.

Sheet crecimiento_bloques_pos_ejec
A1: nivel | B1: anio_inicio | C1: anio_fin | D1: bloque | E1: crecimiento_anual
A2: Posgrado | B2: 2030 | C2: 2034 | D2: 2030–2034 | E2: 3%
A3: Posgrado | B3: 2035 | C3: 2040 | D3: 2035–2040 | E3: 3%
A4: Posgrado | B4: 2041 | C4: 2043 | D4: 2041–2043 | E4: 3%
A5: Posgrado | B5: 2044 | C5: 2045 | D5: 2044–2045 | E5: 3%
A6: Ejecutivo | B6: 2030 | C6: 2034 | D6: 2030–2034 | E6: 3%
A7: Ejecutivo | B7: 2035 | C7: 2040 | D7: 2035–2040 | E7: 3%
A8: Ejecutivo | B8: 2041 | C8: 2043 | D8: 2041–2043 | E8: 3%
A9: Ejecutivo | B9: 2044 | C9: 2045 | D9: 2044–2045 | E9: 3%

Sheet tetra_historica_pos_ejec
A1: nivel | B1: mt_tetra_inicial | C1: egresos_anuales_tetra | D1: periodos_salida | E1: notas
A2: Posgrado | B2: 9800 | C2: 5000 | D2: Agosto, Enero, Junio | E2: Suma a MT Síncrona mientras exista; no es RI bimestral.
A3: Ejecutivo | B3: 6100 | C3: 1200 | D3: Agosto, Enero, Junio | E3: Suma a MT Síncrona mientras exista; no es RI bimestral.

Sheet LEEME_v124_pos_ejec
A1: Tema | B1: Descripción
A2: Parámetros limpios | B2: Se quitó meta Agosto 2029, % NI Síncrono default y escenario 100% Síncrono de la UI.
A3: Meta | B3: Ahora se captura MT objetivo y año objetivo.
A4: Transferencia S→A | B4: Se puede elegir el año en que la MT Síncrona viva pasa a Asíncrona. La MT total no cambia.
A5: Crecimiento por bloques | B5: Se agregó bloque por nivel: 2030–2034, 2035–2040, 2041–2043, 2044–2045.
A6: Distribución NI | B6: Solo 2027–2035. Default 100% Síncrono y 0% Asíncrono.
A7: Tetra histórica | B7: Sale de parámetros/crecimiento y queda en sección propia. Suma a MT mientras exista.
A8: Tablas por nivel | B8: Posgrado y Ejecutivo muestran una fila de Síncrono y otra de Asíncrono por periodo.
A9: Columnas de tabla | B9: Año calendario, año académico, periodo, modalidad, NI, RI, MT tetra, MT transferida y MT.
A10: Tasas | B10: Se muestran en dos bloques lado a lado: Posgrado y Ejecutivo.
A11: Exportación | B11: El CSV incluye configuración, crecimientos por bloque, distribución anual y desglose por nivel/periodo/modalidad.

Sheet LEEME_v125_pos_ejec
A1: Tema | B1: Descripción
A2: Cambio pequeño | B2: Se quitó de Parámetros y crecimiento el control Meta MT Agosto 2029 / 30,000.
A3: Parámetros vigentes | B3: Solo quedan MT objetivo, año objetivo, transferencia S→A y crecimiento por bloques.

Sheet pmp_mt_pos_ejec
A1: anio_calendario | B1: periodo | C1: nivel | D1: modalidad | E1: mt_pmp | F1: notas | H1: anio_calendario | I1: periodo | J1: nivel | K1: modalidad | L1: mt_pmp
A2: 2026 | B2: Agosto | C2: Posgrado | D2: Total | E2: 14561 | F2: Captura la MT PMP de Agosto 2026 para Posgrado. | H2: 2027 | I2: Agosto | J2: Total | K2: Total
A3: 2026 | B3: Agosto | C3: Ejecutivo | D3: Total | E3: 10207 | F3: Captura la MT PMP de Agosto 2026 para Ejecutivo. | H3: 2028 | I3: Agosto | J3: Total | K3: Total
A4: 2027 | B4: Agosto | C4: Posgrado | D4: Total | E4: 15271 | F4: Captura la MT PMP de Agosto 2027 para Posgrado. | H4: 2029 | I4: Agosto | J4: Total | K4: Total | L4: 30000
A5: 2027 | B5: Agosto | C5: Ejecutivo | D5: Total | E5: 10729 | F5: Captura la MT PMP de Agosto 2027 para Ejecutivo. | H5: Nota | I5: El caso base lee la tabla principal A:F. Este bloque es solo referencia visual.
A6: 2028 | B6: Agosto | C6: Posgrado | D6: Total | E6: 16108 | F6: Captura la MT PMP de Agosto 2028 para Posgrado.
A7: 2028 | B7: Agosto | C7: Ejecutivo | D7: Total | E7: 12095 | F7: Captura la MT PMP de Agosto 2028 para Ejecutivo.
A8: 2029 | B8: Agosto | C8: Posgrado | D8: Total | E8: 17341 | F8: Captura la MT PMP de Agosto 2029 para Posgrado.
A9: 2029 | B9: Agosto | C9: Ejecutivo | D9: Total | E9: 12757 | F9: Captura la MT PMP de Agosto 2029 para Ejecutivo.
A10: 2029 | B10: Agosto | C10: Total | D10: Total | E10: 30098 | F10: Fallback: si no capturas Posgrado/Ejecutivo, el caso base usa 30,000 total en Agosto 2029.
A41: 2029 | B41: Octubre | C41: Ejecutivo | D41: Total | F41: Captura aquí la MT PMP oficial. Se usa hasta 2029. Modalidad puede ser Total, Síncrono o Asíncrono.
A42: 2027 | B42: Agosto | C42: Total | D42: Total | F42: PMP/base Agosto 2027. Captura MT total o por nivel si la tienes.
A43: 2028 | B43: Agosto | C43: Total | D43: Total | F43: PMP/base Agosto 2028. Captura MT total o por nivel si la tienes.
A44: 2029 | B44: Agosto | C44: Total | D44: Total | E44: 30000 | F44: PMP/base Agosto 2029 usado por el caso base fijo.

Sheet LEEME_v127_pos_ejec
A1: Tema | B1: Descripción
A2: MT bimestral | B2: La tabla Comparación vs 2026 ahora muestra MT bimestral = MT total - MT tetra histórica.
A3: PMP MT | B3: Captura la MT oficial en la hoja pmp_mt_pos_ejec.
A4: Columnas PMP | B4: anio_calendario, periodo, nivel, modalidad, mt_pmp.
A5: Uso PMP | B5: Si hay valores, el simulador los usa como MT visible hasta 2029.
A6: Crecimiento | B6: El crecimiento manual o calculado empieza desde Enero 2030 por año calendario.
A7: Modo manual | B7: Debajo de Comparación vs 2026 se muestra si la meta se alcanza y en qué periodo/año.
A8: PMP en tablas | B8: Las tablas por nivel muestran columna PMP = Sí cuando esa fila usa MT capturada.

Sheet caso_base_fijo_3pct
A1: Campo | B1: Valor | C1: Notas
A2: Caso | B2: Síncrono 100% + 3% anual | C2: Referencia fija del simulador.
A3: Periodo | B3: 2029 a 2045 | C3: La tabla calculada se descarga desde el HTML.
A4: Crecimiento Posgrado | B4: 3% | C4: Fijo para el caso base.
A5: Crecimiento Ejecutivo | B5: 3% | C5: Fijo para el caso base.
A6: Distribución modalidad | B6: 100% Síncrono / 0% Asíncrono | C6: No usa los controles del escenario editable.
A7: Transferencia S→A | B7: Nunca | C7: No reclasifica matrícula.
A8: Meta referencia | B8: 43,000 | C8: Diferencia contra esta meta.
A9: Tasas reales | B9: tasas_ri_bimestre_pos_ejec | C9: Edita las tasas aquí y vuelve a cargar el Excel en el HTML.

Sheet instrucciones_tasas_reales
A1: Dónde capturar | B1: Hoja | C1: Qué cambiar | D1: Notas
A2: Tasas reales | B2: tasas_ri_bimestre_pos_ejec | C2: Columna de tasa | D2: Una fila por nivel, modalidad y avance B origen → B destino.
A3: Nivel | B3: tasas_ri_bimestre_pos_ejec | C3: Posgrado o Ejecutivo | D3: Conserva el texto del nivel.
A4: Modalidad | B4: tasas_ri_bimestre_pos_ejec | C4: Síncrono o Asíncrono | D4: Puedes tener tasas distintas por modalidad.
A5: Bimestre origen | B5: tasas_ri_bimestre_pos_ejec | C5: B1, B2, B3... | D5: Representa de qué bimestre avanza la cohorte.
A6: Tasa | B6: tasas_ri_bimestre_pos_ejec | C6: Ej. 85% o 0.85 | D6: El simulador acepta porcentajes o decimales.
A7: Después de editar | B7: HTML | C7: Vuelve a cargar el Excel | D7: El simulador recalcula con las tasas nuevas.

Sheet LEEME_v129_pos_ejec
A1: Tema | B1: Descripción
A2: Caso base fijo | B2: Se agregó referencia fija: 100% Síncrono, crecimiento 3% anual, 2029-2045.
A3: Diferencia 43,000 | B3: El caso base calcula diferencia anual contra 43,000.
A4: Exportación Excel | B4: El HTML tiene botón para descargar un Excel con caso base y escenario actual.
A5: Tasas reales | B5: Se capturan en tasas_ri_bimestre_pos_ejec.
A6: Escenario editable | B6: Los parámetros editables siguen funcionando aparte del caso base fijo.
A7: PMP hasta 2029 | B7: La hoja pmp_mt_pos_ejec sigue siendo el lugar para capturar MT PMP oficial hasta 2029.
A8: Recalcular | B8: Después de modificar el Excel, cárgalo de nuevo en el HTML.

Sheet LEEME_v136_pos_ejec
A1: Tema | B1: Descripción
A2: Corrección error | B2: Se reemplazó la referencia inválida BASE_CASE_END_YEAR_V129 por lógica propia v136.
A3: Caso base visible | B3: La tabla Caso base fijo muestra 2027 a 2045.
A4: PMP hasta 2029 | B4: El caso base toma PMP/base hasta 2029; Agosto 2029 queda en 30,000 si no hay otro valor.
A5: Proyección | B5: Desde Enero 2030 usa tasas_ri_bimestre_pos_ejec y crecimiento fijo 3%.
A6: Excel descargable | B6: El botón descarga un .xlsx con Caso_base_3pct y Caso_base_Ene2030.
A7: Dónde editar PMP | B7: Hoja pmp_mt_pos_ejec, columnas A:F, campo mt_pmp.
A8: Dónde editar tasas | B8: Hoja tasas_ri_bimestre_pos_ejec, columna tasa.

Sheet mt_pos_ejec
A1: anio_calendario | B1: periodo | C1: nivel | D1: modalidad | E1: MT | F1: notas
A2: 2026 | B2: Agosto | C2: Total | D2: Total | F2: Captura aquí la MT PMP/base de agosto 2026.
A3: 2027 | B3: Agosto | C3: Total | D3: Total | F3: Captura aquí la MT PMP/base de agosto 2027.
A4: 2028 | B4: Agosto | C4: Total | D4: Total | F4: Captura aquí la MT PMP/base de agosto 2028.
A5: 2029 | B5: Agosto | C5: Total | D5: Total | E5: 30000 | F5: PMP/base Agosto 2029 usado por el caso base fijo.

Sheet LEEME_v137_pos_ejec
A1: Tema | B1: Descripción
A2: Ajuste solicitado | B2: El caso base lee 2026-2029 desde la hoja mt_pos_ejec.
A3: Agosto 2029 | B3: Si mt_pos_ejec no trae otro valor, se usa 30,000 MT.
A4: Proyección | B4: Desde Enero 2030 sigue con tasas_ri_bimestre_pos_ejec y crecimiento 3%.
A5: Botón Excel | B5: Se conserva la exportación de Excel del caso base y escenario editable.
A6: Dónde editar MT base | B6: Hoja mt_pos_ejec, columna MT.
A7: Dónde editar tasas | B7: Hoja tasas_ri_bimestre_pos_ejec, columna tasa.

Sheet internacional_base
A1: anio | B1: NI | C1: RI_Agosto_necesario | D1: MT | E1: notas
A2: 2026 | B2: 0 | C2: =MAX(0,D2-(B2/5)) -> 0 | D2: 0 | E2: Captura NI, RI y MT Internacional para 2026. Hasta 2036 se lee como base.
A3: 2027 | B3: 307 | C3: =MAX(0,D3-(B3/5)) -> 193.576 | D3: 254.976 | E3: Captura NI, RI y MT Internacional para 2027. Hasta 2036 se lee como base.
A4: 2028 | B4: 1162 | C4: =MAX(0,D4-(B4/5)) -> 949.58656 | D4: 1181.9866 | E4: Captura NI, RI y MT Internacional para 2028. Hasta 2036 se lee como base.
A5: 2029 | B5: 1854 | C5: =MAX(0,D5-(B5/5)) -> 2159.1126 | D5: 2529.9126 | E5: Captura NI, RI y MT Internacional para 2029. Hasta 2036 se lee como base.
A6: 2030 | B6: 1989 | C6: =MAX(0,D6-(B6/5)) -> 3424.6651 | D6: 3822.4651 | E6: Captura NI, RI y MT Internacional para 2030. Hasta 2036 se lee como base.
A7: 2031 | B7: 2349 | C7: =MAX(0,D7-(B7/5)) -> 4864.9431 | D7: 5334.7431 | E7: Captura NI, RI y MT Internacional para 2031. Hasta 2036 se lee como base.
A8: 2032 | B8: 3667 | C8: =MAX(0,D8-(B8/5)) -> 6969.5934 | D8: 7702.9934 | E8: Captura NI, RI y MT Internacional para 2032. Hasta 2036 se lee como base.
A9: 2033 | B9: 3845 | C9: =MAX(0,D9-(B9/5)) -> 8847.8482 | D9: 9616.8482 | E9: Captura NI, RI y MT Internacional para 2033. Hasta 2036 se lee como base.
A10: 2034 | B10: 4543 | C10: =MAX(0,D10-(B10/5)) -> 10903.392 | D10: 11811.992 | E10: Captura NI, RI y MT Internacional para 2034. Hasta 2036 se lee como base.
A11: 2035 | B11: 4543 | C11: =MAX(0,D11-(B11/5)) -> 12902.502 | D11: 13811.102 | E11: Captura NI, RI y MT Internacional para 2035. Hasta 2036 se lee como base.
A12: 2036 | B12: 4543 | C12: =MAX(0,D12-(B12/5)) -> 15562.886 | D12: 16471.486 | E12: Captura NI, RI y MT Internacional para 2036. Hasta 2036 se lee como base.

Sheet internacional_crecimiento
A1: anio | B1: crecimiento_NI | C1: crecimiento_RI | D1: crecimiento_MT | E1: notas
A2: 2037 | B2: 0.03 | C2: 0.03 | D2: 0.03 | E2: Default 3%. Puedes modificarlo en Excel o en el simulador.
A3: 2038 | B3: 0.03 | C3: 0.03 | D3: 0.03 | E3: Default 3%. Puedes modificarlo en Excel o en el simulador.
A4: 2039 | B4: 0.03 | C4: 0.03 | D4: 0.03 | E4: Default 3%. Puedes modificarlo en Excel o en el simulador.
A5: 2040 | B5: 0.03 | C5: 0.03 | D5: 0.03 | E5: Default 3%. Puedes modificarlo en Excel o en el simulador.
A6: 2041 | B6: 0.03 | C6: 0.03 | D6: 0.03 | E6: Default 3%. Puedes modificarlo en Excel o en el simulador.
A7: 2042 | B7: 0.03 | C7: 0.03 | D7: 0.03 | E7: Default 3%. Puedes modificarlo en Excel o en el simulador.
A8: 2043 | B8: 0.03 | C8: 0.03 | D8: 0.03 | E8: Default 3%. Puedes modificarlo en Excel o en el simulador.
A9: 2044 | B9: 0.03 | C9: 0.03 | D9: 0.03 | E9: Default 3%. Puedes modificarlo en Excel o en el simulador.
A10: 2045 | B10: 0.03 | C10: 0.03 | D10: 0.03 | E10: Default 3%. Puedes modificarlo en Excel o en el simulador.

Sheet LEEME_v138_pos_ejec
A1: Tema | B1: Descripción
A2: Base usada | B2: Versión v137.
A3: Caso base | B3: La tabla lee PMP 2026-2029 desde pmp_mt_pos_ejec y proyecta desde Enero 2030 con tasas + 3%.
A4: Caso base visual | B4: Se quitó Fuente, se quitó MT base leída y se quitó el detalle desde Enero 2030.
A5: Dif vs 43,000 | B5: Queda en blanco desde 2036 en adelante.
A6: PMP por nivel | B6: Captura en pmp_mt_pos_ejec la MT PMP de Agosto 2026-2029 por Posgrado y Ejecutivo.
A7: Desglose por nivel | B7: Las tablas Posgrado/Ejecutivo periodo por periodo usan pmp_mt_pos_ejec para igualar PMP hasta 2029 cuando esté capturado.
A8: Internacional base | B8: Captura NI, RI y MT hasta 2036 en internacional_base.
A9: Internacional crecimiento | B9: 2037-2045 usa internacional_crecimiento con default 3% editable.
A10: Suma Internacional | B10: Checkbox en Posgrado/Ejecutivo e Internacional para incluir o excluir Internacional en MT total institución 2045.
A11: Descarga Excel | B11: El botón Descarga Excel Posgrado/Ejecutivo incluye caso base, escenario editable e Internacional.
A12: Tasas RI | B12: Se conservan en tasas_ri_bimestre_pos_ejec.

Sheet internacional_bimestres
A1: Hoja sustituida | B1: Usar internacional_agosto
A2: Motivo | B2: Ya no se repiten los 5 bimestres; solo se conserva Agosto.
A3: Regla | B3: NI_Agosto = NI_anual / 5; RI_Agosto_necesario = MT_objetivo - NI_Agosto.

Sheet LEEME_v139_internacional
A1: Tema | B1: Descripción
A2: Base usada | B2: v138 + Excel cargado por el usuario modelo_simulador(9).xlsx.
A3: Internacional anual | B3: Se toman NI y MT de internacional_base.
A4: RI necesario anual | B4: En internacional_base se calcula RI_necesario = MT - NI.
A5: Bimestres | B5: Nueva hoja internacional_bimestres: NI anual se divide entre 5 bimestres.
A6: RI bimestral | B6: RI_necesario_bimestre = MT objetivo anual - NI_bimestre.
A7: Descarga | B7: El botón del simulador exporta Internacional_anual e Internacional_bimestres.

Sheet internacional_agosto
A1: anio | B1: periodo | C1: tipo | D1: NI_anual | E1: MT_objetivo | F1: NI_Agosto | G1: RI_Agosto_necesario | H1: MT_Agosto
A2: 2026 | B2: Agosto | C2: ="Base Excel" -> Base Excel | D2: =IFERROR(INDEX(internacional_base!$B:$B,MATCH(A2,internacional_base!$A:$A,0)),0) -> 0 | E2: =IFERROR(INDEX(internacional_base!$D:$D,MATCH(A2,internacional_base!$A:$A,0)),0) -> 0 | F2: =D2/5 -> 0 | G2: =MAX(0,E2-F2) -> 0 | H2: =F2+G2 -> 0
A3: 2027 | B3: Agosto | C3: ="Base Excel" -> Base Excel | D3: =IFERROR(INDEX(internacional_base!$B:$B,MATCH(A3,internacional_base!$A:$A,0)),0) -> 307 | E3: =IFERROR(INDEX(internacional_base!$D:$D,MATCH(A3,internacional_base!$A:$A,0)),0) -> 254.976 | F3: =D3/5 -> 61.4 | G3: =MAX(0,E3-F3) -> 193.576 | H3: =F3+G3 -> 254.976
A4: 2028 | B4: Agosto | C4: ="Base Excel" -> Base Excel | D4: =IFERROR(INDEX(internacional_base!$B:$B,MATCH(A4,internacional_base!$A:$A,0)),0) -> 1162 | E4: =IFERROR(INDEX(internacional_base!$D:$D,MATCH(A4,internacional_base!$A:$A,0)),0) -> 1181.9866 | F4: =D4/5 -> 232.4 | G4: =MAX(0,E4-F4) -> 949.58656 | H4: =F4+G4 -> 1181.9866
A5: 2029 | B5: Agosto | C5: ="Base Excel" -> Base Excel | D5: =IFERROR(INDEX(internacional_base!$B:$B,MATCH(A5,internacional_base!$A:$A,0)),0) -> 1854 | E5: =IFERROR(INDEX(internacional_base!$D:$D,MATCH(A5,internacional_base!$A:$A,0)),0) -> 2529.9126 | F5: =D5/5 -> 370.8 | G5: =MAX(0,E5-F5) -> 2159.1126 | H5: =F5+G5 -> 2529.9126
A6: 2030 | B6: Agosto | C6: ="Base Excel" -> Base Excel | D6: =IFERROR(INDEX(internacional_base!$B:$B,MATCH(A6,internacional_base!$A:$A,0)),0) -> 1989 | E6: =IFERROR(INDEX(internacional_base!$D:$D,MATCH(A6,internacional_base!$A:$A,0)),0) -> 3822.4651 | F6: =D6/5 -> 397.8 | G6: =MAX(0,E6-F6) -> 3424.6651 | H6: =F6+G6 -> 3822.4651
A7: 2031 | B7: Agosto | C7: ="Base Excel" -> Base Excel | D7: =IFERROR(INDEX(internacional_base!$B:$B,MATCH(A7,internacional_base!$A:$A,0)),0) -> 2349 | E7: =IFERROR(INDEX(internacional_base!$D:$D,MATCH(A7,internacional_base!$A:$A,0)),0) -> 5334.7431 | F7: =D7/5 -> 469.8 | G7: =MAX(0,E7-F7) -> 4864.9431 | H7: =F7+G7 -> 5334.7431
A8: 2032 | B8: Agosto | C8: ="Base Excel" -> Base Excel | D8: =IFERROR(INDEX(internacional_base!$B:$B,MATCH(A8,internacional_base!$A:$A,0)),0) -> 3667 | E8: =IFERROR(INDEX(internacional_base!$D:$D,MATCH(A8,internacional_base!$A:$A,0)),0) -> 7702.9934 | F8: =D8/5 -> 733.4 | G8: =MAX(0,E8-F8) -> 6969.5934 | H8: =F8+G8 -> 7702.9934
A9: 2033 | B9: Agosto | C9: ="Base Excel" -> Base Excel | D9: =IFERROR(INDEX(internacional_base!$B:$B,MATCH(A9,internacional_base!$A:$A,0)),0) -> 3845 | E9: =IFERROR(INDEX(internacional_base!$D:$D,MATCH(A9,internacional_base!$A:$A,0)),0) -> 9616.8482 | F9: =D9/5 -> 769 | G9: =MAX(0,E9-F9) -> 8847.8482 | H9: =F9+G9 -> 9616.8482
A10: 2034 | B10: Agosto | C10: ="Base Excel" -> Base Excel | D10: =IFERROR(INDEX(internacional_base!$B:$B,MATCH(A10,internacional_base!$A:$A,0)),0) -> 4543 | E10: =IFERROR(INDEX(internacional_base!$D:$D,MATCH(A10,internacional_base!$A:$A,0)),0) -> 11811.992 | F10: =D10/5 -> 908.6 | G10: =MAX(0,E10-F10) -> 10903.392 | H10: =F10+G10 -> 11811.992
A11: 2035 | B11: Agosto | C11: ="Base Excel" -> Base Excel | D11: =IFERROR(INDEX(internacional_base!$B:$B,MATCH(A11,internacional_base!$A:$A,0)),0) -> 4543 | E11: =IFERROR(INDEX(internacional_base!$D:$D,MATCH(A11,internacional_base!$A:$A,0)),0) -> 13811.102 | F11: =D11/5 -> 908.6 | G11: =MAX(0,E11-F11) -> 12902.502 | H11: =F11+G11 -> 13811.102
A12: 2036 | B12: Agosto | C12: ="Base Excel" -> Base Excel | D12: =IFERROR(INDEX(internacional_base!$B:$B,MATCH(A12,internacional_base!$A:$A,0)),0) -> 4543 | E12: =IFERROR(INDEX(internacional_base!$D:$D,MATCH(A12,internacional_base!$A:$A,0)),0) -> 16471.486 | F12: =D12/5 -> 908.6 | G12: =MAX(0,E12-F12) -> 15562.886 | H12: =F12+G12 -> 16471.486
A13: 2037 | B13: Agosto | C13: ="Proyección" -> Proyección | D13: =D12*(1+IFERROR(INDEX(internacional_crecimiento!$B:$B,MATCH(A13,internacional_crecimiento!$A:$A,0)),3%)) -> 4679.29 | E13: =E12*(1+IFERROR(INDEX(internacional_crecimiento!$D:$D,MATCH(A13,internacional_crecimiento!$A:$A,0)),3%)) -> 16965.631 | F13: =D13/5 -> 935.858 | G13: =MAX(0,E13-F13) -> 16029.773 | H13: =F13+G13 -> 16965.631
A14: 2038 | B14: Agosto | C14: ="Proyección" -> Proyección | D14: =D13*(1+IFERROR(INDEX(internacional_crecimiento!$B:$B,MATCH(A14,internacional_crecimiento!$A:$A,0)),3%)) -> 4819.6687 | E14: =E13*(1+IFERROR(INDEX(internacional_crecimiento!$D:$D,MATCH(A14,internacional_crecimiento!$A:$A,0)),3%)) -> 17474.6 | F14: =D14/5 -> 963.93374 | G14: =MAX(0,E14-F14) -> 16510.666 | H14: =F14+G14 -> 17474.6
A15: 2039 | B15: Agosto | C15: ="Proyección" -> Proyección | D15: =D14*(1+IFERROR(INDEX(internacional_crecimiento!$B:$B,MATCH(A15,internacional_crecimiento!$A:$A,0)),3%)) -> 4964.2588 | E15: =E14*(1+IFERROR(INDEX(internacional_crecimiento!$D:$D,MATCH(A15,internacional_crecimiento!$A:$A,0)),3%)) -> 17998.838 | F15: =D15/5 -> 992.85175 | G15: =MAX(0,E15-F15) -> 17005.986 | H15: =F15+G15 -> 17998.838
A16: 2040 | B16: Agosto | C16: ="Proyección" -> Proyección | D16: =D15*(1+IFERROR(INDEX(internacional_crecimiento!$B:$B,MATCH(A16,internacional_crecimiento!$A:$A,0)),3%)) -> 5113.1865 | E16: =E15*(1+IFERROR(INDEX(internacional_crecimiento!$D:$D,MATCH(A16,internacional_crecimiento!$A:$A,0)),3%)) -> 18538.803 | F16: =D16/5 -> 1022.6373 | G16: =MAX(0,E16-F16) -> 17516.166 | H16: =F16+G16 -> 18538.803
A17: 2041 | B17: Agosto | C17: ="Proyección" -> Proyección | D17: =D16*(1+IFERROR(INDEX(internacional_crecimiento!$B:$B,MATCH(A17,internacional_crecimiento!$A:$A,0)),3%)) -> 5266.5821 | E17: =E16*(1+IFERROR(INDEX(internacional_crecimiento!$D:$D,MATCH(A17,internacional_crecimiento!$A:$A,0)),3%)) -> 19094.967 | F17: =D17/5 -> 1053.3164 | G17: =MAX(0,E17-F17) -> 18041.651 | H17: =F17+G17 -> 19094.967
A18: 2042 | B18: Agosto | C18: ="Proyección" -> Proyección | D18: =D17*(1+IFERROR(INDEX(internacional_crecimiento!$B:$B,MATCH(A18,internacional_crecimiento!$A:$A,0)),3%)) -> 5424.5796 | E18: =E17*(1+IFERROR(INDEX(internacional_crecimiento!$D:$D,MATCH(A18,internacional_crecimiento!$A:$A,0)),3%)) -> 19667.816 | F18: =D18/5 -> 1084.9159 | G18: =MAX(0,E18-F18) -> 18582.9 | H18: =F18+G18 -> 19667.816
A19: 2043 | B19: Agosto | C19: ="Proyección" -> Proyección | D19: =D18*(1+IFERROR(INDEX(internacional_crecimiento!$B:$B,MATCH(A19,internacional_crecimiento!$A:$A,0)),3%)) -> 5587.317 | E19: =E18*(1+IFERROR(INDEX(internacional_crecimiento!$D:$D,MATCH(A19,internacional_crecimiento!$A:$A,0)),3%)) -> 20257.85 | F19: =D19/5 -> 1117.4634 | G19: =MAX(0,E19-F19) -> 19140.387 | H19: =F19+G19 -> 20257.85
A20: 2044 | B20: Agosto | C20: ="Proyección" -> Proyección | D20: =D19*(1+IFERROR(INDEX(internacional_crecimiento!$B:$B,MATCH(A20,internacional_crecimiento!$A:$A,0)),3%)) -> 5754.9365 | E20: =E19*(1+IFERROR(INDEX(internacional_crecimiento!$D:$D,MATCH(A20,internacional_crecimiento!$A:$A,0)),3%)) -> 20865.586 | F20: =D20/5 -> 1150.9873 | G20: =MAX(0,E20-F20) -> 19714.599 | H20: =F20+G20 -> 20865.586
A21: 2045 | B21: Agosto | C21: ="Proyección" -> Proyección | D21: =D20*(1+IFERROR(INDEX(internacional_crecimiento!$B:$B,MATCH(A21,internacional_crecimiento!$A:$A,0)),3%)) -> 5927.5846 | E21: =E20*(1+IFERROR(INDEX(internacional_crecimiento!$D:$D,MATCH(A21,internacional_crecimiento!$A:$A,0)),3%)) -> 21491.554 | F21: =D21/5 -> 1185.5169 | G21: =MAX(0,E21-F21) -> 20306.037 | H21: =F21+G21 -> 21491.554

Sheet caso_base_meta_2036
A1: anio | B1: concepto | C1: valor | D1: nota | E1: color
A2: 2036 | B2: Año meta | C2: Ver tabla Caso base del simulador | D2: Se marca en amarillo en pantalla. | E2: Amarillo
A3: 2036 | B3: MT Total Ago | C3: Se calcula en el simulador / Excel descargado | D3: Usar para estimar gap contra 43,000. | E3: Amarillo
A4: 2036 | B4: Asíncrono requerido para 43,000 | C4: 43,000 - MT Total Ago | D4: En el Excel descargado queda como columna. | E4: Amarillo
A5: 2037 | B5: Gap vs 43,000 | C5: En blanco | D5: Desde 2037 ya no se muestra ese cálculo.

Sheet espacio_connect
A1: campo | B1: valor_default | C1: descripcion | D1: donde_se_edita | E1: notas
A2: tipo_proyecto | B2: Espacio Connect | C2: Nuevo tipo de proyecto de Inversión. | D2: Pestaña Inversión | E2: Aplica a Campus en línea.
A3: campus | B3: Campus en línea | C3: Campus impactado por defecto. | D3: Pestaña Inversión | E3: Se usa para identificar el proyecto.
A4: nivel | B4: Posgrado + Ejecutivo | C4: Puede ser Posgrado, Ejecutivo o Posgrado + Ejecutivo. | D4: Pestaña Inversión | E4: Si es Posgrado + Ejecutivo, se reparte 50/50.
A5: NI | B5: Editable por año | C5: NI aportado por el proyecto. | D5: Tabla NI proyecto | E5: Se suma a la pestaña Posgrado/Ejecutivo.

Sheet LEEME_v140
A1: Tema | B1: Descripción
A2: Internacional | B2: Se eliminó la repetición por 5 bimestres; solo queda Agosto.
A3: NI Internacional | B3: NI_Agosto = NI anual / 5.
A4: RI Internacional | B4: RI_Agosto_necesario = MT objetivo - NI_Agosto.
A5: Caso base | B5: Gap vs 43,000 se conserva hasta 2036; desde 2037 queda en blanco.
A6: Año 2036 | B6: La fila 2036 queda resaltada en amarillo en la tabla del simulador y documentada en caso_base_meta_2036.
A7: Espacio Connect | B7: Nuevo tipo de proyecto en Inversión, aplicado a Campus en línea.
A8: Posgrado/Ejecutivo | B8: NI de Espacio Connect se suma a la simulación de Posgrado/Ejecutivo.
A9: Excel descargable | B9: Incluye Caso_base_3pct, Internacional_Agosto y Espacio_Connect.
A10: Validación | B10: No se detectaron errores de fórmula en el workbook.

Sheet LEEME_v141
A1: Tema | B1: Descripción
A2: Base | B2: v140 con corrección menor de workbook.
A3: Corrección | B3: Se quitó una fórmula textual que Excel interpretaba como fórmula en caso_base_meta_2036.
A4: Validación | B4: Se volvió a escanear el workbook sin errores de fórmula.
A5: Simulador | B5: Se conserva la lógica de Internacional Agosto y Espacio Connect.

Sheet caso_base_formato_v142
A1: anio | B1: nivel | C1: NI_Agosto | D1: RI_bimestral_Agosto | E1: MT_tetra_historica | F1: MT_Agosto | G1: gap_vs_43000 | H1: asincrono_requerido_para_43000 | I1: marca_2036
A2: 2036 | B2: Posgrado | I2: Año meta 2036
A3: 2036 | B3: Ejecutivo | I3: Año meta 2036
A4: 2036 | B4: Total | G4: 43,000 - MT Total | H4: Gap positivo | I4: Año meta 2036
A5: 2037 | B5: Posgrado
A6: 2037 | B6: Ejecutivo
A7: 2037 | B7: Total | I7: Gap en blanco desde 2037

Sheet LEEME_v142
A1: Tema | B1: Descripción
A2: Caso base | B2: La tabla del simulador ahora muestra Posgrado, Ejecutivo y Total como filas.
A3: Columnas de caso base | B3: Incluye NI Agosto, RI bimestral Agosto, MT tetra histórica y MT Agosto por nivel.
A4: 2036 | B4: Se conserva resaltado en amarillo y con gap/asíncrono requerido en la fila Total.
A5: 2037 en adelante | B5: Gap vs 43,000 queda en blanco.
A6: Tablas por nivel | B6: Posgrado y Ejecutivo ahora muestran solo Agosto, hasta Agosto 2045.
A7: Cálculo interno | B7: Los bimestres intermedios se siguen calculando internamente.
A8: Descarga Excel | B8: Exporta Caso_base_por_nivel, Posgrado_Agosto y Ejecutivo_Agosto.

Sheet ri_bimestral_pos_ejec
A1: anio_academico | B1: periodo | C1: anio_calendario | D1: nivel | E1: modalidad | F1: RI_bimestral | G1: notas
A2: 2026 | B2: Agosto | C2: 2026 | D2: Posgrado | E2: Síncrono | F2: 0 | G2: Captura aquí el RI bimestral total. No es stock por B2/B3; es RI total del periodo.
A3: 2026 | B3: Agosto | C3: 2026 | D3: Posgrado | E3: Asíncrono | F3: 0 | G3: Captura aquí el RI bimestral total. No es stock por B2/B3; es RI total del periodo.
A4: 2026 | B4: Agosto | C4: 2026 | D4: Ejecutivo | E4: Síncrono | F4: 2023 | G4: Captura aquí el RI bimestral total. No es stock por B2/B3; es RI total del periodo.
A5: 2026 | B5: Agosto | C5: 2026 | D5: Ejecutivo | E5: Asíncrono | G5: Captura aquí el RI bimestral total. No es stock por B2/B3; es RI total del periodo.
A6: 2026 | B6: Octubre | C6: 2026 | D6: Posgrado | E6: Síncrono | F6: 1697 | G6: Captura aquí el RI bimestral total. No es stock por B2/B3; es RI total del periodo.
A7: 2026 | B7: Octubre | C7: 2026 | D7: Posgrado | E7: Asíncrono | G7: Captura aquí el RI bimestral total. No es stock por B2/B3; es RI total del periodo.
A8: 2026 | B8: Octubre | C8: 2026 | D8: Ejecutivo | E8: Síncrono | F8: 2702 | G8: Captura aquí el RI bimestral total. No es stock por B2/B3; es RI total del periodo.
A9: 2026 | B9: Octubre | C9: 2026 | D9: Ejecutivo | E9: Asíncrono | G9: Captura aquí el RI bimestral total. No es stock por B2/B3; es RI total del periodo.
A10: 2026 | B10: Enero | C10: 2027 | D10: Posgrado | E10: Síncrono | F10: 3107 | G10: Captura aquí el RI bimestral total. No es stock por B2/B3; es RI total del periodo.
A11: 2026 | B11: Enero | C11: 2027 | D11: Posgrado | E11: Asíncrono | G11: Captura aquí el RI bimestral total. No es stock por B2/B3; es RI total del periodo.
A12: 2027 | B12: Enero | C12: 2027 | D12: Ejecutivo | E12: Síncrono | F12: 3104 | G12: Captura aquí el RI bimestral total. No es stock por B2/B3; es RI total del periodo.
A13: 2027 | B13: Enero | C13: 2027 | D13: Ejecutivo | E13: Asíncrono | G13: Captura aquí el RI bimestral total. No es stock por B2/B3; es RI total del periodo.
A14: 2026 | B14: Marzo | C14: 2027 | D14: Posgrado | E14: Síncrono | F14: 4809 | G14: Captura aquí el RI bimestral total. No es stock por B2/B3; es RI total del periodo.
A15: 2026 | B15: Marzo | C15: 2027 | D15: Posgrado | E15: Asíncrono | G15: Captura aquí el RI bimestral total. No es stock por B2/B3; es RI total del periodo.
A16: 2027 | B16: Marzo | C16: 2027 | D16: Ejecutivo | E16: Síncrono | F16: 3528 | G16: Captura aquí el RI bimestral total. No es stock por B2/B3; es RI total del periodo.
A17: 2027 | B17: Marzo | C17: 2027 | D17: Ejecutivo | E17: Asíncrono | G17: Captura aquí el RI bimestral total. No es stock por B2/B3; es RI total del periodo.
A18: 2026 | B18: Junio | C18: 2027 | D18: Posgrado | E18: Síncrono | F18: 5886 | G18: Captura aquí el RI bimestral total. No es stock por B2/B3; es RI total del periodo.
A19: 2026 | B19: Junio | C19: 2027 | D19: Posgrado | E19: Asíncrono | G19: Captura aquí el RI bimestral total. No es stock por B2/B3; es RI total del periodo.
A20: 2027 | B20: Junio | C20: 2027 | D20: Ejecutivo | E20: Síncrono | F20: 3798 | G20: Captura aquí el RI bimestral total. No es stock por B2/B3; es RI total del periodo.
A21: 2027 | B21: Junio | C21: 2027 | D21: Ejecutivo | E21: Asíncrono | G21: Captura aquí el RI bimestral total. No es stock por B2/B3; es RI total del periodo.
A22: 2027 | B22: Agosto | C22: 2027 | D22: Posgrado | E22: Síncrono | F22: 7563 | G22: Captura aquí el RI bimestral total. No es stock por B2/B3; es RI total del periodo.
A23: 2027 | B23: Agosto | C23: 2027 | D23: Posgrado | E23: Asíncrono | G23: Captura aquí el RI bimestral total. No es stock por B2/B3; es RI total del periodo.
A24: 2027 | B24: Agosto | C24: 2027 | D24: Ejecutivo | E24: Síncrono | F24: 4070 | G24: Captura aquí el RI bimestral total. No es stock por B2/B3; es RI total del periodo.
A25: 2027 | B25: Agosto | C25: 2027 | D25: Ejecutivo | E25: Asíncrono | G25: Captura aquí el RI bimestral total. No es stock por B2/B3; es RI total del periodo.
A26: 2027 | B26: Octubre | C26: 2027 | D26: Posgrado | E26: Síncrono | F26: 8762 | G26: Captura aquí el RI bimestral total. No es stock por B2/B3; es RI total del periodo.
A27: 2027 | B27: Octubre | C27: 2027 | D27: Posgrado | E27: Asíncrono | G27: Captura aquí el RI bimestral total. No es stock por B2/B3; es RI total del periodo.
A28: 2027 | B28: Octubre | C28: 2027 | D28: Ejecutivo | E28: Síncrono | F28: 4672 | G28: Captura aquí el RI bimestral total. No es stock por B2/B3; es RI total del periodo.
A29: 2027 | B29: Octubre | C29: 2027 | D29: Ejecutivo | E29: Asíncrono | G29: Captura aquí el RI bimestral total. No es stock por B2/B3; es RI total del periodo.
A30: 2027 | B30: Enero | C30: 2028 | D30: Posgrado | E30: Síncrono | F30: 9833 | G30: Captura aquí el RI bimestral total. No es stock por B2/B3; es RI total del periodo.
A31: 2027 | B31: Enero | C31: 2028 | D31: Posgrado | E31: Asíncrono | G31: Captura aquí el RI bimestral total. No es stock por B2/B3; es RI total del periodo.
A32: 2028 | B32: Enero | C32: 2028 | D32: Ejecutivo | E32: Síncrono | F32: 4949 | G32: Captura aquí el RI bimestral total. No es stock por B2/B3; es RI total del periodo.
A33: 2028 | B33: Enero | C33: 2028 | D33: Ejecutivo | E33: Asíncrono | G33: Captura aquí el RI bimestral total. No es stock por B2/B3; es RI total del periodo.
A34: 2027 | B34: Marzo | C34: 2028 | D34: Posgrado | E34: Síncrono | F34: 11303 | G34: Captura aquí el RI bimestral total. No es stock por B2/B3; es RI total del periodo.
A35: 2027 | B35: Marzo | C35: 2028 | D35: Posgrado | E35: Asíncrono | G35: Captura aquí el RI bimestral total. No es stock por B2/B3; es RI total del periodo.
A36: 2028 | B36: Marzo | C36: 2028 | D36: Ejecutivo | E36: Síncrono | F36: 5352 | G36: Captura aquí el RI bimestral total. No es stock por B2/B3; es RI total del periodo.
A37: 2028 | B37: Marzo | C37: 2028 | D37: Ejecutivo | E37: Asíncrono | G37: Captura aquí el RI bimestral total. No es stock por B2/B3; es RI total del periodo.
A38: 2027 | B38: Junio | C38: 2028 | D38: Posgrado | E38: Síncrono | F38: 12071 | G38: Captura aquí el RI bimestral total. No es stock por B2/B3; es RI total del periodo.
A39: 2027 | B39: Junio | C39: 2028 | D39: Posgrado | E39: Asíncrono | G39: Captura aquí el RI bimestral total. No es stock por B2/B3; es RI total del periodo.
A40: 2028 | B40: Junio | C40: 2028 | D40: Ejecutivo | E40: Síncrono | F40: 5847 | G40: Captura aquí el RI bimestral total. No es stock por B2/B3; es RI total del periodo.
A41: 2028 | B41: Junio | C41: 2028 | D41: Ejecutivo | E41: Asíncrono | G41: Captura aquí el RI bimestral total. No es stock por B2/B3; es RI total del periodo.
A42: 2028 | B42: Agosto | C42: 2028 | D42: Posgrado | E42: Síncrono | F42: 13052 | G42: Captura aquí el RI bimestral total. No es stock por B2/B3; es RI total del periodo.
A43: 2028 | B43: Agosto | C43: 2028 | D43: Posgrado | E43: Asíncrono | G43: Captura aquí el RI bimestral total. No es stock por B2/B3; es RI total del periodo.
A44: 2028 | B44: Agosto | C44: 2028 | D44: Ejecutivo | E44: Síncrono | F44: 6377 | G44: Captura aquí el RI bimestral total. No es stock por B2/B3; es RI total del periodo.
A45: 2028 | B45: Agosto | C45: 2028 | D45: Ejecutivo | E45: Asíncrono | G45: Captura aquí el RI bimestral total. No es stock por B2/B3; es RI total del periodo.
A46: 2028 | B46: Octubre | C46: 2028 | D46: Posgrado | E46: Síncrono | F46: 13294 | G46: Captura aquí el RI bimestral total. No es stock por B2/B3; es RI total del periodo.
A47: 2028 | B47: Octubre | C47: 2028 | D47: Posgrado | E47: Asíncrono | G47: Captura aquí el RI bimestral total. No es stock por B2/B3; es RI total del periodo.
A48: 2028 | B48: Octubre | C48: 2028 | D48: Ejecutivo | E48: Síncrono | F48: 6525 | G48: Captura aquí el RI bimestral total. No es stock por B2/B3; es RI total del periodo.
A49: 2028 | B49: Octubre | C49: 2028 | D49: Ejecutivo | E49: Asíncrono | G49: Captura aquí el RI bimestral total. No es stock por B2/B3; es RI total del periodo.
A50: 2028 | B50: Enero | C50: 2029 | D50: Posgrado | E50: Síncrono | F50: 13470 | G50: Captura aquí el RI bimestral total. No es stock por B2/B3; es RI total del periodo.
A51: 2028 | B51: Enero | C51: 2029 | D51: Posgrado | E51: Asíncrono | G51: Captura aquí el RI bimestral total. No es stock por B2/B3; es RI total del periodo.
A52: 2029 | B52: Enero | C52: 2029 | D52: Ejecutivo | E52: Síncrono | F52: 6633 | G52: Captura aquí el RI bimestral total. No es stock por B2/B3; es RI total del periodo.
A53: 2029 | B53: Enero | C53: 2029 | D53: Ejecutivo | E53: Asíncrono | G53: Captura aquí el RI bimestral total. No es stock por B2/B3; es RI total del periodo.
A54: 2028 | B54: Marzo | C54: 2029 | D54: Posgrado | E54: Síncrono | F54: 13844 | G54: Captura aquí el RI bimestral total. No es stock por B2/B3; es RI total del periodo.
A55: 2028 | B55: Marzo | C55: 2029 | D55: Posgrado | E55: Asíncrono | G55: Captura aquí el RI bimestral total. No es stock por B2/B3; es RI total del periodo.
A56: 2029 | B56: Marzo | C56: 2029 | D56: Ejecutivo | E56: Síncrono | F56: 7373 | G56: Captura aquí el RI bimestral total. No es stock por B2/B3; es RI total del periodo.
A57: 2029 | B57: Marzo | C57: 2029 | D57: Ejecutivo | E57: Asíncrono | G57: Captura aquí el RI bimestral total. No es stock por B2/B3; es RI total del periodo.
A58: 2028 | B58: Junio | C58: 2029 | D58: Posgrado | E58: Síncrono | F58: 14119 | G58: Captura aquí el RI bimestral total. No es stock por B2/B3; es RI total del periodo.
A59: 2028 | B59: Junio | C59: 2029 | D59: Posgrado | E59: Asíncrono | G59: Captura aquí el RI bimestral total. No es stock por B2/B3; es RI total del periodo.
A60: 2029 | B60: Junio | C60: 2029 | D60: Ejecutivo | E60: Síncrono | F60: 7521 | G60: Captura aquí el RI bimestral total. No es stock por B2/B3; es RI total del periodo.
A61: 2029 | B61: Junio | C61: 2029 | D61: Ejecutivo | E61: Asíncrono | G61: Captura aquí el RI bimestral total. No es stock por B2/B3; es RI total del periodo.
A62: 2029 | B62: Agosto | C62: 2029 | D62: Posgrado | E62: Síncrono | F62: 14902 | G62: Captura aquí el RI bimestral total. No es stock por B2/B3; es RI total del periodo.
A63: 2029 | B63: Agosto | C63: 2029 | D63: Posgrado | E63: Asíncrono | G63: Captura aquí el RI bimestral total. No es stock por B2/B3; es RI total del periodo.
A64: 2029 | B64: Agosto | C64: 2029 | D64: Ejecutivo | E64: Síncrono | F64: 7764 | G64: Captura aquí el RI bimestral total. No es stock por B2/B3; es RI total del periodo.
A65: 2029 | B65: Agosto | C65: 2029 | D65: Ejecutivo | E65: Asíncrono | G65: Captura aquí el RI bimestral total. No es stock por B2/B3; es RI total del periodo.
A66: 2029 | B66: Octubre | C66: 2029 | D66: Posgrado | E66: Síncrono | F66: 15196 | G66: Captura aquí el RI bimestral total. No es stock por B2/B3; es RI total del periodo.
A67: 2029 | B67: Octubre | C67: 2029 | D67: Posgrado | E67: Asíncrono | G67: Captura aquí el RI bimestral total. No es stock por B2/B3; es RI total del periodo.
A68: 2029 | B68: Octubre | C68: 2029 | D68: Ejecutivo | E68: Síncrono | F68: 8479 | G68: Captura aquí el RI bimestral total. No es stock por B2/B3; es RI total del periodo.
A69: 2029 | B69: Octubre | C69: 2029 | D69: Ejecutivo | E69: Asíncrono | G69: Captura aquí el RI bimestral total. No es stock por B2/B3; es RI total del periodo.
A70: 2030 | B70: Enero | C70: 2030 | D70: Posgrado | E70: Síncrono | F70: 14986 | G70: Captura aquí el RI bimestral total. No es stock por B2/B3; es RI total del periodo.
A71: 2030 | B71: Enero | C71: 2030 | D71: Posgrado | E71: Asíncrono | G71: Captura aquí el RI bimestral total. No es stock por B2/B3; es RI total del periodo.
A72: 2030 | B72: Enero | C72: 2030 | D72: Ejecutivo | E72: Síncrono | F72: 8122 | G72: Captura aquí el RI bimestral total. No es stock por B2/B3; es RI total del periodo.
A73: 2030 | B73: Enero | C73: 2030 | D73: Ejecutivo | E73: Asíncrono | G73: Captura aquí el RI bimestral total. No es stock por B2/B3; es RI total del periodo.
A74: 2030 | B74: Marzo | C74: 2030 | D74: Posgrado | E74: Síncrono | F74: 15496 | G74: Captura aquí el RI bimestral total. No es stock por B2/B3; es RI total del periodo.
A75: 2030 | B75: Marzo | C75: 2030 | D75: Posgrado | E75: Asíncrono | G75: Captura aquí el RI bimestral total. No es stock por B2/B3; es RI total del periodo.
A76: 2030 | B76: Marzo | C76: 2030 | D76: Ejecutivo | E76: Síncrono | F76: 9538 | G76: Captura aquí el RI bimestral total. No es stock por B2/B3; es RI total del periodo.
A77: 2030 | B77: Marzo | C77: 2030 | D77: Ejecutivo | E77: Asíncrono | G77: Captura aquí el RI bimestral total. No es stock por B2/B3; es RI total del periodo.
A78: 2030 | B78: Junio | C78: 2030 | D78: Posgrado | E78: Síncrono | F78: 15802 | G78: Captura aquí el RI bimestral total. No es stock por B2/B3; es RI total del periodo.
A79: 2030 | B79: Junio | C79: 2030 | D79: Posgrado | E79: Asíncrono | G79: Captura aquí el RI bimestral total. No es stock por B2/B3; es RI total del periodo.
A80: 2030 | B80: Junio | C80: 2030 | D80: Ejecutivo | E80: Síncrono | F80: 10052 | G80: Captura aquí el RI bimestral total. No es stock por B2/B3; es RI total del periodo.
A81: 2030 | B81: Junio | C81: 2030 | D81: Ejecutivo | E81: Asíncrono | G81: Captura aquí el RI bimestral total. No es stock por B2/B3; es RI total del periodo.

Sheet mt_tetra_historica_pos_ejec
A1: anio_calendario | B1: periodo | C1: nivel | D1: modalidad | E1: MT_tetra_historica
A2: 2026 | B2: Enero | C2: Posgrado | D2: Síncrono | E2: ...
A3: 2026 | B3: Mayo | C3: Posgrado | D3: Síncrono | E3: ...
A4: 2026 | B4: Septiembre | C4: Posgrado | D4: Síncrono | E4: 9820
A5: 2026 | B5: Enero | C5: Ejecutivo | D5: Síncrono | E5: ...
A6: 2026 | B6: Mayo | C6: Ejecutivo | D6: Síncrono | E6: ...
A7: 2026 | B7: Septiembre | C7: Ejecutivo | D7: Síncrono | E7: 6185
A8: 2027 | B8: Enero | C8: Posgrado | D8: Síncrono | E8: 7800
A9: 2027 | B9: Mayo | C9: Posgrado | D9: Síncrono | E9: 5810
A10: 2027 | B10: Septiembre | C10: Posgrado | D10: Síncrono | E10: 3800
A11: 2027 | B11: Enero | C11: Ejecutivo | D11: Síncrono | E11: 5709
A12: 2027 | B12: Mayo | C12: Ejecutivo | D12: Síncrono | E12: 5500
A13: 2027 | B13: Septiembre | C13: Ejecutivo | D13: Síncrono | E13: 5100
A14: 2028 | B14: Enero | C14: Posgrado | D14: Síncrono | E14: 1800
A15: 2028 | B15: Mayo | C15: Posgrado | D15: Síncrono | E15: 1000
A16: 2028 | B16: Septiembre | C16: Posgrado | D16: Síncrono
A17: 2028 | B17: Enero | C17: Ejecutivo | D17: Síncrono | E17: 4756
A18: 2028 | B18: Mayo | C18: Ejecutivo | D18: Síncrono | E18: 4225
A19: 2028 | B19: Septiembre | C19: Ejecutivo | D19: Síncrono | E19: 3976
A20: 2029 | B20: Enero | C20: Posgrado | D20: Síncrono
A21: 2029 | B21: Mayo | C21: Posgrado | D21: Síncrono
A22: 2029 | B22: Septiembre | C22: Posgrado | D22: Síncrono
A23: 2029 | B23: Enero | C23: Ejecutivo | D23: Síncrono | E23: 3745
A24: 2029 | B24: Mayo | C24: Ejecutivo | D24: Síncrono | E24: 3500
A25: 2029 | B25: Septiembre | C25: Ejecutivo | D25: Síncrono | E25: 2900
A26: 2030 | B26: Enero | C26: Ejecutivo | D26: Sincrono | E26: 2056
A27: 2030 | B27: Mayo | C27: Ejecutivo | D27: Sincrono | E27: 1656
A28: 2030 | B28: Septiembre | C28: Ejecutivo | D28: Sincrono | E28: 1045
A29: 2031 | B29: Enero | C29: Ejecutivo | D29: Sincrono | E29: 645

Sheet calculo_tetra_pmp_pos_ejec
A1: anio_academico | B1: periodo | C1: anio_calendario | D1: nivel | E1: modalidad | F1: NI | G1: RI_bimestral | H1: MT_PMP | I1: MT_tetra_calculada | J1: validacion
A2: 2026 | B2: Agosto | C2: 2026 | D2: Posgrado | E2: Síncrono | F2: =SUMIFS(ni_bimestral_pos_ejec!$F:$F,ni_bimestral_pos_ejec!$C:$C,$C2,ni_bimestral_pos_ejec!$B:$B,$B2,ni_bimestral_pos_ejec!$D:$D,$D2,ni_bimestral_pos_ejec!$E:$E,$E2) -> 1866 | G2: =SUMIFS(ri_bimestral_pos_ejec!$F:$F,ri_bimestral_pos_ejec!$C:$C,$C2,ri_bimestral_pos_ejec!$B:$B,$B2,ri_bimestral_pos_ejec!$D:$D,$D2,ri_bimestral_pos_ejec!$E:$E,$E2) -> 0 | H2: =SUMIFS(pmp_mt_pos_ejec!$E:$E,pmp_mt_pos_ejec!$A:$A,$C2,pmp_mt_pos_ejec!$B:$B,$B2,pmp_mt_pos_ejec!$C:$C,$D2) -> 14561 | I2: =IF(H2=0,"",MAX(0,H2-F2-G2)) -> 12695 | J2: =IF(H2=0,"Sin PMP",IF(ABS((F2+G2+I2)-H2)<1,"OK","Revisar")) -> OK
A3: 2026 | B3: Agosto | C3: 2026 | D3: Posgrado | E3: Asíncrono | F3: =SUMIFS(ni_bimestral_pos_ejec!$F:$F,ni_bimestral_pos_ejec!$C:$C,$C3,ni_bimestral_pos_ejec!$B:$B,$B3,ni_bimestral_pos_ejec!$D:$D,$D3,ni_bimestral_pos_ejec!$E:$E,$E3) -> 0 | G3: =SUMIFS(ri_bimestral_pos_ejec!$F:$F,ri_bimestral_pos_ejec!$C:$C,$C3,ri_bimestral_pos_ejec!$B:$B,$B3,ri_bimestral_pos_ejec!$D:$D,$D3,ri_bimestral_pos_ejec!$E:$E,$E3) -> 0 | H3: =SUMIFS(pmp_mt_pos_ejec!$E:$E,pmp_mt_pos_ejec!$A:$A,$C3,pmp_mt_pos_ejec!$B:$B,$B3,pmp_mt_pos_ejec!$C:$C,$D3) -> 14561 | I3: =IF(H3=0,"",MAX(0,H3-F3-G3)) -> 14561 | J3: =IF(H3=0,"Sin PMP",IF(ABS((F3+G3+I3)-H3)<1,"OK","Revisar")) -> OK
A4: 2026 | B4: Agosto | C4: 2026 | D4: Ejecutivo | E4: Síncrono | F4: =SUMIFS(ni_bimestral_pos_ejec!$F:$F,ni_bimestral_pos_ejec!$C:$C,$C4,ni_bimestral_pos_ejec!$B:$B,$B4,ni_bimestral_pos_ejec!$D:$D,$D4,ni_bimestral_pos_ejec!$E:$E,$E4) -> 952 | G4: =SUMIFS(ri_bimestral_pos_ejec!$F:$F,ri_bimestral_pos_ejec!$C:$C,$C4,ri_bimestral_pos_ejec!$B:$B,$B4,ri_bimestral_pos_ejec!$D:$D,$D4,ri_bimestral_pos_ejec!$E:$E,$E4) -> 2023 | H4: =SUMIFS(pmp_mt_pos_ejec!$E:$E,pmp_mt_pos_ejec!$A:$A,$C4,pmp_mt_pos_ejec!$B:$B,$B4,pmp_mt_pos_ejec!$C:$C,$D4) -> 10207 | I4: =IF(H4=0,"",MAX(0,H4-F4-G4)) -> 7232 | J4: =IF(H4=0,"Sin PMP",IF(ABS((F4+G4+I4)-H4)<1,"OK","Revisar")) -> OK
A5: 2026 | B5: Agosto | C5: 2026 | D5: Ejecutivo | E5: Asíncrono | F5: =SUMIFS(ni_bimestral_pos_ejec!$F:$F,ni_bimestral_pos_ejec!$C:$C,$C5,ni_bimestral_pos_ejec!$B:$B,$B5,ni_bimestral_pos_ejec!$D:$D,$D5,ni_bimestral_pos_ejec!$E:$E,$E5) -> 0 | G5: =SUMIFS(ri_bimestral_pos_ejec!$F:$F,ri_bimestral_pos_ejec!$C:$C,$C5,ri_bimestral_pos_ejec!$B:$B,$B5,ri_bimestral_pos_ejec!$D:$D,$D5,ri_bimestral_pos_ejec!$E:$E,$E5) -> 0 | H5: =SUMIFS(pmp_mt_pos_ejec!$E:$E,pmp_mt_pos_ejec!$A:$A,$C5,pmp_mt_pos_ejec!$B:$B,$B5,pmp_mt_pos_ejec!$C:$C,$D5) -> 10207 | I5: =IF(H5=0,"",MAX(0,H5-F5-G5)) -> 10207 | J5: =IF(H5=0,"Sin PMP",IF(ABS((F5+G5+I5)-H5)<1,"OK","Revisar")) -> OK
A6: 2026 | B6: Octubre | C6: 2026 | D6: Posgrado | E6: Síncrono | F6: =SUMIFS(ni_bimestral_pos_ejec!$F:$F,ni_bimestral_pos_ejec!$C:$C,$C6,ni_bimestral_pos_ejec!$B:$B,$B6,ni_bimestral_pos_ejec!$D:$D,$D6,ni_bimestral_pos_ejec!$E:$E,$E6) -> 1660 | G6: =SUMIFS(ri_bimestral_pos_ejec!$F:$F,ri_bimestral_pos_ejec!$C:$C,$C6,ri_bimestral_pos_ejec!$B:$B,$B6,ri_bimestral_pos_ejec!$D:$D,$D6,ri_bimestral_pos_ejec!$E:$E,$E6) -> 1697 | H6: =SUMIFS(pmp_mt_pos_ejec!$E:$E,pmp_mt_pos_ejec!$A:$A,$C6,pmp_mt_pos_ejec!$B:$B,$B6,pmp_mt_pos_ejec!$C:$C,$D6) -> 0 | I6: =IF(H6=0,"",MAX(0,H6-F6-G6)) | J6: =IF(H6=0,"Sin PMP",IF(ABS((F6+G6+I6)-H6)<1,"OK","Revisar")) -> Sin PMP
A7: 2026 | B7: Octubre | C7: 2026 | D7: Posgrado | E7: Asíncrono | F7: =SUMIFS(ni_bimestral_pos_ejec!$F:$F,ni_bimestral_pos_ejec!$C:$C,$C7,ni_bimestral_pos_ejec!$B:$B,$B7,ni_bimestral_pos_ejec!$D:$D,$D7,ni_bimestral_pos_ejec!$E:$E,$E7) -> 0 | G7: =SUMIFS(ri_bimestral_pos_ejec!$F:$F,ri_bimestral_pos_ejec!$C:$C,$C7,ri_bimestral_pos_ejec!$B:$B,$B7,ri_bimestral_pos_ejec!$D:$D,$D7,ri_bimestral_pos_ejec!$E:$E,$E7) -> 0 | H7: =SUMIFS(pmp_mt_pos_ejec!$E:$E,pmp_mt_pos_ejec!$A:$A,$C7,pmp_mt_pos_ejec!$B:$B,$B7,pmp_mt_pos_ejec!$C:$C,$D7) -> 0 | I7: =IF(H7=0,"",MAX(0,H7-F7-G7)) | J7: =IF(H7=0,"Sin PMP",IF(ABS((F7+G7+I7)-H7)<1,"OK","Revisar")) -> Sin PMP
A8: 2026 | B8: Octubre | C8: 2026 | D8: Ejecutivo | E8: Síncrono | F8: =SUMIFS(ni_bimestral_pos_ejec!$F:$F,ni_bimestral_pos_ejec!$C:$C,$C8,ni_bimestral_pos_ejec!$B:$B,$B8,ni_bimestral_pos_ejec!$D:$D,$D8,ni_bimestral_pos_ejec!$E:$E,$E8) -> 867 | G8: =SUMIFS(ri_bimestral_pos_ejec!$F:$F,ri_bimestral_pos_ejec!$C:$C,$C8,ri_bimestral_pos_ejec!$B:$B,$B8,ri_bimestral_pos_ejec!$D:$D,$D8,ri_bimestral_pos_ejec!$E:$E,$E8) -> 2702 | H8: =SUMIFS(pmp_mt_pos_ejec!$E:$E,pmp_mt_pos_ejec!$A:$A,$C8,pmp_mt_pos_ejec!$B:$B,$B8,pmp_mt_pos_ejec!$C:$C,$D8) -> 0 | I8: =IF(H8=0,"",MAX(0,H8-F8-G8)) | J8: =IF(H8=0,"Sin PMP",IF(ABS((F8+G8+I8)-H8)<1,"OK","Revisar")) -> Sin PMP
A9: 2026 | B9: Octubre | C9: 2026 | D9: Ejecutivo | E9: Asíncrono | F9: =SUMIFS(ni_bimestral_pos_ejec!$F:$F,ni_bimestral_pos_ejec!$C:$C,$C9,ni_bimestral_pos_ejec!$B:$B,$B9,ni_bimestral_pos_ejec!$D:$D,$D9,ni_bimestral_pos_ejec!$E:$E,$E9) -> 0 | G9: =SUMIFS(ri_bimestral_pos_ejec!$F:$F,ri_bimestral_pos_ejec!$C:$C,$C9,ri_bimestral_pos_ejec!$B:$B,$B9,ri_bimestral_pos_ejec!$D:$D,$D9,ri_bimestral_pos_ejec!$E:$E,$E9) -> 0 | H9: =SUMIFS(pmp_mt_pos_ejec!$E:$E,pmp_mt_pos_ejec!$A:$A,$C9,pmp_mt_pos_ejec!$B:$B,$B9,pmp_mt_pos_ejec!$C:$C,$D9) -> 0 | I9: =IF(H9=0,"",MAX(0,H9-F9-G9)) | J9: =IF(H9=0,"Sin PMP",IF(ABS((F9+G9+I9)-H9)<1,"OK","Revisar")) -> Sin PMP
A10: 2026 | B10: Enero | C10: 2027 | D10: Posgrado | E10: Síncrono | F10: =SUMIFS(ni_bimestral_pos_ejec!$F:$F,ni_bimestral_pos_ejec!$C:$C,$C10,ni_bimestral_pos_ejec!$B:$B,$B10,ni_bimestral_pos_ejec!$D:$D,$D10,ni_bimestral_pos_ejec!$E:$E,$E10) -> 2062 | G10: =SUMIFS(ri_bimestral_pos_ejec!$F:$F,ri_bimestral_pos_ejec!$C:$C,$C10,ri_bimestral_pos_ejec!$B:$B,$B10,ri_bimestral_pos_ejec!$D:$D,$D10,ri_bimestral_pos_ejec!$E:$E,$E10) -> 3107 | H10: =SUMIFS(pmp_mt_pos_ejec!$E:$E,pmp_mt_pos_ejec!$A:$A,$C10,pmp_mt_pos_ejec!$B:$B,$B10,pmp_mt_pos_ejec!$C:$C,$D10) -> 0 | I10: =IF(H10=0,"",MAX(0,H10-F10-G10)) | J10: =IF(H10=0,"Sin PMP",IF(ABS((F10+G10+I10)-H10)<1,"OK","Revisar")) -> Sin PMP
A11: 2026 | B11: Enero | C11: 2027 | D11: Posgrado | E11: Asíncrono | F11: =SUMIFS(ni_bimestral_pos_ejec!$F:$F,ni_bimestral_pos_ejec!$C:$C,$C11,ni_bimestral_pos_ejec!$B:$B,$B11,ni_bimestral_pos_ejec!$D:$D,$D11,ni_bimestral_pos_ejec!$E:$E,$E11) -> 0 | G11: =SUMIFS(ri_bimestral_pos_ejec!$F:$F,ri_bimestral_pos_ejec!$C:$C,$C11,ri_bimestral_pos_ejec!$B:$B,$B11,ri_bimestral_pos_ejec!$D:$D,$D11,ri_bimestral_pos_ejec!$E:$E,$E11) -> 0 | H11: =SUMIFS(pmp_mt_pos_ejec!$E:$E,pmp_mt_pos_ejec!$A:$A,$C11,pmp_mt_pos_ejec!$B:$B,$B11,pmp_mt_pos_ejec!$C:$C,$D11) -> 0 | I11: =IF(H11=0,"",MAX(0,H11-F11-G11)) | J11: =IF(H11=0,"Sin PMP",IF(ABS((F11+G11+I11)-H11)<1,"OK","Revisar")) -> Sin PMP
A12: 2026 | B12: Enero | C12: 2027 | D12: Ejecutivo | E12: Síncrono | F12: =SUMIFS(ni_bimestral_pos_ejec!$F:$F,ni_bimestral_pos_ejec!$C:$C,$C12,ni_bimestral_pos_ejec!$B:$B,$B12,ni_bimestral_pos_ejec!$D:$D,$D12,ni_bimestral_pos_ejec!$E:$E,$E12) -> 1020 | G12: =SUMIFS(ri_bimestral_pos_ejec!$F:$F,ri_bimestral_pos_ejec!$C:$C,$C12,ri_bimestral_pos_ejec!$B:$B,$B12,ri_bimestral_pos_ejec!$D:$D,$D12,ri_bimestral_pos_ejec!$E:$E,$E12) -> 3104 | H12: =SUMIFS(pmp_mt_pos_ejec!$E:$E,pmp_mt_pos_ejec!$A:$A,$C12,pmp_mt_pos_ejec!$B:$B,$B12,pmp_mt_pos_ejec!$C:$C,$D12) -> 0 | I12: =IF(H12=0,"",MAX(0,H12-F12-G12)) | J12: =IF(H12=0,"Sin PMP",IF(ABS((F12+G12+I12)-H12)<1,"OK","Revisar")) -> Sin PMP
A13: 2026 | B13: Enero | C13: 2027 | D13: Ejecutivo | E13: Asíncrono | F13: =SUMIFS(ni_bimestral_pos_ejec!$F:$F,ni_bimestral_pos_ejec!$C:$C,$C13,ni_bimestral_pos_ejec!$B:$B,$B13,ni_bimestral_pos_ejec!$D:$D,$D13,ni_bimestral_pos_ejec!$E:$E,$E13) -> 0 | G13: =SUMIFS(ri_bimestral_pos_ejec!$F:$F,ri_bimestral_pos_ejec!$C:$C,$C13,ri_bimestral_pos_ejec!$B:$B,$B13,ri_bimestral_pos_ejec!$D:$D,$D13,ri_bimestral_pos_ejec!$E:$E,$E13) -> 0 | H13: =SUMIFS(pmp_mt_pos_ejec!$E:$E,pmp_mt_pos_ejec!$A:$A,$C13,pmp_mt_pos_ejec!$B:$B,$B13,pmp_mt_pos_ejec!$C:$C,$D13) -> 0 | I13: =IF(H13=0,"",MAX(0,H13-F13-G13)) | J13: =IF(H13=0,"Sin PMP",IF(ABS((F13+G13+I13)-H13)<1,"OK","Revisar")) -> Sin PMP
... A81: 2029 | B81: Junio | C81: 2030 | D81: Ejecutivo | E81: Asíncrono | F81: =SUMIFS(ni_bimestral_pos_ejec!$F:$F,ni_bimestral_pos_ejec!$C:$C,$C81,ni_bimestral_pos_ejec!$B:$B,$B81,ni_bimestral_pos_ejec!$D:$D,$D81,ni_bimestral_pos_ejec!$E:$E,$E81) -> 49 | G81: =SUMIFS(ri_bimestral_pos_ejec!$F:$F,ri_bimestral_pos_ejec!$C:$C,$C81,ri_bimestral_pos_ejec!$B:$B,$B81,ri_bimestral_pos_ejec!$D:$D,$D81,ri_bimestral_pos_ejec!$E:$E,$E81) -> 0 | H81: =SUMIFS(pmp_mt_pos_ejec!$E:$E,pmp_mt_pos_ejec!$A:$A,$C81,pmp_mt_pos_ejec!$B:$B,$B81,pmp_mt_pos_ejec!$C:$C,$D81) -> 0 | I81: =IF(H81=0,"",MAX(0,H81-F81-G81)) | J81: =IF(H81=0,"Sin PMP",IF(ABS((F81+G81+I81)-H81)<1,"OK","Revisar")) -> Sin PMP

Sheet INSTRUCCIONES_captura_PMP_RI
A1: Qué capturar | B1: Dónde capturarlo
A2: NI bimestral 2026-2029 | B2: Hoja ni_bimestral_pos_ejec, columna NI.
A3: RI bimestral 2026-2029 | B3: Hoja ri_bimestral_pos_ejec, columna RI_bimestral.
A4: MT PMP 2026-2029 | B4: Hoja pmp_mt_pos_ejec, columna mt_pmp.
A5: Tetra faltante | B5: No la captures manualmente si no la tienes; se calcula en calculo_tetra_pmp_pos_ejec.
A6: Fórmula | B6: MT_tetra_calculada = MT_PMP - NI - RI_bimestral.
A7: Validación | B7: En calculo_tetra_pmp_pos_ejec, la columna validacion debe decir OK cuando haya PMP.
A8: Importante | B8: Para que cruce bien, usa el mismo anio_calendario, periodo, nivel y modalidad en las tres hojas.
A9: Modalidad | B9: Puedes usar Síncrono / Asíncrono. Si solo tienes total por nivel, pon modalidad Total en pmp_mt_pos_ejec y dime para ajustar el simulador después.

Sheet LEEME_v143_captura
A1: Tema | B1: Descripción
A2: Base | B2: Modelo v142.
A3: Nueva hoja | B3: ri_bimestral_pos_ejec para capturar RI bimestral total 2026-2029.
A4: Nueva hoja | B4: calculo_tetra_pmp_pos_ejec para calcular tetra faltante contra PMP.
A5: Cálculo | B5: MT_tetra_calculada = MT_PMP - NI - RI_bimestral.
A6: Instrucciones | B6: Ver hoja INSTRUCCIONES_captura_PMP_RI.
A7: Uso | B7: Este es el Excel recomendado para que captures NI, RI bimestral y PMP.

Sheet LEEME_v145
A1: Tema | B1: Descripción
A2: Corrección NI | B2: El simulador v145 lee NI desde ni_bimestral_pos_ejec.
A3: Llave de lectura | B3: anio_calendario + periodo + nivel + modalidad.
A4: Año académico | B4: Ya no se usa como llave principal para los NI del caso base 2026-2029.
A5: Caso base | B5: La tabla del caso base usa esos NI para 2026-2029.
A6: Proyección 2030+ | B6: Desde Enero 2030 se conserva tasas + crecimiento 3%.
A7: Descarga Excel | B7: Se agrega hoja NI_bimestral_fuente en la exportación del simulador.
A8: Cálculos | B8: No se cambiaron tasas, Internacional ni Espacio Connect.

Sheet LEEME_v146
A1: Tema | B1: Descripción
A2: Corrección | B2: Se unificó la fórmula de MT total institucional 2045.
A3: Campus | B3: La tarjeta de Campus usa la misma suma que Posgrado/Ejecutivo.
A4: Posgrado/Ejecutivo | B4: La tarjeta MT Total institución 2045 usa la misma suma que Campus.
A5: Fórmula | B5: Preparatoria + Profesional + Posgrado/Ejecutivo del escenario + Internacional solo si el checkbox está activo.
A6: Exportación | B6: Se agregó hoja Resumen_institucional en la descarga de Excel del simulador.
A7: Sin cambios | B7: No se cambiaron tasas, NI, RI, PMP, Internacional ni Espacio Connect.

Sheet LEEME_v147
A1: Tema | B1: Descripción
A2: Default Posgrado/Ejecutivo | B2: Se cambió a Manual por bloques para no forzar 43,000.
A3: Caso base | B3: El default queda con el caso base/manual actual hacia 2045.
A4: Resolver meta | B4: Sigue disponible; si el usuario lo elige manualmente, entonces sí fuerza la meta.
A5: Tablas por nivel | B5: Posgrado y Ejecutivo muestran solo Agosto, completas hasta Agosto 2045.
A6: Bimestres intermedios | B6: Se siguen calculando internamente; solo se ocultan en la vista.
A7: Exportación | B7: El Excel descargado exporta Posgrado_Agosto_2045 y Ejecutivo_Agosto_2045.
A8: Sin cambios | B8: No se cambiaron NI, RI, PMP, tasas, Internacional ni Espacio Connect.

Sheet LEEME_v150
A1: Tema | B1: Descripción
A2: Corrección principal | B2: El escenario editable ya no manda ceros a NI Asíncrono desde 2036.
A3: NI Asíncrono | B3: Desde 2030 crece desde los NI Asíncronos capturados en ni_bimestral_pos_ejec.
A4: NI Síncrono | B4: Si el reparto es 100% Asíncrono, Síncrono deja de recibir NI y sus RI bajan con tasas.
A5: RI por modalidad | B5: RI Síncrono y RI Asíncrono se calculan por cohortes separadas y tasas de cada modalidad.
A6: RI capturado | B6: Si ri_bimestral_pos_ejec tiene valores 2026-2029, se usan para ajustar el stock interno.
A7: Reparto default | B7: reparto_ni_anual_pos_ejec queda 100% Asíncrono de 2030 a 2045.
A8: PMP | B8: pmp_mt_pos_ejec se usa para cuadrar 2026-2029 con MT tetra histórica.
A9: Vista | B9: Tablas Posgrado/Ejecutivo muestran Agosto 2026-2045 con NI/RI Síncrono y Asíncrono.
A10: Sin cambios | B10: Se conserva Internacional, Espacio Connect y el botón de Excel.

Sheet LEEME_v152
A1: Tema | B1: Descripción
A2: Base | B2: Se tomó como base la v150, no la v151.
A3: NI Asíncrono 2030+ | B3: Crece desde su propia base asíncrona por periodo, por ejemplo de ~245 a ~267 si la tasa así lo da.
A4: No cambio a total | B4: No se pasa el NI total síncrono completo a Asíncrono.
A5: 5 periodos internos | B5: Agosto, Octubre, Enero, Marzo y Junio alimentan los RI aunque la vista muestre solo Agosto.
A6: RI | B6: El RI se calcula por cohortes internas y tasas por modalidad.
A7: Histórico previo | B7: Los NIs anteriores a 2026 se procesan como historia interna cuando existen para alimentar RI futuro.
A8: Vista | B8: Las tablas de nivel agregan NI anual de 5 periodos para validar que sí entran los periodos internos.
A9: Exportación | B9: La descarga del simulador agrega Detalle_periodos_interno con todos los periodos calculados.
A10: Sin cambios | B10: No se cambiaron PMP, tasas, Internacional, Espacio Connect ni el botón de Excel.
